Workbook

Sheet Cover
B2: Does M&A Create Value? Long-Run Performance of US Acquirers
B3: Alessandro Radice · data to 31 March 2025 · SEC EDGAR, DoltHub, Kenneth French data library
B5: Sheet | D5: What it holds
B6: Inputs | D6: Horizon, benchmark and filters that drive every live result
B7: Deals | D7: 786 acquisitions completed 2012-2021, one row each, with the BHAR as a live formula
B8: Returns | D8: Monthly returns of each acquirer and of its size/book-to-market benchmark, months 1 to 60 after completion
B9: Summary | D9: Mean, median, share positive and t-statistic, overall and by payment method, from the Deals sheet
B10: Calendar time | D10: Monthly portfolio of recent acquirers and its alpha against the Fama-French factors (LINEST)
B11: Operating | D11: Industry-adjusted operating return on assets before and after, the regression of post on pre, goodwill impairments
B12: Checks | D12: Every headline number recomputed in Excel and compared with the Python engine
B14: Colour code: blue = input, black = formula, green = link to another sheet. Educational project, not investment advice.
B16: Headline results (live)
B17: Mean 36-month BHAR | C17: =Summary!D9 -> -0.12392209
B18: Median 36-month BHAR | C18: =Summary!E9 -> -0.21343492
B19: FF5 + momentum alpha, annualized | C19: ='Calendar time'!P10 -> -0.022410138
B20: Checks | C20: =Checks!F16 -> OK

Sheet Inputs
B2: Inputs
B3: Change the blue cells; every sheet recalculates
B5: Input | C5: Value | D5: Notes
B6: Horizon (months after completion) | C6: 36 | D6: 12, 24, 36 or 60. 60 months only for deals completed by March 2020
B7: Benchmark (1 = value-weighted, 2 = equal-weighted) | C7: 1 | D7: Fama-French 25 portfolios formed on size and book-to-market
B8: Minimum deal size (% of acquirer market value) | C8: 0.1 | D8: The sample is built at 10%; raise it to study larger deals
B9: Payment method filter | C9: All | D9: All, Cash, Mixed or Stock-heavy
B10: Completion year from | C10: 2012
B11: Completion year to | C11: 2021
B13: Definitions
B14: BHAR = (1+r1)(1+r2)...(1+rH) - (1+b1)(1+b2)...(1+bH): the buy-and-hold return of the acquirer minus that of its benchmark portfolio.
B15: Month 1 is the first full month after the month of completion (the 8-K Item 2.01 filing).
B16: If the acquirer stops trading (acquired, delisted), the remaining months earn the benchmark: the BHAR is frozen, not dropped.
B17: Payment: Cash = stock under 5% of the price paid; Stock-heavy = 50% or more; Mixed in between (XBRL cash-flow and equity statements).
B18: Deal size = deal value / acquirer market value at the end of the month before completion.

Sheet Returns
B2: Returns
B3: Monthly total returns; acquirer after delisting = benchmark; blank after March 2025
D5: Acquirer | BM5: Benchmark, value-weighted | DV5: Benchmark, equal-weighted
B6: Deal | C6: Traded in month 1 | D6: 1 | E6: 2 | F6: 3 | G6: 4 | H6: 5 | I6: 6 | J6: 7 | K6: 8 | L6: 9 | M6: 10 | N6: 11 | O6: 12 | P6: 13 | Q6: 14 | R6: 15 | S6: 16 | T6: 17 | U6: 18 | V6: 19 | W6: 20 | X6: 21 | Y6: 22 | Z6: 23 | AA6: 24 | AB6: 25 | AC6: 26 | AD6: 27 | AE6: 28 | AF6: 29 | AG6: 30 | AH6: 31 | AI6: 32 | AJ6: 33 | AK6: 34 | AL6: 35 | AM6: 36 | AN6: 37 | AO6: 38 | AP6: 39 | AQ6: 40 | AR6: 41 | AS6: 42 | AT6: 43 | AU6: 44 | AV6: 45 | AW6: 46 | AX6: 47 | AY6: 48 | AZ6: 49 | BA6: 50 | BB6: 51 | BC6: 52 | BD6: 53 | BE6: 54 | BF6: 55 | BG6: 56 | BH6: 57 | BI6: 58 | BJ6: 59 | BK6: 60 | BM6: 1 | BN6: 2 | BO6: 3 | BP6: 4 | BQ6: 5 | BR6: 6 | BS6: 7 | BT6: 8 | BU6: 9 | BV6: 10 | BW6: 11 | BX6: 12 | BY6: 13 | BZ6: 14 | CA6: 15 | CB6: 16 | CC6: 17 | CD6: 18 | CE6: 19 | CF6: 20 | CG6: 21 | CH6: 22 | CI6: 23 | CJ6: 24 | CK6: 25 | CL6: 26 | CM6: 27 | CN6: 28 | CO6: 29 | CP6: 30 | CQ6: 31 | CR6: 32 | CS6: 33 | CT6: 34 | CU6: 35 | CV6: 36 | CW6: 37 | CX6: 38 | CY6: 39 | CZ6: 40 | DA6: 41 | DB6: 42 | DC6: 43 | DD6: 44 | DE6: 45 | DF6: 46 | DG6: 47 | DH6: 48 | DI6: 49 | DJ6: 50 | DK6: 51 | DL6: 52 | DM6: 53 | DN6: 54 | DO6: 55 | DP6: 56 | DQ6: 57 | DR6: 58 | DS6: 59 | DT6: 60 | DV6: 1 | DW6: 2 | DX6: 3 | DY6: 4 | DZ6: 5 | EA6: 6 | EB6: 7 | EC6: 8 | ED6: 9 | EE6: 10 | EF6: 11 | EG6: 12 | EH6: 13 | EI6: 14 | EJ6: 15 | EK6: 16 | EL6: 17 | EM6: 18 | EN6: 19 | EO6: 20 | EP6: 21 | EQ6: 22 | ER6: 23 | ES6: 24 | ET6: 25 | EU6: 26 | EV6: 27 | EW6: 28 | EX6: 29 | EY6: 30 | EZ6: 31 | FA6: 32 | FB6: 33 | FC6: 34 | FD6: 35 | FE6: 36 | FF6: 37 | FG6: 38 | FH6: 39 | FI6: 40 | FJ6: 41 | FK6: 42 | FL6: 43 | FM6: 44 | FN6: 45 | FO6: 46 | FP6: 47 | FQ6: 48 | FR6: 49 | FS6: 50 | FT6: 51 | FU6: 52 | FV6: 53 | FW6: 54 | FX6: 55 | FY6: 56 | FZ6: 57 | GA6: 58 | GB6: 59 | GC6: 60
B7: =Deals!B7 -> Cabot Corp | C7: 1 | D7: 0.119061 | E7: 0.053567 | F7: 0.010544 | G7: -0.12358 | H7: 0.07672 | I7: -0.041769 | J7: -0.106923 | K7: 0.049957 | L7: -0.022149 | M7: 0.055089 | N7: 0.054598 | O7: -0.059311 | P7: -0.017366 | Q7: -0.070147 | R7: 0.098246 | S7: 0.089989 | T7: -0.085979 | U7: 0.096205 | V7: -0.02511 | W7: 0.068017 | X7: 0.091314 | Y7: 0.043767 | Z7: 0.056526 | AA7: -0.053113 | AB7: 0.11239 | AC7: 0.090876 | AD7: -0.021334 | AE7: -0.021626 | AF7: 0.025464 | AG7: -0.096568 | AH7: 0.045619 | AI7: -0.073202 | AJ7: -0.085484 | AK7: -0.072152 | AL7: 0.018106 | AM7: -0.03306 | AN7: 0.0639 | AO7: -0.00266 | AP7: -0.050222 | AQ7: -0.029715 | AR7: -0.100796 | AS7: -0.056584 | AT7: -0.037237 | AU7: -0.068202 | AV7: 0.138783 | AW7: 0.211464 | AX7: -0.061093 | AY7: -0.013209 | AZ7: 0.103867 | BA7: 0.085336 | BB7: 0.009518 | BC7: -0.063128 | BD7: -0.001094 | BE7: 0.06636 | BF7: 0.02403 | BG7: 0.051143 | BH7: -0.005152 | BI7: -0.023207 | BJ7: -0.007658 | BK7: 0.095568 | BM7: 0.038859 | BN7: 0.017779 | BO7: -0.009457 | BP7: -0.061153 | BQ7: 0.023912 | BR7: 0.004514 | BS7: 0.042119 | BT7: 0.031368 | BU7: 0.010094 | BV7: 0.020912 | BW7: 0.028549 | BX7: 0.071309 | BY7: 0.026138 | BZ7: 0.036034 | CA7: -0.008356 | CB7: 0.050238 | CC7: -0.007612 | CD7: 0.07738 | CE7: -0.046876 | CF7: 0.055928 | CG7: 0.042349 | CH7: 0.025847 | CI7: 0.036152 | CJ7: -0.026369 | CK7: 0.069644 | CL7: 0.013672 | CM7: -0.014688 | CN7: 0.00594 | CO7: 0.04965 | CP7: -0.064442 | CQ7: 0.055168 | CR7: -0.066219 | CS7: 0.04088 | CT7: 0.001903 | CU7: 0.01593 | CV7: -0.046629 | CW7: 0.060563 | CX7: 0.011549 | CY7: -0.01011 | CZ7: 0.020129 | DA7: -0.019694 | DB7: -0.035205 | DC7: -0.050275 | DD7: -0.05851 | DE7: 0.049146 | DF7: 0.029941 | DG7: -0.057563 | DH7: -0.064508 | DI7: 0.009635 | DJ7: 0.103282 | DK7: 0.033338 | DL7: 0.009363 | DM7: -0.008015 | DN7: 0.041571 | DO7: 0.021929 | DP7: 0.013879 | DQ7: -0.028352 | DR7: 0.132419 | DS7: 0.021499 | DT7: -0.001631 | DV7: 0.041584 | DW7: 0.019052 | DX7: -0.012578 | DY7: -0.063155 | DZ7: 0.023735 | EA7: 0.001745 | EB7: 0.041711 | EC7: 0.029139 | ED7: 0.007073 | EE7: 0.018115 | EF7: 0.035914 | EG7: 0.069168 | EH7: 0.021522 | EI7: 0.039946 | EJ7: 0.00271 | EK7: 0.046562 | EL7: -0.007702 | EM7: 0.077152 | EN7: -0.049581 | EO7: 0.056228 | EP7: 0.041576 | EQ7: 0.0322 | ER7: 0.034934 | ES7: -0.02792 | ET7: 0.065997 | EU7: 0.014204 | EV7: -0.018209 | EW7: 0.006657 | EX7: 0.045963 | EY7: -0.066784 | EZ7: 0.054171 | FA7: -0.069202 | FB7: 0.042942 | FC7: -0.005519 | FD7: 0.015904 | FE7: -0.053487 | FF7: 0.071358 | FG7: 0.005373 | FH7: 0.001698 | FI7: 0.010095 | FJ7: -0.022698 | FK7: -0.036976 | FL7: -0.052086 | FM7: -0.066209 | FN7: 0.061982 | FO7: 0.031808 | FP7: -0.056919 | FQ7: -0.071494 | FR7: 0.01819 | FS7: 0.120043 | FT7: 0.046792 | FU7: 0.007433 | FV7: -0.009751 | FW7: 0.045997 | FX7: 0.027097 | FY7: 0.016254 | FZ7: -0.028065 | GA7: 0.135358 | GB7: 0.023606 | GC7: -0.001285
B8: =Deals!B8 -> Worthington Enterprises, Inc. | C8: 1 | D8: -0.08365 | E8: 0.136929 | F8: -0.069864 | G8: -0.089126 | H8: 0.259692 | I8: 0.060088 | J8: -0.036866 | K8: 0.036364 | L8: -0.001847 | M8: 0.089732 | N8: 0.103141 | O8: 0.05733 | P8: 0.031295 | Q8: 0.093155 | R8: 0.038735 | S8: 0.068365 | T8: -0.077661 | U8: 0.128035 | V8: -0.068214 | W8: 0.033003 | X8: 0.177462 | Y8: 0.029107 | Z8: 0.008629 | AA8: -0.036597 | AB8: -0.016774 | AC8: -0.040391 | AD8: -0.037908 | AE8: 0.095109 | AF8: 0.06799 | AG8: -0.111292 | AH8: 0.057255 | AI8: -0.079624 | AJ8: 0.03842 | AK8: -0.024321 | AL8: -0.202068 | AM8: -0.005317 | AN8: -0.097895 | AO8: -0.014444 | AP8: 0.015784 | AQ8: 0.006659 | AR8: 0.104741 | AS8: -0.0998 | AT8: -0.054324 | AU8: 0.034779 | AV8: 0.159366 | AW8: 0.00228 | AX8: -0.020474 | AY8: 0.01493 | AZ8: 0.016999 | BA8: 0.145612 | BB8: 0.059203 | BC8: -0.010331 | BD8: 0.132227 | BE8: 0.047518 | BF8: -0.031821 | BG8: 0.11958 | BH8: -0.021445 | BI8: 0.197447 | BJ8: -0.157072 | BK8: 0.007378 | BM8: 0.012292 | BN8: 0.027379 | BO8: -0.026073 | BP8: -0.076493 | BQ8: 0.038655 | BR8: -0.008013 | BS8: 0.028409 | BT8: 0.033264 | BU8: -0.012454 | BV8: 0.010914 | BW8: 0.030347 | BX8: 0.074979 | BY8: 0.00909 | BZ8: 0.039187 | CA8: -0.012214 | CB8: 0.056093 | CC8: -0.003673 | CD8: 0.06385 | CE8: -0.031632 | CF8: 0.075391 | CG8: 0.012683 | CH8: 0.03311 | CI8: 0.035485 | CJ8: -0.05261 | CK8: 0.060029 | CL8: 0.014743 | CM8: -0.030005 | CN8: 0.01466 | CO8: 0.057216 | CP8: -0.055099 | CQ8: 0.040594 | CR8: -0.053281 | CS8: 0.061126 | CT8: -0.004914 | CU8: 0.028335 | CV8: -0.043235 | CW8: 0.065447 | CX8: 0.008073 | CY8: -0.027893 | CZ8: 0.028258 | DA8: -0.002503 | DB8: -0.006629 | DC8: -0.034871 | DD8: -0.050823 | DE8: 0.063448 | DF8: 0.030003 | DG8: -0.050286 | DH8: -0.083393 | DI8: 0.018763 | DJ8: 0.08417 | DK8: -2.2e-05 | DL8: 0.00702 | DM8: -0.008668 | DN8: 0.05865 | DO8: 0.021658 | DP8: 0.009925 | DQ8: -0.056638 | DR8: 0.130835 | DS8: 0.024077 | DT8: -0.005274 | DV8: 0.011654 | DW8: 0.02661 | DX8: -0.031859 | DY8: -0.08365 | DZ8: 0.043386 | EA8: -0.011056 | EB8: 0.029146 | EC8: 0.03486 | ED8: -0.012993 | EE8: 0.012777 | EF8: 0.033761 | EG8: 0.07714 | EH8: 0.009752 | EI8: 0.03385 | EJ8: -0.004858 | EK8: 0.060055 | EL8: -0.001103 | EM8: 0.066793 | EN8: -0.03239 | EO8: 0.074048 | EP8: 0.016767 | EQ8: 0.034997 | ER8: 0.036564 | ES8: -0.048941 | ET8: 0.058335 | EU8: 0.018288 | EV8: -0.028006 | EW8: 0.014879 | EX8: 0.058355 | EY8: -0.055238 | EZ8: 0.042686 | FA8: -0.056324 | FB8: 0.060625 | FC8: -0.009011 | FD8: 0.029404 | FE8: -0.051372 | FF8: 0.073055 | FG8: 0.001979 | FH8: -0.012164 | FI8: 0.020936 | FJ8: 0.002798 | FK8: -0.009748 | FL8: -0.03247 | FM8: -0.05037 | FN8: 0.071433 | FO8: 0.034408 | FP8: -0.05314 | FQ8: -0.082202 | FR8: 0.022044 | FS8: 0.079691 | FT8: 0.017991 | FU8: 0.011739 | FV8: -0.014708 | FW8: 0.056092 | FX8: 0.019127 | FY8: 0.013815 | FZ8: -0.055074 | GA8: 0.135632 | GB8: 0.026419 | GC8: -0.00429
B9: =Deals!B9 -> Firstcash Holdings, Inc. | C9: 1 | D9: 0.049938 | E9: 0.014908 | F9: -0.044999 | G9: -0.085449 | H9: 0.072344 | I9: -0.001743 | J9: 0.112718 | K9: 0.031152 | L9: -0.029341 | M9: 0.081729 | N9: 0.027117 | O9: 0.074365 | P9: -0.007503 | Q9: 0.102627 | R9: -0.117758 | S9: 0.045463 | T9: -0.085486 | U9: 0.085145 | V9: 0.035019 | W9: 0.047404 | X9: 0.044913 | Y9: 0.050091 | Z9: -0.026448 | AA9: -0.205369 | AB9: 0.075092 | AC9: -0.044861 | AD9: -0.033492 | AE9: 0.076892 | AF9: 0.096535 | AG9: -0.02049 | AH9: 0.023932 | AI9: -0.030817 | AJ9: 0.055377 | AK9: -0.022004 | AL9: -0.036518 | AM9: -0.10688 | AN9: -0.031778 | AO9: -0.033652 | AP9: 0.039123 | AQ9: -0.036202 | AR9: -0.021464 | AS9: -0.107918 | AT9: 0.014753 | AU9: -0.029319 | AV9: -0.047678 | AW9: 0.019397 | AX9: -0.037542 | AY9: -0.051563 | AZ9: 0.191408 | BA9: 0.092246 | BB9: -0.007165 | BC9: -0.041876 | BD9: 0.174868 | BE9: -0.00039 | BF9: 0.010427 | BG9: -0.089714 | BH9: 0.002549 | BI9: -0.023517 | BJ9: 0.023965 | BK9: -0.091489 | BM9: 0.044547 | BN9: 0.018867 | BO9: 0.000317 | BP9: -0.053893 | BQ9: 0.069423 | BR9: -0.038722 | BS9: 0.018064 | BT9: 0.049843 | BU9: -0.055653 | BV9: -0.004674 | BW9: 0.035149 | BX9: 0.070883 | BY9: 0.008534 | BZ9: 0.05133 | CA9: -0.007138 | CB9: 0.054283 | CC9: 0.018013 | CD9: 0.070419 | CE9: -0.005681 | CF9: 0.068252 | CG9: 0.006633 | CH9: 0.064781 | CI9: 0.028395 | CJ9: 0.001207 | CK9: 0.048235 | CL9: -0.041372 | CM9: -0.067967 | CN9: -0.004401 | CO9: 0.07526 | CP9: -0.050242 | CQ9: 0.055697 | CR9: -0.049962 | CS9: 0.083606 | CT9: 0.016146 | CU9: 0.009829 | CV9: -0.012307 | CW9: 0.074649 | CX9: 0.03186 | CY9: -0.039124 | CZ9: 0.028908 | DA9: 0.012554 | DB9: -0.001721 | DC9: -0.100334 | DD9: -0.095752 | DE9: 0.03069 | DF9: 0.080711 | DG9: -0.03045 | DH9: -0.17716 | DI9: -0.014349 | DJ9: 0.08568 | DK9: 0.045734 | DL9: 0.033855 | DM9: -0.003661 | DN9: 0.0807 | DO9: 0.003679 | DP9: 0.049663 | DQ9: -0.099241 | DR9: 0.093107 | DS9: -0.022398 | DT9: 0.025391 | DV9: 0.040077 | DW9: 0.014133 | DX9: -0.006743 | DY9: -0.060207 | DZ9: 0.065607 | EA9: -0.040728 | EB9: 0.026895 | EC9: 0.051158 | ED9: -0.057903 | EE9: -0.004906 | EF9: 0.035724 | EG9: 0.068896 | EH9: 0.007246 | EI9: 0.049268 | EJ9: -0.006341 | EK9: 0.062929 | EL9: 0.01317 | EM9: 0.075285 | EN9: -0.011026 | EO9: 0.06595 | EP9: 0.010795 | EQ9: 0.066441 | ER9: 0.026067 | ES9: 0.009733 | ET9: 0.03455 | EU9: -0.025746 | EV9: -0.061748 | EW9: -0.008859 | EX9: 0.08789 | EY9: -0.063573 | EZ9: 0.054443 | FA9: -0.0538 | FB9: 0.082902 | FC9: 0.013356 | FD9: 0.011862 | FE9: -0.025271 | FF9: 0.093297 | FG9: 0.030284 | FH9: -0.02015 | FI9: 0.00991 | FJ9: 0.017252 | FK9: -0.003168 | FL9: -0.092336 | FM9: -0.102882 | FN9: 0.04163 | FO9: 0.086308 | FP9: -0.033729 | FQ9: -0.1895 | FR9: -0.00396 | FS9: 0.102724 | FT9: 0.056026 | FU9: 0.03106 | FV9: -0.008278 | FW9: 0.083394 | FX9: -0.000451 | FY9: 0.049994 | FZ9: -0.091743 | GA9: 0.084524 | GB9: -0.015069 | GC9: 0.021881
B10: =Deals!B10 -> Gilead Sciences, Inc. | C10: 1 | D10: -0.068052 | E10: 0.073021 | F10: 0.064675 | G10: -0.039792 | H10: 0.026627 | I10: 0.059477 | J10: 0.061844 | K10: 0.149766 | L10: 0.012739 | M10: 0.116487 | N10: -0.020667 | O10: 0.0742 | P10: 0.08289 | Q10: 0.145599 | R10: 0.034736 | S10: 0.075829 | T10: -0.058921 | U10: 0.197581 | V10: -0.018404 | W10: 0.043139 | X10: 0.132098 | Y10: 0.048542 | Z10: 0.006298 | AA10: 0.073901 | AB10: 0.026534 | AC10: -0.1441 | AD10: 0.107677 | AE10: 0.034654 | AF10: 0.020933 | AG10: 0.104209 | AH10: 0.174877 | AI10: -0.01032 | AJ10: 0.052137 | AK10: -0.104286 | AL10: -0.060407 | AM10: 0.112137 | AN10: -0.012401 | AO10: -0.052159 | AP10: 0.024254 | AQ10: 0.117003 | AR10: 0.042843 | AS10: 0.006662 | AT10: -0.108519 | AU10: -0.06548 | AV10: 0.101232 | AW10: -0.020068 | AX10: -0.045017 | AY10: -0.179761 | AZ10: 0.051205 | BA10: 0.052837 | BB10: -0.039734 | BC10: -0.013037 | BD10: -0.04181 | BE10: -0.047351 | BF10: -0.013716 | BG10: 0.009441 | BH10: -0.069388 | BI10: 0.000951 | BJ10: -0.028358 | BK10: 0.01173 | BM10: 0.051896 | BN10: 0.040349 | BO10: 0.000173 | BP10: -0.063942 | BQ10: 0.028124 | BR10: 0.013732 | BS10: 0.020822 | BT10: 0.017873 | BU10: -0.033013 | BV10: 0.01218 | BW10: -0.009557 | BX10: 0.036126 | BY10: 0.011784 | BZ10: 0.039569 | CA10: 0.02303 | CB10: 0.012043 | CC10: -0.023098 | CD10: 0.059978 | CE10: -0.014845 | CF10: 0.043089 | CG10: 0.048861 | CH10: 0.031878 | CI10: 0.02593 | CJ10: -0.040348 | CK10: 0.051051 | CL10: -0.014273 | CM10: 0.015398 | CN10: 0.031845 | CO10: 0.011359 | CP10: -0.016618 | CQ10: 0.048826 | CR10: -0.006074 | CS10: 0.02283 | CT10: 0.035515 | CU10: -0.012368 | CV10: -0.008353 | CW10: 0.059661 | CX10: -0.010453 | CY10: 0.002214 | CZ10: 0.015755 | DA10: -0.004802 | DB10: 0.031311 | DC10: -0.059184 | DD10: -0.017 | DE10: 0.085501 | DF10: 0.000862 | DG10: -0.013923 | DH10: -0.060194 | DI10: 0.002648 | DJ10: 0.065164 | DK10: -0.007147 | DL10: 0.016604 | DM10: 0.000702 | DN10: 0.051821 | DO10: -0.007159 | DP10: 0.005453 | DQ10: -0.023749 | DR10: 0.010556 | DS10: 0.012329 | DT10: 0.034037 | DV10: 0.038624 | DW10: 0.026205 | DX10: 0.000215 | DY10: -0.076207 | DZ10: 0.026946 | EA10: -1.6e-05 | EB10: 0.025875 | EC10: 0.02156 | ED10: -0.02846 | EE10: 0.022282 | EF10: 0.014411 | EG10: 0.054591 | EH10: 0.013843 | EI10: 0.045019 | EJ10: 0.015903 | EK10: 0.016297 | EL10: -0.012769 | EM10: 0.061764 | EN10: -0.019309 | EO10: 0.050029 | EP10: 0.036587 | EQ10: 0.022659 | ER10: 0.026889 | ES10: -0.025893 | ET10: 0.05659 | EU10: -0.015759 | EV10: 0.002797 | EW10: 0.028851 | EX10: 0.014915 | EY10: -0.024557 | EZ10: 0.050111 | FA10: -0.013994 | FB10: 0.02638 | FC10: 0.037801 | FD10: -0.009339 | FE10: -0.020233 | FF10: 0.068639 | FG10: -0.006734 | FH10: 0.006928 | FI10: 0.003641 | FJ10: -0.010359 | FK10: 0.028827 | FL10: -0.064724 | FM10: -0.022601 | FN10: 0.075987 | FO10: 0.001824 | FP10: -0.00837 | FQ10: -0.063947 | FR10: 0.012902 | FS10: 0.060117 | FT10: -0.004977 | FU10: 0.008057 | FV10: 0.006806 | FW10: 0.049935 | FX10: -0.009553 | FY10: -0.002709 | FZ10: -0.034978 | GA10: 0.024645 | GB10: -0.000502 | GC10: 0.034016
B11: =Deals!B11 -> 3D Systems Corp | C11: 1 | D11: 0.171548 | E11: 0.050893 | F11: 0.252761 | G11: 0.030858 | H11: 0.123026 | I11: 0.113064 | J11: 0.150263 | K11: -0.248456 | L11: 0.324201 | M11: 0.027816 | N11: 0.193245 | O11: 0.084349 | P11: -0.361106 | Q11: -0.127706 | R11: 0.186104 | S11: 0.268828 | T11: -0.095218 | U11: 0.075854 | V11: 0.088291 | W11: 0.050389 | X11: 0.152806 | Y11: 0.20196 | Z11: 0.242214 | AA11: -0.163564 | AB11: -0.022771 | AC11: -0.221301 | AD11: -0.199662 | AE11: 0.06992 | AF11: 0.180652 | AG11: -0.161706 | AH11: 0.067425 | AI11: -0.133433 | AJ11: -0.184818 | AK11: -0.066667 | AL11: -0.068311 | AM11: -0.115303 | AN11: 0.047799 | AO11: -0.100098 | AP11: -0.084974 | AQ11: -0.128338 | AR11: -0.107453 | AS11: -0.32582 | AT11: 0.043313 | AU11: -0.158776 | AV11: -0.129004 | AW11: -0.093439 | AX11: -0.047149 | AY11: -0.078251 | AZ11: 0.332085 | BA11: 0.449859 | BB11: 0.143504 | BC11: -0.243075 | BD11: 0.022405 | BE11: -0.021914 | BF11: 0.082898 | BG11: 0.237931 | BH11: -0.227298 | BI11: -0.001442 | BJ11: -0.040433 | BK11: 0.240783 | BM11: 0.044547 | BN11: 0.018867 | BO11: 0.000317 | BP11: -0.053893 | BQ11: 0.069423 | BR11: -0.038722 | BS11: 0.018064 | BT11: 0.049843 | BU11: -0.055653 | BV11: -0.004674 | BW11: 0.035149 | BX11: 0.070883 | BY11: 0.008534 | BZ11: 0.05133 | CA11: -0.007138 | CB11: 0.054283 | CC11: 0.018013 | CD11: 0.070419 | CE11: -0.005681 | CF11: 0.068252 | CG11: 0.006633 | CH11: 0.064781 | CI11: 0.028395 | CJ11: 0.001207 | CK11: 0.048235 | CL11: -0.041372 | CM11: -0.067967 | CN11: -0.004401 | CO11: 0.07526 | CP11: -0.050242 | CQ11: 0.055697 | CR11: -0.049962 | CS11: 0.083606 | CT11: 0.016146 | CU11: 0.009829 | CV11: -0.012307 | CW11: 0.074649 | CX11: 0.03186 | CY11: -0.039124 | CZ11: 0.028908 | DA11: 0.012554 | DB11: -0.001721 | DC11: -0.100334 | DD11: -0.095752 | DE11: 0.03069 | DF11: 0.080711 | DG11: -0.03045 | DH11: -0.17716 | DI11: -0.014349 | DJ11: 0.08568 | DK11: 0.045734 | DL11: 0.033855 | DM11: -0.003661 | DN11: 0.0807 | DO11: 0.003679 | DP11: 0.049663 | DQ11: -0.099241 | DR11: 0.093107 | DS11: -0.022398 | DT11: 0.025391 | DV11: 0.040077 | DW11: 0.014133 | DX11: -0.006743 | DY11: -0.060207 | DZ11: 0.065607 | EA11: -0.040728 | EB11: 0.026895 | EC11: 0.051158 | ED11: -0.057903 | EE11: -0.004906 | EF11: 0.035724 | EG11: 0.068896 | EH11: 0.007246 | EI11: 0.049268 | EJ11: -0.006341 | EK11: 0.062929 | EL11: 0.01317 | EM11: 0.075285 | EN11: -0.011026 | EO11: 0.06595 | EP11: 0.010795 | EQ11: 0.066441 | ER11: 0.026067 | ES11: 0.009733 | ET11: 0.03455 | EU11: -0.025746 | EV11: -0.061748 | EW11: -0.008859 | EX11: 0.08789 | EY11: -0.063573 | EZ11: 0.054443 | FA11: -0.0538 | FB11: 0.082902 | FC11: 0.013356 | FD11: 0.011862 | FE11: -0.025271 | FF11: 0.093297 | FG11: 0.030284 | FH11: -0.02015 | FI11: 0.00991 | FJ11: 0.017252 | FK11: -0.003168 | FL11: -0.092336 | FM11: -0.102882 | FN11: 0.04163 | FO11: 0.086308 | FP11: -0.033729 | FQ11: -0.1895 | FR11: -0.00396 | FS11: 0.102724 | FT11: 0.056026 | FU11: 0.03106 | FV11: -0.008278 | FW11: 0.083394 | FX11: -0.000451 | FY11: 0.049994 | FZ11: -0.091743 | GA11: 0.084524 | GB11: -0.015069 | GC11: 0.021881
B12: =Deals!B12 -> Genesis Energy Lp | C12: 1 | D12: 0.099609 | E12: -0.0055 | F12: 0.021796 | G12: -0.070736 | H12: 0.010428 | I12: 0.067423 | J12: 0.057246 | K12: 0.040532 | L12: -0.027594 | M12: 0.112938 | N12: -0.004182 | O12: 0.141517 | P12: 0.140482 | Q12: 0.049402 | R12: 0.007196 | S12: 0.04327 | T12: 0.0335 | U12: -0.028362 | V12: -0.023671 | W12: 0.028765 | X12: 0.028201 | Y12: 0.010204 | Z12: 0.021173 | AA12: 0.056972 | AB12: -0.000545 | AC12: -0.014545 | AD12: 0.032657 | AE12: 0.02851 | AF12: -0.016842 | AG12: -0.053266 | AH12: 0.061155 | AI12: -0.054937 | AJ12: -0.077508 | AK12: -0.082326 | AL12: -0.036566 | AM12: 0.035479 | AN12: 0.06162 | AO12: 0.021739 | AP12: 0.070638 | AQ12: -0.021726 | AR12: -0.097471 | AS12: 0.025632 | AT12: -0.016445 | AU12: -0.121851 | AV12: 0.068075 | AW12: -0.023815 | AX12: -0.066328 | AY12: -0.208628 | AZ12: -0.098874 | BA12: 0.241312 | BB12: 0.040988 | BC12: 0.161937 | BD12: 0.018582 | BE12: -0.033881 | BF12: -0.016218 | BG12: 0.060911 | BH12: -0.061628 | BI12: 0.000286 | BJ12: 0.03091 | BK12: 0.013463 | BM12: 0.03564 | BN12: 0.016925 | BO12: -0.013647 | BP12: -0.079972 | BQ12: 0.018963 | BR12: -0.013357 | BS12: 0.046121 | BT12: 0.015771 | BU12: -0.004359 | BV12: 0.025113 | BW12: 0.023897 | BX12: 0.062127 | BY12: 0.00487 | BZ12: 0.052829 | CA12: -0.007109 | CB12: 0.041347 | CC12: -0.015247 | CD12: 0.057981 | CE12: -0.034983 | CF12: 0.058569 | CG12: 0.037265 | CH12: 0.037207 | CI12: 0.029865 | CJ12: -0.041643 | CK12: 0.045552 | CL12: 0.00605 | CM12: -0.020868 | CN12: 0.025203 | CO12: 0.037615 | CP12: -0.060663 | CQ12: 0.044977 | CR12: -0.04827 | CS12: 0.039518 | CT12: -0.003724 | CU12: 0.005191 | CV12: -0.038677 | CW12: 0.085639 | CX12: 0.017149 | CY12: -0.009998 | CZ12: 0.029717 | DA12: -0.011516 | DB12: -0.033357 | DC12: -0.035791 | DD12: -0.051436 | DE12: 0.074104 | DF12: 0.007963 | DG12: -0.046804 | DH12: -0.068914 | DI12: 0.023766 | DJ12: 0.078786 | DK12: 0.016005 | DL12: 0.006008 | DM12: -0.000795 | DN12: 0.065576 | DO12: 0.037891 | DP12: 0.003862 | DQ12: -0.029525 | DR12: 0.103264 | DS12: 0.015927 | DT12: 0.013463 | DV12: 0.035691 | DW12: 0.01669 | DX12: -0.019771 | DY12: -0.085092 | DZ12: 0.015011 | EA12: -0.013916 | EB12: 0.047372 | EC12: 0.020104 | ED12: -0.003816 | EE12: 0.025116 | EF12: 0.029117 | EG12: 0.05969 | EH12: 0.004146 | EI12: 0.052415 | EJ12: -0.011178 | EK12: 0.046099 | EL12: -0.015341 | EM12: 0.058453 | EN12: -0.037328 | EO12: 0.056178 | EP12: 0.039877 | EQ12: 0.037221 | ER12: 0.032848 | ES12: -0.043165 | ET12: 0.042305 | EU12: 0.008794 | EV12: -0.020111 | EW12: 0.026815 | EX12: 0.037007 | EY12: -0.062591 | EZ12: 0.046414 | FA12: -0.048632 | FB12: 0.043708 | FC12: -0.008139 | FD12: 0.001292 | FE12: -0.042807 | FF12: 0.086461 | FG12: 0.010184 | FH12: 0.003168 | FI12: 0.021695 | FJ12: -0.012441 | FK12: -0.032816 | FL12: -0.035298 | FM12: -0.052597 | FN12: 0.081152 | FO12: 0.0063 | FP12: -0.040284 | FQ12: -0.078335 | FR12: 0.026229 | FS12: 0.083064 | FT12: 0.026946 | FU12: 0.000891 | FV12: -0.001501 | FW12: 0.065978 | FX12: 0.037025 | FY12: 0.003486 | FZ12: -0.033383 | GA12: 0.109108 | GB12: 0.012881 | GC12: 0.010399
B13: =Deals!B13 -> ICF International, Inc. | C13: 1 | D13: -0.085039 | E13: -0.021597 | F13: -0.016949 | G13: -0.097835 | H13: 0.059556 | I13: 0.030621 | J13: -0.102971 | K13: -0.088022 | L13: -0.087065 | M13: 0.178202 | N13: 0.084181 | O13: -0.023464 | P13: 0.080821 | Q13: 0.099434 | R13: -0.003309 | S13: 0.112136 | T13: 0.045108 | U13: 0.059664 | V13: -0.014975 | W13: 0.076619 | X13: -0.02231 | Y13: 0.033507 | Z13: -0.029905 | AA13: -0.030251 | AB13: 0.200832 | AC13: -0.015092 | AD13: -0.0211 | AE13: -0.04542 | AF13: -0.049462 | AG13: -0.022342 | AH13: -0.022852 | AI13: -0.088514 | AJ13: 0.180253 | AK13: 0.067144 | AL13: 0.05673 | AM13: -0.088336 | AN13: 0.12152 | AO13: -0.02506 | AP13: -0.057528 | AQ13: -0.070649 | AR13: -0.025713 | AS13: 0.051635 | AT13: -0.06683 | AU13: -0.111663 | AV13: 0.009214 | AW13: 0.161722 | AX13: -0.001965 | AY13: -0.037964 | AZ13: -0.012569 | BA13: 0.017466 | BB13: 0.145476 | BC13: 0.035814 | BD13: 0.002943 | BE13: 0.011736 | BF13: 0.011358 | BG13: 0.05902 | BH13: 0.046931 | BI13: 0.192888 | BJ13: -0.00271 | BK13: -0.057971 | BM13: 0.009861 | BN13: 0.034662 | BO13: -0.013323 | BP13: -0.080339 | BQ13: 0.054737 | BR13: -0.017732 | BS13: 0.027338 | BT13: 0.046007 | BU13: -0.032182 | BV13: -0.001937 | BW13: 0.045318 | BX13: 0.056109 | BY13: 0.017514 | BZ13: 0.041721 | CA13: -0.007784 | CB13: 0.065535 | CC13: 0.010997 | CD13: 0.089501 | CE13: -0.037353 | CF13: 0.069327 | CG13: 0.040429 | CH13: 0.071859 | CI13: 0.012559 | CJ13: -0.03596 | CK13: 0.058009 | CL13: 0.008661 | CM13: -0.033099 | CN13: -0.00585 | CO13: 0.041741 | CP13: -0.04321 | CQ13: 0.044624 | CR13: -0.0578 | CS13: 0.072509 | CT13: -0.012612 | CU13: 0.043534 | CV13: -0.05091 | CW13: 0.051146 | CX13: 0.018305 | CY13: -0.020565 | CZ13: -0.001646 | DA13: 0.022 | DB13: -0.055373 | DC13: -0.035985 | DD13: -0.039847 | DE13: 0.05297 | DF13: 0.030741 | DG13: -0.052302 | DH13: -0.063009 | DI13: -0.01309 | DJ13: 0.068055 | DK13: 0.016072 | DL13: -0.008157 | DM13: 0.007352 | DN13: 0.048882 | DO13: 0.041045 | DP13: 0.030226 | DQ13: -0.035925 | DR13: 0.13831 | DS13: 0.080139 | DT13: -0.018857 | DV13: 0.024759 | DW13: 0.042259 | DX13: 0.000228 | DY13: -0.084832 | DZ13: 0.044137 | EA13: -0.015945 | EB13: 0.0255 | EC13: 0.043556 | ED13: -0.022199 | EE13: -0.009866 | EF13: 0.03416 | EG13: 0.06724 | EH13: 0.012135 | EI13: 0.040628 | EJ13: 0.0045 | EK13: 0.051579 | EL13: 0.011459 | EM13: 0.079555 | EN13: -0.029153 | EO13: 0.068792 | EP13: 0.047151 | EQ13: 0.065449 | ER13: 0.015166 | ES13: -0.006881 | ET13: 0.035091 | EU13: -0.000653 | EV13: -0.038076 | EW13: -0.003217 | EX13: 0.033817 | EY13: -0.039386 | EZ13: 0.035353 | FA13: -0.044869 | FB13: 0.03704 | FC13: -0.006985 | FD13: 0.041462 | FE13: -0.039313 | FF13: 0.048343 | FG13: 0.008998 | FH13: -0.01209 | FI13: 0.003564 | FJ13: 0.001854 | FK13: -0.050328 | FL13: -0.034308 | FM13: -0.049615 | FN13: 0.049806 | FO13: 0.011878 | FP13: -0.049649 | FQ13: -0.086043 | FR13: -0.014482 | FS13: 0.077828 | FT13: 0.037266 | FU13: -0.017486 | FV13: 0.008906 | FW13: 0.041202 | FX13: 0.034504 | FY13: 0.027047 | FZ13: -0.045937 | GA13: 0.097765 | GB13: 0.059961 | GC13: 0.000689
B14: =Deals!B14 -> Enovis CORP | C14: 1 | D14: 0.120553 | E14: 0.035861 | F14: -0.038309 | G14: -0.16406 | H14: -0.026827 | I14: 0.049692 | J14: 0.136489 | K14: 0.114929 | L14: -0.062176 | M14: 0.13376 | N14: 0.034881 | O14: 0.105576 | P14: -0.027124 | Q14: 0.07235 | R14: 0.002793 | S14: 0.069209 | T14: 0.044289 | U14: 0.018423 | V14: -0.018466 | W14: 0.084469 | X14: -0.009382 | Y14: 0.045926 | Z14: 0.08816 | AA14: -0.054012 | AB14: 0.180581 | AC14: 0.002812 | AD14: 0.009113 | AE14: 0.011253 | AF14: 0.024042 | AG14: -0.155219 | AH14: 0.010164 | AI14: -0.104386 | AJ14: -0.045463 | AK14: -0.052409 | AL14: 0.000776 | AM14: -0.121388 | AN14: 0.162657 | AO14: -0.093964 | AP14: 0.038969 | AQ14: 0.016132 | AR14: -0.084144 | AS14: -0.173564 | AT14: 0.017042 | AU14: -0.228925 | AV14: -0.098629 | AW14: 0.00408 | AX14: -0.137421 | AY14: -0.05182 | AZ14: 0.14318 | BA14: 0.129593 | BB14: 0.134313 | BC14: -0.164662 | BD14: -0.023256 | BE14: 0.109599 | BF14: 0.010899 | BG14: 0.058962 | BH14: 0.011454 | BI14: 0.183076 | BJ14: -0.044669 | BK14: 0.085444 | BM14: 0.044446 | BN14: 0.014495 | BO14: -0.021785 | BP14: -0.079095 | BQ14: 0.052776 | BR14: -0.026861 | BS14: 0.051294 | BT14: 0.028554 | BU14: -0.038571 | BV14: 0.028796 | BW14: 0.024315 | BX14: 0.054936 | BY14: 0.00502 | BZ14: 0.044964 | CA14: -0.020228 | CB14: 0.029833 | CC14: -0.004107 | CD14: 0.082928 | CE14: -0.016534 | CF14: 0.057374 | CG14: 0.033835 | CH14: 0.027704 | CI14: 0.016469 | CJ14: -0.003567 | CK14: 0.066358 | CL14: -0.046875 | CM14: -0.05681 | CN14: 0.012433 | CO14: 0.062082 | CP14: -0.054705 | CQ14: 0.063988 | CR14: -0.029935 | CS14: 0.058786 | CT14: 0.027658 | CU14: 0.017988 | CV14: -0.005831 | CW14: 0.073006 | CX14: 0.005411 | CY14: -0.031006 | CZ14: 0.044006 | DA14: 0.012921 | DB14: 0.019176 | DC14: -0.080326 | DD14: -0.060705 | DE14: 0.038969 | DF14: 0.019986 | DG14: -0.026704 | DH14: -0.116705 | DI14: -0.002874 | DJ14: 0.056488 | DK14: 0.011506 | DL14: 0.033278 | DM14: 0.008302 | DN14: 0.070227 | DO14: -0.01104 | DP14: 0 | DQ14: -0.048917 | DR14: 0.059159 | DS14: 0.003178 | DT14: 0.025215 | DV14: 0.04168 | DW14: 0.014419 | DX14: -0.027667 | DY14: -0.086416 | DZ14: 0.060592 | EA14: -0.033612 | EB14: 0.051174 | EC14: 0.025462 | ED14: -0.040985 | EE14: 0.032086 | EF14: 0.0249 | EG14: 0.050641 | EH14: 0.005701 | EI14: 0.039137 | EJ14: -0.015095 | EK14: 0.031393 | EL14: -0.008217 | EM14: 0.083009 | EN14: -0.014221 | EO14: 0.057053 | EP14: 0.036623 | EQ14: 0.042054 | ER14: 0.017674 | ES14: -0.010563 | ET14: 0.064953 | EU14: -0.033966 | EV14: -0.04956 | EW14: 0.009724 | EX14: 0.061219 | EY14: -0.054769 | EZ14: 0.059892 | FA14: -0.02737 | FB14: 0.061437 | FC14: 0.027518 | FD14: 0.018058 | FE14: -0.014795 | FF14: 0.082671 | FG14: 0.00508 | FH14: -0.029513 | FI14: 0.036794 | FJ14: 0.016471 | FK14: 0.01547 | FL14: -0.081561 | FM14: -0.066173 | FN14: 0.04778 | FO14: 0.032253 | FP14: -0.028193 | FQ14: -0.130111 | FR14: 0.001735 | FS14: 0.058941 | FT14: 0.017347 | FU14: 0.032947 | FV14: 0.007118 | FW14: 0.071002 | FX14: -0.012112 | FY14: -0.000608 | FZ14: -0.052504 | GA14: 0.057973 | GB14: -0.000793 | GC14: 0.027035
B15: =Deals!B15 -> International Paper Co /New/ | C15: 1 | D15: -0.001422 | E15: -0.050997 | F15: -0.1156 | G15: -0.009932 | H15: 0.134901 | I15: 0.061243 | J15: 0.050926 | K15: -0.013491 | L15: 0.044819 | M15: 0.072698 | N15: 0.039659 | O15: 0.069673 | P15: 0.058396 | Q15: 0.008587 | R15: -0.01137 | S15: -0.03987 | T15: 0.090273 | U15: -0.016645 | V15: -0.051049 | W15: -0.004241 | X15: 0.05526 | Y15: 0.049219 | Z15: -0.02631 | AA15: 0.031319 | AB15: -0.061567 | AC15: 0.016783 | AD15: 0.028407 | AE15: 0.059626 | AF15: -0.058847 | AG15: 0.027368 | AH15: -0.014654 | AI15: 0.060327 | AJ15: 0.071118 | AK15: -0.004459 | AL15: -0.017171 | AM15: 0.078807 | AN15: -0.016309 | AO15: -0.031898 | AP15: -0.027736 | AQ15: -0.081806 | AR15: 0.005884 | AS15: -0.090453 | AT15: -0.124015 | AU15: 0.129664 | AV15: -0.009838 | AW15: -0.098733 | AX15: -0.092573 | AY15: 0.056416 | AZ15: 0.14958 | BA15: 0.054337 | BB15: -0.015484 | BC15: 0.005218 | BD15: 0.080934 | BE15: 0.068107 | BF15: -0.010518 | BG15: -0.061484 | BH15: 0.092227 | BI15: 0.08908 | BJ15: 0.066717 | BK15: -0.060724 | BM15: 0.011104 | BN15: -0.006957 | BO15: -0.053137 | BP15: 0.054172 | BQ15: 0.01408 | BR15: 0.015463 | BS15: 0.035857 | BT15: -0.02592 | BU15: -0.001378 | BV15: 0.015409 | BW15: 0.056 | BX15: 0.019792 | BY15: 0.036318 | BZ15: 0.018478 | CA15: 0.013823 | CB15: 0.001531 | CC15: 0.046444 | CD15: -0.035744 | CE15: 0.025945 | CF15: 0.054352 | CG15: 0.016052 | CH15: 0.035924 | CI15: -0.035102 | CJ15: 0.029857 | CK15: 0.022111 | CL15: 0.014137 | CM15: 0.023498 | CN15: 0.02564 | CO15: -0.004222 | CP15: 0.022102 | CQ15: -0.016297 | CR15: 0.019633 | CS15: 0.033343 | CT15: -0.001868 | CU15: -0.041801 | CV15: 0.067385 | CW15: -0.02256 | CX15: 0.013814 | CY15: 0.011985 | CZ15: -0.016933 | DA15: 0.001147 | DB15: -0.056437 | DC15: -0.018387 | DD15: 0.085874 | DE15: -0.005096 | DF15: -0.022773 | DG15: -0.041199 | DH15: 0.013535 | DI15: 0.065163 | DJ15: 0.025925 | DK15: 0.021844 | DL15: 0.024846 | DM15: 0.01713 | DN15: -0.001476 | DO15: 0.008286 | DP15: -0.021076 | DQ15: 0.046286 | DR15: 0.022528 | DS15: -0.005353 | DT15: 0.023452 | DV15: 0.00889 | DW15: -0.005731 | DX15: -0.065057 | DY15: 0.035797 | DZ15: 0.007011 | EA15: 0.032033 | EB15: 0.024719 | EC15: -0.004593 | ED15: 0.006014 | EE15: 0.02747 | EF15: 0.065184 | EG15: 0.018151 | EH15: 0.051292 | EI15: 0.02256 | EJ15: 0.019439 | EK15: 0.004793 | EL15: 0.049384 | EM15: -0.027341 | EN15: 0.028478 | EO15: 0.047864 | EP15: 0.018236 | EQ15: 0.030343 | ER15: -0.025246 | ES15: 0.045547 | ET15: 0.016672 | EU15: 0.012388 | EV15: 0.018194 | EW15: 0.029903 | EX15: -0.007776 | EY15: 0.030607 | EZ15: -0.015773 | FA15: 0.019988 | FB15: 0.033075 | FC15: -0.002345 | FD15: -0.04333 | FE15: 0.071223 | FF15: -0.015691 | FG15: 0.009233 | FH15: 0.003747 | FI15: -0.021108 | FJ15: 0.002598 | FK15: -0.05208 | FL15: -0.026202 | FM15: 0.076828 | FN15: -0.00011 | FO15: -0.034144 | FP15: -0.039422 | FQ15: -0.002125 | FR15: 0.084992 | FS15: 0.028284 | FT15: 0.02136 | FU15: 0.007837 | FV15: 0.032734 | FW15: 0.004087 | FX15: 0.011858 | FY15: -0.01357 | FZ15: 0.066072 | GA15: 0.010798 | GB15: 0.018176 | GC15: 0.02874
B16: =Deals!B16 -> Synopsys, Inc | C16: 1 | D16: 0.006236 | E16: -0.0212 | F16: -0.015328 | G16: -0.004061 | H16: 0.029222 | I16: 0.090459 | J16: -0.00106 | K16: -0.024095 | L16: 0.020497 | M16: -0.031181 | N16: 0.050403 | O16: 0.047548 | P16: 0.024265 | Q16: -0.00864 | R16: 0.024459 | S16: -0.018935 | T16: 0.036084 | U16: -0.021058 | V16: 0.039713 | W16: -0.033952 | X16: 0.009336 | Y16: 0.103645 | Z16: -0.017501 | AA16: 0.013547 | AB16: -0.049257 | AC16: -0.020568 | AD16: 0.023126 | AE16: 0.008574 | AF16: -0.027048 | AG16: 0.08287 | AH16: -0.029462 | AI16: 0.032372 | AJ16: 0.058809 | AK16: 0.001844 | AL16: -0.011042 | AM16: 0.079553 | AN16: -0.001939 | AO16: 0.01209 | AP16: 0.064206 | AQ16: 0.015234 | AR16: 0.003751 | AS16: -0.076908 | AT16: -0.015981 | AU16: 0.082287 | AV16: 0.002001 | AW16: -0.089257 | AX16: -0.059417 | AY16: 0.043124 | AZ16: 0.082458 | BA16: -0.018993 | BB16: 0.087332 | BC16: 0.046642 | BD16: 0.001479 | BE16: 0.094719 | BF16: 0.001012 | BG16: -0.000674 | BH16: 0.019727 | BI16: -0.026786 | BJ16: 0.068468 | BK16: 0.135952 | BM16: 0.006311 | BN16: -0.005028 | BO16: -0.088132 | BP16: 0.039208 | BQ16: 0.004596 | BR16: 0.025858 | BS16: 0.024552 | BT16: -0.005801 | BU16: -0.000505 | BV16: 0.028551 | BW16: 0.066681 | BX16: 0.016982 | BY16: 0.042198 | BZ16: -0.006672 | CA16: 0.015315 | CB16: -0.012367 | CC16: 0.065184 | CD16: -0.031385 | CE16: 0.051904 | CF16: 0.02806 | CG16: 0.008498 | CH16: 0.028176 | CI16: -0.008152 | CJ16: 0.048088 | CK16: 0.00209 | CL16: 0.001289 | CM16: 0.033027 | CN16: 0.039543 | CO16: -0.033145 | CP16: 0.04848 | CQ16: -0.045069 | CR16: 0.038236 | CS16: 0.03348 | CT16: 0.003273 | CU16: -0.010601 | CV16: 0.075713 | CW16: 0.011038 | CX16: -0.00926 | CY16: 0.029853 | CZ16: -0.021078 | DA16: -0.00198 | DB16: -0.047488 | DC16: -0.043814 | DD16: 0.07451 | DE16: 0.009557 | DF16: -0.044603 | DG16: -0.064723 | DH16: 0.001069 | DI16: 0.095151 | DJ16: 0.018491 | DK16: 0.045514 | DL16: -0.012791 | DM16: 0.033162 | DN16: 0.021293 | DO16: 0.011081 | DP16: -0.008831 | DQ16: 0.072449 | DR16: 0.012484 | DS16: 0.015297 | DT16: 0.030587 | DV16: 0.011422 | DW16: -0.011434 | DX16: -0.090474 | DY16: 0.044112 | DZ16: 0.010579 | EA16: 0.033163 | EB16: 0.025597 | EC16: -0.004533 | ED16: 0.004397 | EE16: 0.029029 | EF16: 0.063545 | EG16: 0.023451 | EH16: 0.043648 | EI16: -0.005544 | EJ16: 0.02183 | EK16: -0.013395 | EL16: 0.062888 | EM16: -0.033477 | EN16: 0.060979 | EO16: 0.02917 | EP16: 0.010095 | EQ16: 0.029533 | ER16: -0.003427 | ES16: 0.045803 | ET16: -0.000132 | EU16: 0.002431 | EV16: 0.036902 | EW16: 0.040403 | EX16: -0.035133 | EY16: 0.045497 | EZ16: -0.044913 | FA16: 0.033794 | FB16: 0.028917 | FC16: -0.001018 | FD16: -0.022323 | FE16: 0.080976 | FF16: 0.007241 | FG16: -0.000627 | FH16: 0.018439 | FI16: -0.023752 | FJ16: 0.001638 | FK16: -0.053171 | FL16: -0.047451 | FM16: 0.064849 | FN16: 0.003787 | FO16: -0.048371 | FP16: -0.059277 | FQ16: 0.007081 | FR16: 0.101215 | FS16: 0.026988 | FT16: 0.032746 | FU16: -0.024517 | FV16: 0.033259 | FW16: 0.020056 | FX16: 0.010726 | FY16: -0.009775 | FZ16: 0.072883 | GA16: 0.017056 | GB16: 0.016222 | GC16: 0.027022
B17: =Deals!B17 -> Aci Worldwide, Inc. | C17: 1 | D17: 0.065908 | E17: -0.010181 | F17: -0.041897 | G17: 0.157633 | H17: -0.004524 | I17: -0.014315 | J17: -0.025818 | K17: -0.074775 | L17: 0.102558 | M17: 0.013454 | N17: 0.088121 | O17: -0.03639 | P17: 0.066579 | Q17: -0.037863 | R17: -0.010636 | S17: -0.000645 | T17: 0.018718 | U17: 0.027878 | V17: 0.110746 | W17: 0.019608 | X17: 0.173803 | Y17: 0.004637 | Z17: -0.067538 | AA17: -0.009569 | AB17: -0.013993 | AC17: -0.034465 | AD17: -0.049694 | AE17: 0.027987 | AF17: 0.006985 | AG17: 0.038954 | AH17: -0.036466 | AI17: 0.025586 | AJ17: 0.010915 | AK17: 0.037018 | AL17: -0.084284 | AM17: 0.074716 | AN17: 0.091184 | AO17: 0.06325 | AP17: 0.033869 | AQ17: 0.031919 | AR17: -0.03663 | AS17: -0.098859 | AT17: -0.009845 | AU17: 0.133996 | AV17: -0.017954 | AW17: -0.090136 | AX17: -0.163551 | AY17: 0.042458 | AZ17: 0.114148 | BA17: -0.03848 | BB17: 0.033517 | BC17: -0.055663 | BD17: 0.015377 | BE17: -0.03584 | BF17: 0.01466 | BG17: -0.065015 | BH17: 0.027042 | BI17: -0.024718 | BJ17: 0.068871 | BK17: 0.008763 | BM17: 0.018867 | BN17: 0.000317 | BO17: -0.053893 | BP17: 0.069423 | BQ17: -0.038722 | BR17: 0.018064 | BS17: 0.049843 | BT17: -0.055653 | BU17: -0.004674 | BV17: 0.035149 | BW17: 0.070883 | BX17: 0.008534 | BY17: 0.05133 | BZ17: -0.007138 | CA17: 0.054283 | CB17: 0.018013 | CC17: 0.070419 | CD17: -0.005681 | CE17: 0.068252 | CF17: 0.006633 | CG17: 0.064781 | CH17: 0.028395 | CI17: 0.001207 | CJ17: 0.048235 | CK17: -0.041372 | CL17: -0.067967 | CM17: -0.004401 | CN17: 0.07526 | CO17: -0.050242 | CP17: 0.055697 | CQ17: -0.049962 | CR17: 0.083606 | CS17: 0.016146 | CT17: 0.009829 | CU17: -0.012307 | CV17: 0.074649 | CW17: 0.03186 | CX17: -0.039124 | CY17: 0.028908 | CZ17: 0.012554 | DA17: -0.001721 | DB17: -0.100334 | DC17: -0.095752 | DD17: 0.03069 | DE17: 0.080711 | DF17: -0.03045 | DG17: -0.17716 | DH17: -0.014349 | DI17: 0.08568 | DJ17: 0.045734 | DK17: 0.033855 | DL17: -0.003661 | DM17: 0.0807 | DN17: 0.003679 | DO17: 0.049663 | DP17: -0.099241 | DQ17: 0.093107 | DR17: -0.022398 | DS17: 0.025391 | DT17: 0.058384 | DV17: 0.014133 | DW17: -0.006743 | DX17: -0.060207 | DY17: 0.065607 | DZ17: -0.040728 | EA17: 0.026895 | EB17: 0.051158 | EC17: -0.057903 | ED17: -0.004906 | EE17: 0.035724 | EF17: 0.068896 | EG17: 0.007246 | EH17: 0.049268 | EI17: -0.006341 | EJ17: 0.062929 | EK17: 0.01317 | EL17: 0.075285 | EM17: -0.011026 | EN17: 0.06595 | EO17: 0.010795 | EP17: 0.066441 | EQ17: 0.026067 | ER17: 0.009733 | ES17: 0.03455 | ET17: -0.025746 | EU17: -0.061748 | EV17: -0.008859 | EW17: 0.08789 | EX17: -0.063573 | EY17: 0.054443 | EZ17: -0.0538 | FA17: 0.082902 | FB17: 0.013356 | FC17: 0.011862 | FD17: -0.025271 | FE17: 0.093297 | FF17: 0.030284 | FG17: -0.02015 | FH17: 0.00991 | FI17: 0.017252 | FJ17: -0.003168 | FK17: -0.092336 | FL17: -0.102882 | FM17: 0.04163 | FN17: 0.086308 | FO17: -0.033729 | FP17: -0.1895 | FQ17: -0.00396 | FR17: 0.102724 | FS17: 0.056026 | FT17: 0.03106 | FU17: -0.008278 | FV17: 0.083394 | FW17: -0.000451 | FX17: 0.049994 | FY17: -0.091743 | FZ17: 0.084524 | GA17: -0.015069 | GB17: 0.021881 | GC17: 0.051798
B18: =Deals!B18 -> Jazz Pharmaceuticals plc | C18: 1 | D18: -0.076234 | E18: 0.052816 | F18: -0.153439 | G18: 0.041898 | H18: 0.067985 | I18: -0.053256 | J18: 0.25245 | K18: -0.059282 | L18: 0.004849 | M18: -0.011691 | N18: 0.058965 | O18: 0.031743 | P18: -0.039017 | Q18: 0.043642 | R18: 0.164867 | S18: 0.011181 | T18: 0.099345 | U18: 0.160565 | V18: 0.048808 | W18: -0.013374 | X18: 0.274521 | Y18: 0.094336 | Z18: 0.198325 | AA18: 0.001879 | AB18: -0.087301 | AC18: -0.027257 | AD18: 0.051594 | AE18: 0.036303 | AF18: -0.04952 | AG18: 0.165963 | AH18: -0.014486 | AI18: 0.05157 | AJ18: 0.048863 | AK18: -0.075442 | AL18: 0.034264 | AM18: 0.004429 | AN18: 0.015874 | AO18: 0.034203 | AP18: 0.003637 | AQ18: -0.018288 | AR18: 0.091838 | AS18: -0.121827 | AT18: -0.213304 | AU18: 0.033657 | AV18: 0.067818 | AW18: -0.041135 | AX18: -0.084092 | AY18: -0.055616 | AZ18: 0.073779 | BA18: 0.154347 | BB18: 0.005707 | BC18: -0.06763 | BD18: 0.06836 | BE18: -0.179771 | BF18: -0.018978 | BG18: -0.098864 | BH18: -0.053348 | BI18: 0.052108 | BJ18: 0.118224 | BK18: 0.087762 | BM18: 0.014495 | BN18: -0.021785 | BO18: -0.079095 | BP18: 0.052776 | BQ18: -0.026861 | BR18: 0.051294 | BS18: 0.028554 | BT18: -0.038571 | BU18: 0.028796 | BV18: 0.024315 | BW18: 0.054936 | BX18: 0.00502 | BY18: 0.044964 | BZ18: -0.020228 | CA18: 0.029833 | CB18: -0.004107 | CC18: 0.082928 | CD18: -0.016534 | CE18: 0.057374 | CF18: 0.033835 | CG18: 0.027704 | CH18: 0.016469 | CI18: -0.003567 | CJ18: 0.066358 | CK18: -0.046875 | CL18: -0.05681 | CM18: 0.012433 | CN18: 0.062082 | CO18: -0.054705 | CP18: 0.063988 | CQ18: -0.029935 | CR18: 0.058786 | CS18: 0.027658 | CT18: 0.017988 | CU18: -0.005831 | CV18: 0.073006 | CW18: 0.005411 | CX18: -0.031006 | CY18: 0.044006 | CZ18: 0.012921 | DA18: 0.019176 | DB18: -0.080326 | DC18: -0.060705 | DD18: 0.038969 | DE18: 0.019986 | DF18: -0.026704 | DG18: -0.116705 | DH18: -0.002874 | DI18: 0.056488 | DJ18: 0.011506 | DK18: 0.033278 | DL18: 0.008302 | DM18: 0.070227 | DN18: -0.01104 | DO18: 0 | DP18: -0.048917 | DQ18: 0.059159 | DR18: 0.003178 | DS18: 0.025215 | DT18: 0.039548 | DV18: 0.014419 | DW18: -0.027667 | DX18: -0.086416 | DY18: 0.060592 | DZ18: -0.033612 | EA18: 0.051174 | EB18: 0.025462 | EC18: -0.040985 | ED18: 0.032086 | EE18: 0.0249 | EF18: 0.050641 | EG18: 0.005701 | EH18: 0.039137 | EI18: -0.015095 | EJ18: 0.031393 | EK18: -0.008217 | EL18: 0.083009 | EM18: -0.014221 | EN18: 0.057053 | EO18: 0.036623 | EP18: 0.042054 | EQ18: 0.017674 | ER18: -0.010563 | ES18: 0.064953 | ET18: -0.033966 | EU18: -0.04956 | EV18: 0.009724 | EW18: 0.061219 | EX18: -0.054769 | EY18: 0.059892 | EZ18: -0.02737 | FA18: 0.061437 | FB18: 0.027518 | FC18: 0.018058 | FD18: -0.014795 | FE18: 0.082671 | FF18: 0.00508 | FG18: -0.029513 | FH18: 0.036794 | FI18: 0.016471 | FJ18: 0.01547 | FK18: -0.081561 | FL18: -0.066173 | FM18: 0.04778 | FN18: 0.032253 | FO18: -0.028193 | FP18: -0.130111 | FQ18: 0.001735 | FR18: 0.058941 | FS18: 0.017347 | FT18: 0.032947 | FU18: 0.007118 | FV18: 0.071002 | FW18: -0.012112 | FX18: -0.000608 | FY18: -0.052504 | FZ18: 0.057973 | GA18: -0.000793 | GB18: 0.027035 | GC18: 0.042605
... B650: =Deals!B650 -> Clarivate Plc | C650: 1 | D650: 0.10747 | E650: -0.003916 | F650: -0.024465 | G650: 0.238245 | H650: 0.064738 | I650: 0.052649 | J650: -0.10455 | K650: -0.011171 | L650: 0.082726 | M650: -0.025917 | N650: -0.213891 | O650: 0.16 | P650: 0.058355 | Q650: 0.075546 | R650: -0.083555 | S650: -0.171813 | T650: 0.104825 | U650: -0.130607 | V650: 0.070776 | W650: -0.004691 | X650: 0.007712 | Y650: -0.30017 | Z650: -0.089915 | AA650: 0.118825 | AB650: -0.064439 | AC650: -0.058036 | AD650: -0.061611 | AE650: 0.045455 | AF650: -0.194617 | AG650: -0.195373 | AH650: 0.100106 | AI650: -0.052275 | AJ650: -0.14811 | AK650: 0.333333 | AL650: -0.089029 | AM650: -0.07305 | AN650: -0.056443 | AO650: -0.119639 | AP650: 0.221795 | AQ650: -0.002099 | AR650: -0.218717 | AS650: -0.096904 | AT650: -0.04918 | AU650: 0.216301 | AV650: 0.193299 | AW650: -0.034557 | AX650: -0.196868 | AY650: 0.034819 | AZ650: -0.090175 | BA650: -0.156805 | BB650: -0.001754 | BC650: 0.184534 | BD650: 0.017804 | BE650: 0.034985 | BF650: -0.070423 | BG650: -0.131818 | BH650: -0.113438 | BI650: 0.066929 | BJ650: -0.208487 | BK650: -0.083916 | BM650: 0.165635 | BN650: 0.108631 | BO650: 0.022515 | BP650: 0.060034 | BQ650: 0.042064 | BR650: 0.00853 | BS650: 0.014059 | BT650: 0.135594 | BU650: 0.068794 | BV650: -0.002337 | BW650: 0.034689 | BX650: -0.020006 | BY650: 0.043697 | BZ650: -0.020314 | CA650: 0.05157 | CB650: -0.008614 | CC650: 0.031631 | CD650: -0.042971 | CE650: 0.047924 | CF650: -0.063866 | CG650: 0.003966 | CH650: -0.127141 | CI650: 0.001103 | CJ650: 0.001259 | CK650: -0.107022 | CL650: -0.028824 | CM650: -0.072625 | CN650: 0.130842 | CO650: -0.025181 | CP650: -0.091353 | CQ650: 0.057844 | CR650: 0.043218 | CS650: -0.053526 | CT650: 0.096917 | CU650: -0.024248 | CV650: 0.012549 | CW650: -0.018976 | CX650: 0.00158 | CY650: 0.08151 | CZ650: 0.012495 | DA650: -0.024647 | DB650: -0.058736 | DC650: -0.06088 | DD650: 0.098774 | DE650: 0.08847 | DF650: -0.016905 | DG650: 0.070309 | DH650: 0.038473 | DI650: -0.057327 | DJ650: 0.025533 | DK650: -0.006069 | DL650: 0.032133 | DM650: 0.017784 | DN650: 0.034516 | DO650: -0.010065 | DP650: 0.097341 | DQ650: -0.082651 | DR650: 0.042638 | DS650: -0.042825 | DT650: -0.066421 | DV650: 0.181242 | DW650: 0.100358 | DX650: 0.023159 | DY650: 0.053911 | DZ650: 0.040966 | EA650: 0.005233 | EB650: 0.019264 | EC650: 0.135549 | ED650: 0.067697 | EE650: 0.004164 | EF650: 0.031611 | EG650: -0.019813 | EH650: 0.037602 | EI650: -0.018649 | EJ650: 0.047074 | EK650: -0.012965 | EL650: 0.026925 | EM650: -0.043898 | EN650: 0.049157 | EO650: -0.074862 | EP650: 0.009118 | EQ650: -0.133336 | ER650: -0.004978 | ES650: 0.001746 | ET650: -0.124799 | EU650: -0.039308 | EV650: -0.070351 | EW650: 0.130499 | EX650: -0.023216 | EY650: -0.090202 | EZ650: 0.053736 | FA650: 0.048669 | FB650: -0.052265 | FC650: 0.117259 | FD650: -0.019842 | FE650: 0.012199 | FF650: -0.009812 | FG650: 0.008894 | FH650: 0.090874 | FI650: 0.014205 | FJ650: -0.019595 | FK650: -0.061965 | FL650: -0.063279 | FM650: 0.099242 | FN650: 0.096129 | FO650: -0.01973 | FP650: 0.076137 | FQ650: 0.039414 | FR650: -0.059407 | FS650: 0.019381 | FT650: -0.010354 | FU650: 0.033709 | FV650: 0.014427 | FW650: 0.029627 | FX650: -0.006623 | FY650: 0.091114 | FZ650: -0.075772 | GA650: 0.036599 | GB650: -0.045902 | GC650: -0.058795
B651: =Deals!B651 -> Danaher Corporation | C651: 1 | D651: 0.019271 | E651: 0.062421 | F651: 0.152519 | G651: 0.013101 | H651: 0.043784 | I651: 0.065992 | J651: -0.021391 | K651: -0.010284 | L651: 0.070676 | M651: -0.076396 | N651: 0.025584 | O651: 0.128221 | P651: 0.008663 | Q651: 0.048528 | R651: 0.108548 | S651: 0.08965 | T651: -0.060186 | U651: 0.024077 | V651: 0.031658 | W651: 0.023567 | X651: -0.131364 | Y651: -0.039819 | Z651: 0.069859 | AA651: -0.143865 | AB651: 0.050532 | AC651: -0.038094 | AD651: 0.149692 | AE651: -0.07397 | AF651: -0.042125 | AG651: -0.02563 | AH651: 0.086383 | AI651: -0.028309 | AJ651: -0.003918 | AK651: -0.063734 | AL651: 0.019311 | AM651: -0.06003 | AN651: -0.030771 | AO651: 0.046381 | AP651: 0.06275 | AQ651: 0.038971 | AR651: -0.063774 | AS651: -0.22495 | AT651: 0.162952 | AU651: 0.037034 | AV651: 0.037045 | AW651: 0.055146 | AX651: -0.012444 | AY651: -0.012414 | AZ651: 0.041278 | BA651: -0.026012 | BB651: 0.108985 | BC651: -0.028042 | BD651: 0.033344 | BE651: -0.116395 | BF651: -0.024302 | BG651: -0.041178 | BH651: -0.029667 | BI651: -0.067253 | BJ651: -0.011744 | BM651: 0.054962 | BN651: -0.008925 | BO651: 0.053871 | BP651: 0.063251 | BQ651: -0.033897 | BR651: 0.001671 | BS651: 0.095437 | BT651: 0.018008 | BU651: -0.004263 | BV651: 0.033434 | BW651: 0.050128 | BX651: 0.057761 | BY651: 0.008179 | BZ651: 0.014271 | CA651: 0.031948 | CB651: 0.041276 | CC651: -0.062381 | CD651: 0.056413 | CE651: -0.030068 | CF651: 0.052595 | CG651: -0.063404 | CH651: -0.043294 | CI651: 0.035373 | CJ651: -0.092215 | CK651: -0.003193 | CL651: -0.055016 | CM651: 0.054082 | CN651: -0.03048 | CO651: -0.053718 | CP651: 0.074071 | CQ651: 0.066348 | CR651: -0.037114 | CS651: 0.019238 | CT651: -0.021663 | CU651: 0.032915 | CV651: 0.01434 | CW651: -0.011454 | CX651: 0.054518 | CY651: 0.062584 | CZ651: -0.00811 | DA651: -0.043722 | DB651: -0.049086 | DC651: 0.069409 | DD651: 0.047821 | DE651: -0.005114 | DF651: 0.016618 | DG651: 0.064515 | DH651: 0.01242 | DI651: 0.040278 | DJ651: 0.01096 | DK651: 0.022329 | DL651: 0.038852 | DM651: 0.039933 | DN651: -0.013064 | DO651: 0.053371 | DP651: -0.048243 | DQ651: 0.078641 | DR651: -0.01884 | DS651: -0.04998 | DV651: 0.060166 | DW651: 0.013725 | DX651: 0.051247 | DY651: 0.043716 | DZ651: -0.011563 | EA651: -0.010968 | EB651: 0.107181 | EC651: 0.030363 | ED651: -0.005163 | EE651: 0.036358 | EF651: 0.054406 | EG651: 0.037926 | EH651: 0.009424 | EI651: 0.005841 | EJ651: 0.007504 | EK651: 0.018091 | EL651: -0.045445 | EM651: 0.054598 | EN651: -0.036521 | EO651: 0.062596 | EP651: -0.052353 | EQ651: -0.01718 | ER651: 0.02918 | ES651: -0.064922 | ET651: 0.00681 | EU651: -0.072194 | EV651: 0.087506 | EW651: -0.022641 | EX651: -0.065037 | EY651: 0.097577 | EZ651: 0.065188 | FA651: -0.052193 | FB651: 0.04789 | FC651: -0.022741 | FD651: 0.007548 | FE651: 0.004502 | FF651: -0.023821 | FG651: 0.074965 | FH651: 0.043995 | FI651: -0.029982 | FJ651: -0.049891 | FK651: -0.058507 | FL651: 0.075235 | FM651: 0.064448 | FN651: -0.021101 | FO651: 0.051823 | FP651: 0.054538 | FQ651: -0.026294 | FR651: 0.028052 | FS651: -0.019401 | FT651: 0.049667 | FU651: 0.019289 | FV651: 0.028512 | FW651: -0.005521 | FX651: 0.068438 | FY651: -0.070851 | FZ651: 0.047296 | GA651: -0.021506 | GB651: -0.026357
B652: =Deals!B652 -> Roper Technologies, Inc. | C652: 1 | D652: 0.154737 | E652: -0.014068 | F652: 0.115137 | G652: -0.012163 | H652: -0.075095 | I652: -0.058862 | J652: 0.14989 | K652: 0.009578 | L652: -0.08726 | M652: -0.038915 | N652: 0.068111 | O652: 0.106858 | P652: 0.007997 | Q652: 0.044866 | R652: 0.046157 | S652: -0.016404 | T652: -0.076871 | U652: 0.094822 | V652: -0.04862 | W652: 0.059701 | X652: -0.10995 | Y652: 0.0253 | Z652: 0.053567 | AA652: -0.003579 | AB652: -0.058478 | AC652: -0.108015 | AD652: 0.108045 | AE652: -0.078068 | AF652: -0.106662 | AG652: 0.154377 | AH652: 0.05874 | AI652: -0.015494 | AJ652: -0.010778 | AK652: 0.008084 | AL652: 0.024384 | AM652: 0.033522 | AN652: -0.001231 | AO652: 0.058518 | AP652: 0.026899 | AQ652: 0.012189 | AR652: -0.029616 | AS652: 0.010269 | AT652: 0.101685 | AU652: 0.012856 | AV652: -0.01361 | AW652: 0.014395 | AX652: 0.029574 | AY652: -0.086709 | AZ652: 0.041645 | BA652: 0.058 | BB652: -0.033549 | BC652: 0.017733 | BD652: 0.003662 | BE652: -0.032277 | BF652: 0.053391 | BG652: -0.082251 | BH652: 0.108926 | BI652: 0.015374 | BJ652: 0.008691 | BM652: 0.054962 | BN652: -0.008925 | BO652: 0.053871 | BP652: 0.063251 | BQ652: -0.033897 | BR652: 0.001671 | BS652: 0.095437 | BT652: 0.018008 | BU652: -0.004263 | BV652: 0.033434 | BW652: 0.050128 | BX652: 0.057761 | BY652: 0.008179 | BZ652: 0.014271 | CA652: 0.031948 | CB652: 0.041276 | CC652: -0.062381 | CD652: 0.056413 | CE652: -0.030068 | CF652: 0.052595 | CG652: -0.063404 | CH652: -0.043294 | CI652: 0.035373 | CJ652: -0.092215 | CK652: -0.003193 | CL652: -0.055016 | CM652: 0.054082 | CN652: -0.03048 | CO652: -0.053718 | CP652: 0.074071 | CQ652: 0.066348 | CR652: -0.037114 | CS652: 0.019238 | CT652: -0.021663 | CU652: 0.032915 | CV652: 0.01434 | CW652: -0.011454 | CX652: 0.054518 | CY652: 0.062584 | CZ652: -0.00811 | DA652: -0.043722 | DB652: -0.049086 | DC652: 0.069409 | DD652: 0.047821 | DE652: -0.005114 | DF652: 0.016618 | DG652: 0.064515 | DH652: 0.01242 | DI652: 0.040278 | DJ652: 0.01096 | DK652: 0.022329 | DL652: 0.038852 | DM652: 0.039933 | DN652: -0.013064 | DO652: 0.053371 | DP652: -0.048243 | DQ652: 0.078641 | DR652: -0.01884 | DS652: -0.04998 | DV652: 0.060166 | DW652: 0.013725 | DX652: 0.051247 | DY652: 0.043716 | DZ652: -0.011563 | EA652: -0.010968 | EB652: 0.107181 | EC652: 0.030363 | ED652: -0.005163 | EE652: 0.036358 | EF652: 0.054406 | EG652: 0.037926 | EH652: 0.009424 | EI652: 0.005841 | EJ652: 0.007504 | EK652: 0.018091 | EL652: -0.045445 | EM652: 0.054598 | EN652: -0.036521 | EO652: 0.062596 | EP652: -0.052353 | EQ652: -0.01718 | ER652: 0.02918 | ES652: -0.064922 | ET652: 0.00681 | EU652: -0.072194 | EV652: 0.087506 | EW652: -0.022641 | EX652: -0.065037 | EY652: 0.097577 | EZ652: 0.065188 | FA652: -0.052193 | FB652: 0.04789 | FC652: -0.022741 | FD652: 0.007548 | FE652: 0.004502 | FF652: -0.023821 | FG652: 0.074965 | FH652: 0.043995 | FI652: -0.029982 | FJ652: -0.049891 | FK652: -0.058507 | FL652: 0.075235 | FM652: 0.064448 | FN652: -0.021101 | FO652: 0.051823 | FP652: 0.054538 | FQ652: -0.026294 | FR652: 0.028052 | FS652: -0.019401 | FT652: 0.049667 | FU652: 0.019289 | FV652: 0.028512 | FW652: -0.005521 | FX652: 0.068438 | FY652: -0.070851 | FZ652: 0.047296 | GA652: -0.021506 | GB652: -0.026357
B653: =Deals!B653 -> Maxar Technologies Inc. | C653: 1 | D653: 0.195083 | E653: 0.192435 | F653: -0.009465 | G653: 0.301293 | H653: 0.077754 | I653: 0.03328 | J653: 0.079162 | K653: 0.38799 | L653: 0.084996 | M653: 0.142823 | N653: -0.209404 | O653: 0.026177 | P653: -0.19866 | Q653: 0.283923 | R653: -0.091433 | S653: -0.123518 | T653: -0.108839 | U653: -0.0625 | V653: 0.036911 | W653: 0.073011 | X653: -0.119201 | Y653: 0.247213 | Z653: 0.216708 | AA653: -0.18373 | AB653: -0.072959 | AC653: -0.125921 | AD653: 0.053277 | AE653: -0.132824 | AF653: -0.214016 | AG653: 0.193376 | AH653: 0.083259 | AI653: 1.13843 | AJ653: -0.001353 | AK653: -0.00329 | AL653: -0.00835 | AM653: 0.032511 | AN653: -0.049448 | AO653: 0.082103 | AP653: 0.102372 | AQ653: -0.042175 | AR653: -0.063858 | AS653: -0.070333 | AT653: 0.106582 | AU653: 0.156883 | AV653: -0.059712 | AW653: 0.008072 | AX653: 0.043252 | AY653: -0.067276 | AZ653: 0.055662 | BA653: -0.02875 | BB653: 0.149324 | BC653: -0.018352 | BD653: -0.009528 | BE653: -0.009615 | BF653: 0.11257 | BG653: -0.067704 | BH653: 0.025424 | BI653: -0.042389 | BJ653: -0.072074 | BM653: 0.07167 | BN653: 0.031663 | BO653: 0.02819 | BP653: 0.091547 | BQ653: -0.051048 | BR653: 0.061753 | BS653: 0.190474 | BT653: 0.071491 | BU653: 0.089893 | BV653: 0.08839 | BW653: 0.074558 | BX653: 0.012305 | BY653: 0.071065 | BZ653: 0.004465 | CA653: -0.060784 | CB653: 0.024565 | CC653: 0.033738 | CD653: 0.028453 | CE653: -0.040391 | CF653: 0.050249 | CG653: 0.003868 | CH653: 0.027265 | CI653: -0.000287 | CJ653: -0.060679 | CK653: 0.059566 | CL653: -0.128977 | CM653: 0.092258 | CN653: -0.024771 | CO653: -0.101276 | CP653: 0.157299 | CQ653: 0.014679 | CR653: -0.056763 | CS653: 0.066881 | CT653: -0.015086 | CU653: -0.100858 | CV653: -0.029129 | CW653: -0.049448 | CX653: 0.082103 | CY653: 0.102372 | CZ653: -0.042175 | DA653: -0.063858 | DB653: -0.070333 | DC653: 0.106582 | DD653: 0.156883 | DE653: -0.059712 | DF653: 0.008072 | DG653: 0.043252 | DH653: -0.067276 | DI653: 0.055662 | DJ653: -0.02875 | DK653: 0.149324 | DL653: -0.018352 | DM653: -0.009528 | DN653: -0.009615 | DO653: 0.11257 | DP653: -0.067704 | DQ653: 0.025424 | DR653: -0.042389 | DS653: -0.072074 | DV653: 0.071711 | DW653: 0.066996 | DX653: 0.020001 | DY653: 0.09015 | DZ653: -0.059242 | EA653: 0.066831 | EB653: 0.207981 | EC653: 0.066273 | ED653: 0.082058 | EE653: 0.104681 | EF653: 0.087232 | EG653: 0.018575 | EH653: 0.064895 | EI653: -0.004041 | EJ653: -0.062834 | EK653: 0.023676 | EL653: 0.038432 | EM653: 0.027954 | EN653: -0.042826 | EO653: 0.047521 | EP653: 0.005107 | EQ653: 0.031754 | ER653: 0.002859 | ES653: -0.064882 | ET653: 0.048428 | EU653: -0.118309 | EV653: 0.088304 | EW653: -0.01777 | EX653: -0.107483 | EY653: 0.153918 | EZ653: 0.014489 | FA653: -0.056602 | FB653: 0.077091 | FC653: -0.018164 | FD653: -0.10622 | FE653: -0.03736 | FF653: -0.047588 | FG653: 0.085889 | FH653: 0.103458 | FI653: -0.027839 | FJ653: -0.069414 | FK653: -0.078196 | FL653: 0.117579 | FM653: 0.155973 | FN653: -0.059929 | FO653: 0.0096 | FP653: 0.049697 | FQ653: -0.073271 | FR653: 0.057942 | FS653: -0.038418 | FT653: 0.151899 | FU653: -0.021682 | FV653: -0.00605 | FW653: -0.013066 | FX653: 0.118278 | FY653: -0.07173 | FZ653: 0.015888 | GA653: -0.041501 | GB653: -0.079441
B654: =Deals!B654 -> T-Mobile Us, Inc. | C654: 1 | D654: 0.139408 | E654: 0.041084 | F654: 0.031013 | G654: 0.086608 | H654: -0.019883 | I654: -0.041885 | J654: 0.213288 | K654: 0.014367 | L654: -0.065035 | M654: -0.048461 | N654: 0.044344 | O654: 0.054593 | P654: 0.070537 | Q654: 0.023895 | R654: -0.005593 | S654: -0.048604 | T654: -0.067581 | U654: -0.09964 | V654: -0.054073 | W654: 0.065895 | X654: -0.067339 | Y654: 0.13904 | Z654: 0.041717 | AA654: -0.040592 | AB654: 0.082427 | AC654: 0.009378 | AD654: 0.063327 | AE654: 0.006291 | AF654: -0.068005 | AG654: 0.129612 | AH654: -0.00066 | AI654: -0.075664 | AJ654: 0.0665 | AK654: -0.047753 | AL654: 0.018709 | AM654: -0.00649 | AN654: -0.046213 | AO654: 0.012022 | AP654: -0.008135 | AQ654: -0.011033 | AR654: 0.02789 | AS654: 0.027205 | AT654: 0.050327 | AU654: 0.06567 | AV654: 0.005613 | AW654: 0.01687 | AX654: -0.00049 | AY654: 0.00582 | AZ654: 0.065725 | BA654: 0.006973 | BB654: 0.034624 | BC654: 0.093757 | BD654: 0.038446 | BE654: 0.081411 | BF654: 0.110504 | BG654: -0.106139 | BH654: 0.055452 | BI654: 0.161394 | BJ654: -0.01105 | BM654: 0.054962 | BN654: -0.008925 | BO654: 0.053871 | BP654: 0.063251 | BQ654: -0.033897 | BR654: 0.001671 | BS654: 0.095437 | BT654: 0.018008 | BU654: -0.004263 | BV654: 0.033434 | BW654: 0.050128 | BX654: 0.057761 | BY654: 0.008179 | BZ654: 0.014271 | CA654: 0.031948 | CB654: 0.041276 | CC654: -0.062381 | CD654: 0.056413 | CE654: -0.030068 | CF654: 0.052595 | CG654: -0.063404 | CH654: -0.043294 | CI654: 0.035373 | CJ654: -0.092215 | CK654: -0.003193 | CL654: -0.055016 | CM654: 0.054082 | CN654: -0.03048 | CO654: -0.053718 | CP654: 0.074071 | CQ654: 0.066348 | CR654: -0.037114 | CS654: 0.019238 | CT654: -0.021663 | CU654: 0.032915 | CV654: 0.01434 | CW654: -0.011454 | CX654: 0.054518 | CY654: 0.062584 | CZ654: -0.00811 | DA654: -0.043722 | DB654: -0.049086 | DC654: 0.069409 | DD654: 0.047821 | DE654: -0.005114 | DF654: 0.016618 | DG654: 0.064515 | DH654: 0.01242 | DI654: 0.040278 | DJ654: 0.01096 | DK654: 0.022329 | DL654: 0.038852 | DM654: 0.039933 | DN654: -0.013064 | DO654: 0.053371 | DP654: -0.048243 | DQ654: 0.078641 | DR654: -0.01884 | DS654: -0.04998 | DV654: 0.060166 | DW654: 0.013725 | DX654: 0.051247 | DY654: 0.043716 | DZ654: -0.011563 | EA654: -0.010968 | EB654: 0.107181 | EC654: 0.030363 | ED654: -0.005163 | EE654: 0.036358 | EF654: 0.054406 | EG654: 0.037926 | EH654: 0.009424 | EI654: 0.005841 | EJ654: 0.007504 | EK654: 0.018091 | EL654: -0.045445 | EM654: 0.054598 | EN654: -0.036521 | EO654: 0.062596 | EP654: -0.052353 | EQ654: -0.01718 | ER654: 0.02918 | ES654: -0.064922 | ET654: 0.00681 | EU654: -0.072194 | EV654: 0.087506 | EW654: -0.022641 | EX654: -0.065037 | EY654: 0.097577 | EZ654: 0.065188 | FA654: -0.052193 | FB654: 0.04789 | FC654: -0.022741 | FD654: 0.007548 | FE654: 0.004502 | FF654: -0.023821 | FG654: 0.074965 | FH654: 0.043995 | FI654: -0.029982 | FJ654: -0.049891 | FK654: -0.058507 | FL654: 0.075235 | FM654: 0.064448 | FN654: -0.021101 | FO654: 0.051823 | FP654: 0.054538 | FQ654: -0.026294 | FR654: 0.028052 | FS654: -0.019401 | FT654: 0.049667 | FU654: 0.019289 | FV654: 0.028512 | FW654: -0.005521 | FX654: 0.068438 | FY654: -0.070851 | FZ654: 0.047296 | GA654: -0.021506 | GB654: -0.026357
B655: =Deals!B655 -> Cornerstone OnDemand Inc | C655: 1 | D655: 0.151669 | E655: -0.002329 | F655: -0.079098 | G655: -0.006759 | H655: 0.030904 | I655: 0.044829 | J655: 0.162148 | K655: -0.002492 | L655: -0.071299 | M655: 0.235208 | N655: -0.137371 | O655: 0.015718 | P655: -0.006664 | Q655: 0.173073 | R655: -0.07057 | S655: 0.195244 | T655: -0.000698 | U655: 0.046626 | V655: -0.08576 | W655: 0.000968 | X655: -0.142109 | Y655: -0.007716 | Z655: 0.017833 | AA655: -0.117955 | AB655: -0.053077 | AC655: -0.044319 | AD655: 0.116268 | AE655: -0.038541 | AF655: -0.088512 | AG655: 0.034639 | AH655: 0.031372 | AI655: -0.043533 | AJ655: 0.106176 | AK655: -0.003618 | AL655: -0.008652 | AM655: -0.032515 | AN655: 0.010489 | AO655: 0.068229 | AP655: 0.053331 | AQ655: -0.053394 | AR655: -0.058727 | AS655: -0.073528 | AT655: 0.111124 | AU655: 0.103291 | AV655: -0.042161 | AW655: 0.032515 | AX655: 0.006384 | AY655: -0.06286 | AZ655: 0.046483 | BA655: 0.028059 | BB655: 0.064974 | BC655: -0.001472 | BD655: 0.042635 | BE655: -0.016588 | BF655: 0.102793 | BG655: -0.079478 | BH655: 0.053794 | BI655: -0.056928 | BJ655: -0.07451 | BM655: 0.124257 | BN655: 0.046007 | BO655: 0.011045 | BP655: 0.084196 | BQ655: -0.031087 | BR655: 0.030388 | BS655: 0.207556 | BT655: 0.12645 | BU655: 0.024415 | BV655: -0.000483 | BW655: -0.047837 | BX655: 0.02869 | BY655: -0.033421 | BZ655: 0.054695 | CA655: -0.02501 | CB655: 0.019022 | CC655: -0.038561 | CD655: 0.046626 | CE655: -0.08576 | CF655: 0.000968 | CG655: -0.142109 | CH655: -0.007716 | CI655: 0.017833 | CJ655: -0.117955 | CK655: -0.053077 | CL655: -0.044319 | CM655: 0.116268 | CN655: -0.038541 | CO655: -0.088512 | CP655: 0.034639 | CQ655: 0.031372 | CR655: -0.043533 | CS655: 0.106176 | CT655: -0.003618 | CU655: -0.008652 | CV655: -0.032515 | CW655: 0.010489 | CX655: 0.068229 | CY655: 0.053331 | CZ655: -0.053394 | DA655: -0.058727 | DB655: -0.073528 | DC655: 0.111124 | DD655: 0.103291 | DE655: -0.042161 | DF655: 0.032515 | DG655: 0.006384 | DH655: -0.06286 | DI655: 0.046483 | DJ655: 0.028059 | DK655: 0.064974 | DL655: -0.001472 | DM655: 0.042635 | DN655: -0.016588 | DO655: 0.102793 | DP655: -0.079478 | DQ655: 0.053794 | DR655: -0.056928 | DS655: -0.07451 | DV655: 0.118762 | DW655: 0.046814 | DX655: 0.008228 | DY655: 0.084717 | DZ655: -0.030373 | EA655: 0.034269 | EB655: 0.21392 | EC655: 0.129432 | ED655: 0.017059 | EE655: 0.021424 | EF655: -0.036464 | EG655: 0.030769 | EH655: -0.028421 | EI655: 0.061708 | EJ655: -0.023545 | EK655: 0.015868 | EL655: -0.039964 | EM655: 0.047113 | EN655: -0.084736 | EO655: -0.003415 | EP655: -0.141596 | EQ655: -0.016339 | ER655: 0.004296 | ES655: -0.138311 | ET655: -0.045222 | EU655: -0.046504 | EV655: 0.116767 | EW655: -0.030875 | EX655: -0.092886 | EY655: 0.038196 | EZ655: 0.031364 | FA655: -0.050589 | FB655: 0.12749 | FC655: -0.008377 | FD655: -0.018392 | FE655: -0.031244 | FF655: 0.024876 | FG655: 0.074528 | FH655: 0.058153 | FI655: -0.055866 | FJ655: -0.061774 | FK655: -0.07758 | FL655: 0.128905 | FM655: 0.115622 | FN655: -0.04519 | FO655: 0.029184 | FP655: 0.003445 | FQ655: -0.066565 | FR655: 0.07274 | FS655: 0.026772 | FT655: 0.068904 | FU655: -0.001826 | FV655: 0.034451 | FW655: -0.012354 | FX655: 0.129517 | FY655: -0.079792 | FZ655: 0.048261 | GA655: -0.057773 | GB655: -0.075988
B656: =Deals!B656 -> Novavax, Inc. | C656: 1 | D656: 0.810382 | E656: 0.716857 | F656: -0.228931 | G656: -0.018035 | H656: -0.255099 | I656: 0.72841 | J656: -0.200645 | K656: 0.981347 | L656: 0.046574 | M656: -0.215889 | N656: 0.306767 | O656: -0.376947 | P656: 0.43822 | Q656: -0.155339 | R656: 0.330173 | S656: -0.130921 | T656: -0.28209 | U656: 0.401801 | V656: -0.314241 | W656: -0.345076 | X656: -0.110245 | Y656: -0.116589 | Z656: -0.388052 | AA656: 0.227646 | AB656: -0.070486 | AC656: 0.059887 | AD656: -0.393873 | AE656: -0.449153 | AF656: 0.223626 | AG656: -0.259542 | AH656: -0.376592 | AI656: 0.061284 | AJ656: -0.151237 | AK656: -0.25162 | AL656: 0.106782 | AM656: 0.049544 | AN656: -0.077019 | AO656: 0.248991 | AP656: -0.137931 | AQ656: -0.095 | AR656: -0.08011 | AS656: -0.174174 | AT656: -0.127273 | AU656: -0.166667 | AV656: 0.235 | AW656: -0.032389 | AX656: -0.094142 | AY656: 2.471132 | AZ656: -0.157685 | BA656: 0.011848 | BB656: -0.033568 | BC656: 0.020194 | BD656: -0.239113 | BE656: -0.092612 | BF656: -0.077982 | BG656: 0.080846 | BH656: -0.041427 | BI656: -0.230492 | BM656: 0.05686 | BN656: 0.007253 | BO656: 0.079862 | BP656: 0.003401 | BQ656: -0.019809 | BR656: 0.214791 | BS656: 0.115065 | BT656: 0.116678 | BU656: 0.040745 | BV656: -0.048473 | BW656: 0.032353 | BX656: -0.025949 | BY656: 0.06983 | BZ656: -0.075376 | CA656: 0.020545 | CB656: -0.052806 | CC656: 0.024457 | CD656: -0.080613 | CE656: -0.005266 | CF656: -0.163775 | CG656: -0.001611 | CH656: 0.012199 | CI656: -0.180685 | CJ656: -0.032766 | CK656: -0.019338 | CL656: 0.128546 | CM656: 0.036743 | CN656: -0.088022 | CO656: 0.076143 | CP656: -0.002315 | CQ656: -0.050589 | CR656: 0.141421 | CS656: -0.040665 | CT656: -0.034632 | CU656: -0.027967 | CV656: 0.012513 | CW656: 0.070349 | CX656: 0.041532 | CY656: -0.071954 | CZ656: -0.091371 | DA656: -0.101457 | DB656: 0.108746 | DC656: 0.122171 | DD656: -0.039346 | DE656: 0.094637 | DF656: 0.003944 | DG656: -0.069152 | DH656: 0.019278 | DI656: -0.016837 | DJ656: 0.075097 | DK656: 0.006764 | DL656: 0.000931 | DM656: -0.008068 | DN656: 0.14058 | DO656: -0.041389 | DP656: 0.005532 | DQ656: -0.084494 | DR656: -0.082801 | DV656: 0.060359 | DW656: 0.001874 | DX656: 0.087533 | DY656: -0.011573 | DZ656: -0.028636 | EA656: 0.206308 | EB656: 0.094331 | EC656: 0.112618 | ED656: 0.051624 | EE656: -0.046095 | EF656: 0.028573 | EG656: -0.026132 | EH656: 0.06635 | EI656: -0.076813 | EJ656: 0.018217 | EK656: -0.053317 | EL656: 0.021146 | EM656: -0.091985 | EN656: -0.014805 | EO656: -0.173369 | EP656: -0.012789 | EQ656: 0.018464 | ER656: -0.198696 | ES656: -0.057167 | ET656: -0.02625 | EU656: 0.129928 | EV656: 0.030138 | EW656: -0.081445 | EX656: 0.087294 | EY656: -0.006501 | EZ656: -0.051629 | FA656: 0.164361 | FB656: -0.049102 | FC656: -0.042333 | FD656: -0.043651 | FE656: 0.027983 | FF656: 0.075292 | FG656: 0.041174 | FH656: -0.071456 | FI656: -0.098155 | FJ656: -0.110132 | FK656: 0.107279 | FL656: 0.142226 | FM656: -0.046726 | FN656: 0.099012 | FO656: -0.006566 | FP656: -0.088553 | FQ656: 0.04379 | FR656: -0.01381 | FS656: 0.076992 | FT656: -0.007169 | FU656: -0.005011 | FV656: -0.001446 | FW656: 0.13118 | FX656: -0.044324 | FY656: 0.027517 | FZ656: -0.087576 | GA656: -0.080425
B657: =Deals!B657 -> ModivCare Inc. | C657: 1 | D657: -0.019752 | E657: 0.026613 | F657: 0.142945 | G657: 0.003456 | H657: 0.265203 | I657: 0.155168 | J657: 0.020915 | K657: 0.143836 | L657: -0.191146 | M657: 0.154842 | N657: -0.05428 | O657: 0.051042 | P657: 0.155131 | Q657: -0.000412 | R657: 0.160353 | S657: -0.079286 | T657: -0.103788 | U657: -0.158137 | V657: 0.082172 | W657: -0.218221 | X657: 0.017856 | Y657: -0.022119 | Z657: -0.098969 | AA657: -0.082139 | AB657: -0.114534 | AC657: 0.181065 | AD657: 0.085371 | AE657: -0.079764 | AF657: -0.024478 | AG657: -0.208145 | AH657: 0.165325 | AI657: 0.195364 | AJ657: -0.084561 | AK657: -0.143701 | AL657: -0.243578 | AM657: -0.293553 | AN657: 0.006232 | AO657: -0.032515 | AP657: -0.266118 | AQ657: -0.01838 | AR657: 0.340527 | AS657: -0.106061 | AT657: 0.164989 | AU657: -0.095931 | AV657: -0.294946 | AW657: -0.163695 | AX657: 0.000853 | AY657: 0.164039 | AZ657: -0.039531 | BA657: -0.130335 | BB657: 0.26468 | BC657: -0.505198 | BD657: 0.132353 | BE657: 0.162028 | BF657: -0.369878 | BG657: -0.662162 | BH657: -0.175 | BI657: -0.601515 | BM657: 0.028131 | BN657: 0.035905 | BO657: 0.069178 | BP657: -0.047385 | BQ657: 0.03365 | BR657: 0.188158 | BS657: 0.101547 | BT657: 0.049816 | BU657: 0.086155 | BV657: -0.008262 | BW657: 0.015677 | BX657: 0.002446 | BY657: 0.035313 | BZ657: -0.028278 | CA657: 0.024312 | CB657: -0.041121 | CC657: 0.023534 | CD657: -0.034555 | CE657: 0.001539 | CF657: -0.116597 | CG657: 0.020508 | CH657: 0.022185 | CI657: -0.119564 | CJ657: -0.028738 | CK657: -0.063921 | CL657: 0.135102 | CM657: -0.007929 | CN657: -0.088004 | CO657: 0.092762 | CP657: -0.018141 | CQ657: -0.073757 | CR657: 0.160132 | CS657: -0.029084 | CT657: -0.030294 | CU657: 0.000974 | CV657: 0.034374 | CW657: 0.071376 | CX657: 0.055658 | CY657: -0.070227 | CZ657: -0.055895 | DA657: -0.076043 | DB657: 0.090818 | DC657: 0.141331 | DD657: -0.03884 | DE657: 0.062772 | DF657: 0.020685 | DG657: -0.08132 | DH657: 0.03247 | DI657: -0.016085 | DJ657: 0.096359 | DK657: 0.002008 | DL657: 0.012156 | DM657: -0.00881 | DN657: 0.132864 | DO657: -0.092084 | DP657: 0.027376 | DQ657: -0.087184 | DR657: -0.07152 | DV657: 0.042922 | DW657: 0.025254 | DX657: 0.076086 | DY657: -0.053883 | DZ657: 0.035066 | EA657: 0.203256 | EB657: 0.100877 | EC657: 0.053073 | ED657: 0.075831 | EE657: -0.001805 | EF657: 0.008333 | EG657: -0.008533 | EH657: 0.032572 | EI657: -0.030216 | EJ657: 0.020798 | EK657: -0.040113 | EL657: 0.024885 | EM657: -0.052054 | EN657: 0.002106 | EO657: -0.122474 | EP657: 0.004163 | EQ657: 0.029007 | ER657: -0.150847 | ES657: -0.038851 | ET657: -0.043457 | EU657: 0.133239 | EV657: 0.00337 | EW657: -0.088268 | EX657: 0.09263 | EY657: -0.008961 | EZ657: -0.073196 | FA657: 0.179925 | FB657: -0.037455 | FC657: -0.045087 | FD657: -0.007067 | FE657: 0.026671 | FF657: 0.081708 | FG657: 0.048745 | FH657: -0.067184 | FI657: -0.056578 | FJ657: -0.086289 | FK657: 0.096397 | FL657: 0.143956 | FM657: -0.055801 | FN657: 0.059786 | FO657: 0.003677 | FP657: -0.079926 | FQ657: 0.024106 | FR657: -0.027662 | FS657: 0.104449 | FT657: -0.005668 | FU657: 0.005186 | FV657: -0.005121 | FW657: 0.118651 | FX657: -0.083389 | FY657: 0.025358 | FZ657: -0.082682 | GA657: -0.0774
B658: =Deals!B658 -> AbbVie Inc. | C658: 1 | D658: 0.059458 | E658: -0.021287 | F658: 0.009061 | G658: -0.085413 | H658: -0.014956 | I658: 0.228907 | J658: 0.024574 | K658: -0.031451 | L658: 0.051327 | M658: 0.004455 | N658: 0.042321 | O658: 0.015247 | P658: -0.004947 | Q658: 0.044034 | R658: 0.038521 | S658: -0.106889 | T658: 0.07509 | U658: 0.00532 | V658: 0.174532 | W658: 0.021418 | X658: 0.07948 | Y658: 0.097043 | Z658: -0.085251 | AA658: 0.003336 | AB658: 0.039289 | AC658: -0.0538 | AD658: -0.063062 | AE658: -0.001859 | AF658: 0.101334 | AG658: 0.100956 | AH658: 0.002668 | AI658: -0.076604 | AJ658: 0.041624 | AK658: 0.035543 | AL658: -0.04248 | AM658: -0.087083 | AN658: -0.023413 | AO658: 0.121205 | AP658: -0.017516 | AQ658: 0.01429 | AR658: -0.042936 | AS658: 0.008571 | AT658: 0.088349 | AU658: 0.070852 | AV658: 0.070864 | AW658: 0.034365 | AX658: -0.098353 | AY658: -0.008608 | AZ658: 0.063756 | BA658: 0.089494 | BB658: 0.059303 | BC658: 0.00596 | BD658: 0.040207 | BE658: -0.102713 | BF658: -0.02859 | BG658: 0.044119 | BH658: 0.13665 | BI658: 0.002344 | BM658: 0.050972 | BN658: 0.07725 | BO658: 0.107972 | BP658: -0.045521 | BQ658: -0.045743 | BR658: 0.107281 | BS658: 0.053002 | BT658: -0.009351 | BU658: -0.005854 | BV658: 0.01839 | BW658: 0.059373 | BX658: -0.013515 | BY658: 0.057192 | BZ658: 0.032936 | CA658: 0.033156 | CB658: -0.052802 | CC658: 0.089956 | CD658: 0.012325 | CE658: 0.021218 | CF658: -0.077613 | CG658: -0.033277 | CH658: 0.048718 | CI658: -0.10863 | CJ658: -0.030079 | CK658: -0.078069 | CL658: 0.127169 | CM658: -0.053498 | CN658: -0.100388 | CO658: 0.052883 | CP658: 0.047454 | CQ658: -0.082033 | CR658: 0.087217 | CS658: -0.01317 | CT658: 0.081256 | CU658: 0.01129 | CV658: 0.054991 | CW658: 0.072447 | CX658: 0.023838 | CY658: -0.008326 | CZ658: -0.05542 | DA658: -0.009954 | DB658: 0.098907 | DC658: 0.037524 | DD658: 0.022668 | DE658: 0.060191 | DF658: 0.016533 | DG658: -0.040193 | DH658: 0.059598 | DI658: 0.061092 | DJ658: -0.008513 | DK658: 0.021543 | DL658: 0.024194 | DM658: -0.007924 | DN658: 0.063182 | DO658: 0.003266 | DP658: 0.014885 | DQ658: -0.031109 | DR658: -0.076633 | DV658: 0.018928 | DW658: 0.070143 | DX658: 0.054124 | DY658: -0.020604 | DZ658: -0.021628 | EA658: 0.130555 | EB658: 0.041795 | EC658: -0.018249 | ED658: 0.019443 | EE658: 0.020896 | EF658: 0.053291 | EG658: -0.004423 | EH658: 0.043268 | EI658: 0.030241 | EJ658: 0.029029 | EK658: -0.051931 | EL658: 0.076494 | EM658: -0.023675 | EN658: 0.027244 | EO658: -0.105932 | EP658: -0.028087 | EQ658: 0.024591 | ER658: -0.102794 | ES658: -0.042047 | ET658: -0.081421 | EU658: 0.115932 | EV658: -0.040409 | EW658: -0.09131 | EX658: 0.077555 | EY658: 0.068696 | EZ658: -0.064949 | FA658: 0.083649 | FB658: -0.013406 | FC658: 0.044705 | FD658: -0.010179 | FE658: 0.017315 | FF658: 0.073915 | FG658: 0.027187 | FH658: -0.023523 | FI658: -0.051409 | FJ658: -0.03327 | FK658: 0.105435 | FL658: 0.064066 | FM658: 0.005583 | FN658: 0.053753 | FO658: 0.021634 | FP658: -0.048148 | FQ658: 0.010258 | FR658: 0.019325 | FS658: 0.000127 | FT658: 0.029717 | FU658: 0.023121 | FV658: -0.009897 | FW658: 0.082276 | FX658: -0.042846 | FY658: 0.045785 | FZ658: -0.023907 | GA658: -0.062674
B659: =Deals!B659 -> Silgan Holdings Inc | C659: 1 | D659: 0.18092 | E659: -0.00183 | F659: -0.033894 | G659: -0.063095 | H659: -0.015385 | I659: 0.097041 | J659: -0.01753 | K659: 0.031018 | L659: 0.122737 | M659: 0.003331 | N659: 0.002371 | O659: -0.014954 | P659: -0.023614 | Q659: 0.050592 | R659: -0.095923 | S659: 0.047967 | T659: 0.035075 | U659: 0.033036 | V659: 0.045285 | W659: -0.064761 | X659: 0.107689 | Y659: -0.040234 | Z659: -0.009015 | AA659: -0.056152 | AB659: 0.076179 | AC659: 0.027191 | AD659: -0.077058 | AE659: 0.126546 | AF659: 0.120355 | AG659: -0.020038 | AH659: 0.039545 | AI659: -0.009093 | AJ659: 0.008427 | AK659: -0.082169 | AL659: -0.083029 | AM659: 0.042232 | AN659: -0.064833 | AO659: 0.033295 | AP659: -0.04476 | AQ659: -0.070749 | AR659: 0.045931 | AS659: 0.084612 | AT659: 0.015249 | AU659: -0.044188 | AV659: 0.110225 | AW659: -0.039127 | AX659: 0.012645 | AY659: -0.100106 | AZ659: 0.214978 | BA659: 0.016333 | BB659: 0.008035 | BC659: -0.014476 | BD659: 0.111906 | BE659: -0.091952 | BF659: 0.057061 | BG659: -0.012904 | BH659: -0.055054 | BM659: 0.037942 | BN659: 0.055215 | BO659: -0.011854 | BP659: 0.020769 | BQ659: 0.176056 | BR659: 0.08836 | BS659: 0.00942 | BT659: 0.079959 | BU659: 0.025467 | BV659: 0.039993 | BW659: -0.007853 | BX659: 0.001045 | BY659: -0.008307 | BZ659: 0.01354 | CA659: -0.039939 | CB659: 0.038484 | CC659: -0.021291 | CD659: 0.044855 | CE659: -0.101419 | CF659: 0.005679 | CG659: 0.008371 | CH659: -0.076092 | CI659: 0.009316 | CJ659: -0.073263 | CK659: 0.117887 | CL659: -0.03435 | CM659: -0.091984 | CN659: 0.09267 | CO659: 0.054291 | CP659: -0.075471 | CQ659: 0.127305 | CR659: -0.012527 | CS659: -0.00927 | CT659: -0.004757 | CU659: -0.021191 | CV659: 0.089021 | CW659: 0.032669 | CX659: -0.044226 | CY659: -0.046387 | CZ659: -0.06206 | DA659: 0.074219 | DB659: 0.108568 | DC659: -0.030991 | DD659: 0.05521 | DE659: 0.028812 | DF659: -0.062882 | DG659: 0.051154 | DH659: -0.00855 | DI659: 0.060491 | DJ659: -0.020629 | DK659: 0.023503 | DL659: -0.027289 | DM659: 0.111932 | DN659: -0.079098 | DO659: 0.028509 | DP659: -0.049352 | DQ659: -0.068196 | DV659: 0.039286 | DW659: 0.050398 | DX659: -0.010098 | DY659: 0.031145 | DZ659: 0.183067 | EA659: 0.08896 | EB659: 0.013987 | EC659: 0.089016 | ED659: 0.028616 | EE659: 0.03792 | EF659: -0.009349 | EG659: 0.003632 | EH659: -0.007576 | EI659: 0.0162 | EJ659: -0.038653 | EK659: 0.035353 | EL659: -0.023202 | EM659: 0.045936 | EN659: -0.099006 | EO659: -0.001334 | EP659: 0.010422 | EQ659: -0.081153 | ER659: 0.007554 | ES659: -0.063068 | ET659: 0.12091 | EU659: -0.033799 | EV659: -0.094081 | EW659: 0.091652 | EX659: 0.062795 | EY659: -0.069898 | EZ659: 0.136796 | FA659: -0.019023 | FB659: -0.011326 | FC659: -0.003019 | FD659: -0.022705 | FE659: 0.084591 | FF659: 0.036865 | FG659: -0.046647 | FH659: -0.049839 | FI659: -0.066086 | FJ659: 0.082842 | FK659: 0.115153 | FL659: -0.037422 | FM659: 0.047999 | FN659: 0.024713 | FO659: -0.074428 | FP659: 0.050026 | FQ659: -0.009515 | FR659: 0.060442 | FS659: -0.020796 | FT659: 0.019958 | FU659: -0.025874 | FV659: 0.113772 | FW659: -0.072511 | FX659: 0.021458 | FY659: -0.05812 | FZ659: -0.071289
B660: =Deals!B660 -> WESCO International, Inc. | C660: 1 | D660: 0.107092 | E660: 0.2053 | F660: -0.060406 | G660: -0.063153 | H660: 0.581474 | I660: 0.203619 | J660: -0.030446 | K660: 0.054789 | L660: 0.077853 | M660: 0.059979 | N660: 0.161906 | O660: -0.035188 | P660: 0.035304 | Q660: 0.099295 | R660: -0.014527 | S660: 0.123482 | T660: -0.041911 | U660: 0.060098 | V660: -0.073714 | W660: -0.001313 | X660: 0.069087 | Y660: -0.052866 | Z660: 0.018822 | AA660: -0.147157 | AB660: 0.193651 | AC660: 0.030038 | AD660: -0.093408 | AE660: 0.154046 | AF660: -0.064237 | AG660: -0.028855 | AH660: 0.190176 | AI660: 0.111201 | AJ660: -0.06441 | AK660: -0.068202 | AL660: -0.045972 | AM660: 0.306122 | AN660: -0.019491 | AO660: -0.078145 | AP660: -0.109082 | AQ660: -0.108608 | AR660: 0.215679 | AS660: 0.118094 | AT660: -0.00207 | AU660: -0.138485 | AV660: 0.148525 | AW660: -0.108185 | AX660: 0.175057 | AY660: -0.11453 | AZ660: 0.103646 | BA660: -0.054701 | BB660: 0.018216 | BC660: 0.142815 | BD660: 0.102099 | BE660: -0.142731 | BF660: 0.022325 | BG660: -0.024486 | BH660: -0.136955 | BM660: 0.02819 | BN660: 0.091547 | BO660: -0.051048 | BP660: 0.061753 | BQ660: 0.190474 | BR660: 0.071491 | BS660: 0.089893 | BT660: 0.08839 | BU660: 0.074558 | BV660: 0.012305 | BW660: 0.071065 | BX660: 0.004465 | BY660: -0.060784 | BZ660: 0.024565 | CA660: 0.033738 | CB660: 0.028453 | CC660: -0.040391 | CD660: 0.050249 | CE660: 0.003868 | CF660: 0.027265 | CG660: -0.000287 | CH660: -0.060679 | CI660: 0.059566 | CJ660: -0.128977 | CK660: 0.092258 | CL660: -0.024771 | CM660: -0.101276 | CN660: 0.157299 | CO660: 0.014679 | CP660: -0.056763 | CQ660: 0.066881 | CR660: -0.015086 | CS660: -0.100858 | CT660: -0.029129 | CU660: -0.049448 | CV660: 0.082103 | CW660: 0.102372 | CX660: -0.042175 | CY660: -0.063858 | CZ660: -0.070333 | DA660: 0.106582 | DB660: 0.156883 | DC660: -0.059712 | DD660: 0.008072 | DE660: 0.043252 | DF660: -0.067276 | DG660: 0.055662 | DH660: -0.02875 | DI660: 0.149324 | DJ660: -0.018352 | DK660: -0.009528 | DL660: -0.009615 | DM660: 0.11257 | DN660: -0.067704 | DO660: 0.025424 | DP660: -0.042389 | DQ660: -0.072074 | DV660: 0.020001 | DW660: 0.09015 | DX660: -0.059242 | DY660: 0.066831 | DZ660: 0.207981 | EA660: 0.066273 | EB660: 0.082058 | EC660: 0.104681 | ED660: 0.087232 | EE660: 0.018575 | EF660: 0.064895 | EG660: -0.004041 | EH660: -0.062834 | EI660: 0.023676 | EJ660: 0.038432 | EK660: 0.027954 | EL660: -0.042826 | EM660: 0.047521 | EN660: 0.005107 | EO660: 0.031754 | EP660: 0.002859 | EQ660: -0.064882 | ER660: 0.048428 | ES660: -0.118309 | ET660: 0.088304 | EU660: -0.01777 | EV660: -0.107483 | EW660: 0.153918 | EX660: 0.014489 | EY660: -0.056602 | EZ660: 0.077091 | FA660: -0.018164 | FB660: -0.10622 | FC660: -0.03736 | FD660: -0.047588 | FE660: 0.085889 | FF660: 0.103458 | FG660: -0.027839 | FH660: -0.069414 | FI660: -0.078196 | FJ660: 0.117579 | FK660: 0.155973 | FL660: -0.059929 | FM660: 0.0096 | FN660: 0.049697 | FO660: -0.073271 | FP660: 0.057942 | FQ660: -0.038418 | FR660: 0.151899 | FS660: -0.021682 | FT660: -0.00605 | FU660: -0.013066 | FV660: 0.118278 | FW660: -0.07173 | FX660: 0.015888 | FY660: -0.041501 | FZ660: -0.079441
B661: =Deals!B661 -> Supernus Pharmaceuticals, Inc. | C661: 1 | D661: -0.062316 | E661: -0.012573 | F661: -0.052296 | G661: -0.119002 | H661: 0.160131 | I661: 0.181221 | J661: 0.168124 | K661: -0.085743 | L661: -0.025679 | M661: 0.163102 | N661: -0.019704 | O661: 0.031491 | P661: -0.144852 | Q661: 0.045575 | R661: -0.031239 | S661: 0.119235 | T661: 0.00402 | U661: -0.027027 | V661: 0.057956 | W661: 0.035656 | X661: 0.011581 | Y661: -0.136757 | Z661: -0.001075 | AA661: 0.037675 | AB661: 0.097856 | AC661: 0.07811 | AD661: -0.011101 | AE661: 0.012408 | AF661: 0.071491 | AG661: -0.028595 | AH661: 0.149706 | AI661: -0.083394 | AJ661: -0.03618 | AK661: 0.017389 | AL661: -0.100922 | AM661: -0.092939 | AN661: 0.020958 | AO661: 0.037471 | AP661: -0.134108 | AQ661: -0.134929 | AR661: 0.142558 | AS661: 0.062018 | AT661: -0.043538 | AU661: 0.072977 | AV661: 0.148485 | AW661: -0.117561 | AX661: -0.099003 | AY661: -0.013643 | AZ661: 0.114766 | BA661: 0.179074 | BB661: -0.113197 | BC661: 0.092688 | BD661: 0.073378 | BE661: -0.011211 | BF661: 0.061117 | BG661: -0.164451 | BH661: 0.021522 | BM661: 0.036019 | BN661: 0.045969 | BO661: -0.050916 | BP661: 0.024776 | BQ661: 0.183297 | BR661: 0.08958 | BS661: 0.077042 | BT661: 0.09566 | BU661: 0.02182 | BV661: 0.023396 | BW661: 0.011055 | BX661: 0.012853 | BY661: -0.018155 | BZ661: 0.013589 | CA661: -0.034063 | CB661: 0.039859 | CC661: 0.0057 | CD661: 0.0589 | CE661: -0.095829 | CF661: 0.005483 | CG661: 0.017931 | CH661: -0.080424 | CI661: 0.023442 | CJ661: -0.072115 | CK661: 0.115972 | CL661: -0.044554 | CM661: -0.114803 | CN661: 0.104466 | CO661: 0.004422 | CP661: -0.070133 | CQ661: 0.1231 | CR661: -0.00465 | CS661: -0.032965 | CT661: -0.032649 | CU661: 0.019558 | CV661: 0.091615 | CW661: 0.061544 | CX661: -0.036861 | CY661: -0.046311 | CZ661: -0.069716 | DA661: 0.086093 | DB661: 0.108974 | DC661: -0.035745 | DD661: 0.06812 | DE661: 0.025352 | DF661: -0.065718 | DG661: 0.052673 | DH661: -0.021843 | DI661: 0.098444 | DJ661: -0.036221 | DK661: 0.009113 | DL661: -0.032464 | DM661: 0.108871 | DN661: -0.087427 | DO661: 0.036021 | DP661: -0.082942 | DQ661: -0.084026 | DV661: 0.029421 | DW661: 0.038437 | DX661: -0.05288 | DY661: 0.030608 | DZ661: 0.193071 | EA661: 0.097805 | EB661: 0.082572 | EC661: 0.092176 | ED661: 0.032457 | EE661: 0.023833 | EF661: 0.016413 | EG661: 0.003494 | EH661: -0.023492 | EI661: 0.010659 | EJ661: -0.035282 | EK661: 0.041156 | EL661: -0.003587 | EM661: 0.054826 | EN661: -0.097752 | EO661: 0.003239 | EP661: 0.007621 | EQ661: -0.080781 | ER661: 0.012501 | ES661: -0.060414 | ET661: 0.113842 | EU661: -0.039008 | EV661: -0.119468 | EW661: 0.105606 | EX661: 0.003522 | EY661: -0.065539 | EZ661: 0.134282 | FA661: -0.02221 | FB661: -0.049024 | FC661: -0.025935 | FD661: 0.015862 | FE661: 0.096287 | FF661: 0.061646 | FG661: -0.040878 | FH661: -0.054465 | FI661: -0.078234 | FJ661: 0.101981 | FK661: 0.125443 | FL661: -0.045067 | FM661: 0.078133 | FN661: 0.031478 | FO661: -0.080992 | FP661: 0.054415 | FQ661: -0.025984 | FR661: 0.100317 | FS661: -0.040457 | FT661: 0.012299 | FU661: -0.028165 | FV661: 0.103669 | FW661: -0.083363 | FX661: 0.030766 | FY661: -0.088055 | FZ661: -0.091066
B662: =Deals!B662 -> Synaptics Incorporated | C662: 1 | D662: 0.066358 | E662: -0.057541 | F662: -0.04663 | G662: 0.014347 | H662: 0.239553 | I662: 0.029253 | J662: 0.350837 | K662: 0.010371 | L662: 0.032861 | M662: -0.096804 | N662: 0.231536 | O662: -0.023525 | P662: 0.24921 | Q662: -0.052956 | R662: 0.082568 | S662: 0.450583 | T662: 0.025758 | U662: -0.273428 | V662: 0.085952 | W662: -0.126647 | X662: -0.25594 | Y662: -0.002156 | Z662: -0.203011 | AA662: 0.22787 | AB662: -0.202415 | AC662: -0.143586 | AD662: -0.105141 | AE662: 0.19605 | AF662: -0.10201 | AG662: 0.127305 | AH662: -0.012527 | AI662: -0.00927 | AJ662: -0.004757 | AK662: -0.021191 | AL662: 0.089021 | AM662: 0.032669 | AN662: -0.044226 | AO662: -0.046387 | AP662: -0.06206 | AQ662: 0.074219 | AR662: 0.108568 | AS662: -0.030991 | AT662: 0.05521 | AU662: 0.028812 | AV662: -0.062882 | AW662: 0.051154 | AX662: -0.00855 | AY662: 0.060491 | AZ662: -0.020629 | BA662: 0.023503 | BB662: -0.027289 | BC662: 0.111932 | BD662: -0.079098 | BE662: 0.028509 | BF662: -0.049352 | BG662: -0.068196 | BM662: 0.055215 | BN662: -0.011854 | BO662: 0.020769 | BP662: 0.176056 | BQ662: 0.08836 | BR662: 0.00942 | BS662: 0.079959 | BT662: 0.025467 | BU662: 0.039993 | BV662: -0.007853 | BW662: 0.001045 | BX662: -0.008307 | BY662: 0.01354 | BZ662: -0.039939 | CA662: 0.038484 | CB662: -0.021291 | CC662: 0.044855 | CD662: -0.101419 | CE662: 0.005679 | CF662: 0.008371 | CG662: -0.076092 | CH662: 0.009316 | CI662: -0.073263 | CJ662: 0.117887 | CK662: -0.03435 | CL662: -0.091984 | CM662: 0.09267 | CN662: 0.054291 | CO662: -0.075471 | CP662: 0.127305 | CQ662: -0.012527 | CR662: -0.00927 | CS662: -0.004757 | CT662: -0.021191 | CU662: 0.089021 | CV662: 0.032669 | CW662: -0.044226 | CX662: -0.046387 | CY662: -0.06206 | CZ662: 0.074219 | DA662: 0.108568 | DB662: -0.030991 | DC662: 0.05521 | DD662: 0.028812 | DE662: -0.062882 | DF662: 0.051154 | DG662: -0.00855 | DH662: 0.060491 | DI662: -0.020629 | DJ662: 0.023503 | DK662: -0.027289 | DL662: 0.111932 | DM662: -0.079098 | DN662: 0.028509 | DO662: -0.049352 | DP662: -0.068196 | DV662: 0.050398 | DW662: -0.010098 | DX662: 0.031145 | DY662: 0.183067 | DZ662: 0.08896 | EA662: 0.013987 | EB662: 0.089016 | EC662: 0.028616 | ED662: 0.03792 | EE662: -0.009349 | EF662: 0.003632 | EG662: -0.007576 | EH662: 0.0162 | EI662: -0.038653 | EJ662: 0.035353 | EK662: -0.023202 | EL662: 0.045936 | EM662: -0.099006 | EN662: -0.001334 | EO662: 0.010422 | EP662: -0.081153 | EQ662: 0.007554 | ER662: -0.063068 | ES662: 0.12091 | ET662: -0.033799 | EU662: -0.094081 | EV662: 0.091652 | EW662: 0.062795 | EX662: -0.069898 | EY662: 0.136796 | EZ662: -0.019023 | FA662: -0.011326 | FB662: -0.003019 | FC662: -0.022705 | FD662: 0.084591 | FE662: 0.036865 | FF662: -0.046647 | FG662: -0.049839 | FH662: -0.066086 | FI662: 0.082842 | FJ662: 0.115153 | FK662: -0.037422 | FL662: 0.047999 | FM662: 0.024713 | FN662: -0.074428 | FO662: 0.050026 | FP662: -0.009515 | FQ662: 0.060442 | FR662: -0.020796 | FS662: 0.019958 | FT662: -0.025874 | FU662: 0.113772 | FV662: -0.072511 | FW662: 0.021458 | FX662: -0.05812 | FY662: -0.071289
B663: =Deals!B663 -> Avient Corporation | C663: 1 | D663: 0.067782 | E663: 0.044788 | F663: 0.174225 | G663: 0.176376 | H663: 0.10788 | I663: -0.045929 | J663: 0.124642 | K663: 0.098635 | L663: 0.074043 | M663: 0.023833 | N663: -0.050154 | O663: -0.013019 | P663: 0.073578 | Q663: -0.106105 | R663: 0.16246 | S663: 0.020973 | T663: 0.021414 | U663: -0.110456 | V663: 0.052642 | W663: -0.079261 | X663: 0.025833 | Y663: -0.000812 | Z663: -0.180528 | AA663: 0.076597 | AB663: 0.015759 | AC663: -0.303263 | AD663: 0.138284 | AE663: 0.003479 | AF663: -0.017394 | AG663: 0.200237 | AH663: 0.076752 | AI663: -0.050928 | AJ663: -0.064383 | AK663: -0.052194 | AL663: 0.127342 | AM663: -0.009046 | AN663: -0.010363 | AO663: -0.113239 | AP663: -0.104757 | AQ663: 0.086338 | AR663: 0.2177 | AS663: -0.128939 | AT663: 0.117923 | AU663: 0.078508 | AV663: -0.022581 | AW663: 0.053277 | AX663: -0.017278 | AY663: 0.036426 | AZ663: 0.085986 | BA663: 0.029463 | BB663: -0.073728 | BC663: 0.099549 | BD663: -0.197463 | BE663: 0.049927 | BF663: -0.00303 | BG663: -0.124854 | BM663: 0.03218 | BN663: -0.042964 | BO663: 0.030633 | BP663: 0.152673 | BQ663: 0.069227 | BR663: 0.026253 | BS663: 0.083383 | BT663: 0.050807 | BU663: 0.039311 | BV663: 0.00368 | BW663: -0.020617 | BX663: -0.014361 | BY663: 0.019025 | BZ663: -0.029657 | CA663: 0.039369 | CB663: -0.02552 | CC663: 0.043022 | CD663: -0.063419 | CE663: 0.015302 | CF663: 0.008021 | CG663: -0.064057 | CH663: 0.012167 | CI663: -0.073974 | CJ663: 0.097031 | CK663: -0.029051 | CL663: -0.098544 | CM663: 0.123911 | CN663: 0.063521 | CO663: -0.054844 | CP663: 0.105504 | CQ663: -0.016618 | CR663: -0.026911 | CS663: -0.013867 | CT663: -0.03655 | CU663: 0.084236 | CV663: 0.038932 | CW663: -0.052068 | CX663: -0.059445 | CY663: -0.054472 | CZ663: 0.084571 | DA663: 0.09972 | DB663: -0.040306 | DC663: 0.053529 | DD663: 0.047299 | DE663: -0.059534 | DF663: 0.042114 | DG663: -0.017701 | DH663: 0.091286 | DI663: -0.009634 | DJ663: 0.010493 | DK663: -0.012831 | DL663: 0.115833 | DM663: -0.080605 | DN663: 0.046361 | DO663: -0.049152 | DP663: -0.063499 | DV663: 0.028826 | DW663: -0.045935 | DX663: 0.026239 | DY663: 0.16104 | DZ663: 0.066408 | EA663: 0.03008 | EB663: 0.076997 | EC663: 0.055609 | ED663: 0.031663 | EE663: 0.012116 | EF663: -0.01594 | EG663: -0.014149 | EH663: 0.020098 | EI663: -0.030775 | EJ663: 0.04496 | EK663: -0.023879 | EL663: 0.046081 | EM663: -0.065981 | EN663: 0.01874 | EO663: 0.003467 | EP663: -0.072255 | EQ663: 0.015656 | ER663: -0.079185 | ES663: 0.097155 | ET663: -0.030417 | EU663: -0.101629 | EV663: 0.126585 | EW663: 0.062172 | EX663: -0.055573 | EY663: 0.108861 | EZ663: -0.016155 | FA663: -0.025283 | FB663: -0.014063 | FC663: -0.031882 | FD663: 0.076746 | FE663: 0.041123 | FF663: -0.054372 | FG663: -0.061727 | FH663: -0.056256 | FI663: 0.090276 | FJ663: 0.101353 | FK663: -0.046179 | FL663: 0.044354 | FM663: 0.043283 | FN663: -0.062582 | FO663: 0.04155 | FP663: -0.019875 | FQ663: 0.095316 | FR663: -0.008765 | FS663: 0.012007 | FT663: -0.009706 | FU663: 0.117638 | FV663: -0.084348 | FW663: 0.042485 | FX663: -0.053294 | FY663: -0.051079
B664: =Deals!B664 -> Zynga Inc | C664: 1 | D664: -0.078332 | E664: 0.006623 | F664: -0.014254 | G664: -0.082314 | H664: 0.196364 | I664: 0.004053 | J664: 0.125126 | K664: -0.084305 | L664: 0.059745 | M664: 0.001848 | N664: -0.019373 | O664: -0.049859 | P664: -0.123762 | Q664: -0.149153 | R664: -0.01992 | S664: -0.182927 | T664: 0.06136 | U664: 0.417188 | V664: 0.001103 | W664: 0.017621 | X664: -0.104978 | Y664: -0.028824 | Z664: -0.072625 | AA664: 0.130842 | AB664: -0.025181 | AC664: -0.091353 | AD664: 0.057844 | AE664: 0.043218 | AF664: -0.053526 | AG664: 0.096917 | AH664: -0.024248 | AI664: 0.012549 | AJ664: -0.018976 | AK664: 0.00158 | AL664: 0.08151 | AM664: 0.012495 | AN664: -0.024647 | AO664: -0.058736 | AP664: -0.06088 | AQ664: 0.098774 | AR664: 0.08847 | AS664: -0.016905 | AT664: 0.070309 | AU664: 0.038473 | AV664: -0.057327 | AW664: 0.025533 | AX664: -0.006069 | AY664: 0.032133 | AZ664: 0.017784 | BA664: 0.034516 | BB664: -0.010065 | BC664: 0.097341 | BD664: -0.082651 | BE664: 0.042638 | BF664: -0.042825 | BG664: -0.066421 | BM664: 0.042064 | BN664: 0.00853 | BO664: 0.014059 | BP664: 0.135594 | BQ664: 0.068794 | BR664: -0.002337 | BS664: 0.034689 | BT664: -0.020006 | BU664: 0.043697 | BV664: -0.020314 | BW664: 0.05157 | BX664: -0.008614 | BY664: 0.031631 | BZ664: -0.042971 | CA664: 0.047924 | CB664: -0.063866 | CC664: 0.003966 | CD664: -0.127141 | CE664: 0.001103 | CF664: 0.001259 | CG664: -0.107022 | CH664: -0.028824 | CI664: -0.072625 | CJ664: 0.130842 | CK664: -0.025181 | CL664: -0.091353 | CM664: 0.057844 | CN664: 0.043218 | CO664: -0.053526 | CP664: 0.096917 | CQ664: -0.024248 | CR664: 0.012549 | CS664: -0.018976 | CT664: 0.00158 | CU664: 0.08151 | CV664: 0.012495 | CW664: -0.024647 | CX664: -0.058736 | CY664: -0.06088 | CZ664: 0.098774 | DA664: 0.08847 | DB664: -0.016905 | DC664: 0.070309 | DD664: 0.038473 | DE664: -0.057327 | DF664: 0.025533 | DG664: -0.006069 | DH664: 0.032133 | DI664: 0.017784 | DJ664: 0.034516 | DK664: -0.010065 | DL664: 0.097341 | DM664: -0.082651 | DN664: 0.042638 | DO664: -0.042825 | DP664: -0.066421 | DV664: 0.040966 | DW664: 0.005233 | DX664: 0.019264 | DY664: 0.135549 | DZ664: 0.067697 | EA664: 0.004164 | EB664: 0.031611 | EC664: -0.019813 | ED664: 0.037602 | EE664: -0.018649 | EF664: 0.047074 | EG664: -0.012965 | EH664: 0.026925 | EI664: -0.043898 | EJ664: 0.049157 | EK664: -0.074862 | EL664: 0.009118 | EM664: -0.133336 | EN664: -0.004978 | EO664: 0.001746 | EP664: -0.124799 | EQ664: -0.039308 | ER664: -0.070351 | ES664: 0.130499 | ET664: -0.023216 | EU664: -0.090202 | EV664: 0.053736 | EW664: 0.048669 | EX664: -0.052265 | EY664: 0.117259 | EZ664: -0.019842 | FA664: 0.012199 | FB664: -0.009812 | FC664: 0.008894 | FD664: 0.090874 | FE664: 0.014205 | FF664: -0.019595 | FG664: -0.061965 | FH664: -0.063279 | FI664: 0.099242 | FJ664: 0.096129 | FK664: -0.01973 | FL664: 0.076137 | FM664: 0.039414 | FN664: -0.059407 | FO664: 0.019381 | FP664: -0.010354 | FQ664: 0.033709 | FR664: 0.014427 | FS664: 0.029627 | FT664: -0.006623 | FU664: 0.091114 | FV664: -0.075772 | FW664: 0.036599 | FX664: -0.045902 | FY664: -0.058795
B665: =Deals!B665 -> Teladoc Health, Inc. | C665: 1 | D665: -0.092328 | E665: 0.016459 | F665: -0.103904 | G665: 0.011758 | H665: 0.005987 | I665: 0.319414 | J665: -0.161998 | K665: -0.177937 | L665: -0.051719 | M665: -0.126313 | N665: 0.10433 | O665: -0.107282 | P665: -0.027147 | Q665: -0.121936 | R665: 0.179639 | S665: -0.32315 | T665: -0.093136 | U665: -0.164561 | V665: -0.010429 | W665: -0.049796 | X665: -0.531956 | Y665: 0.009775 | Z665: -0.025814 | AA665: 0.109606 | AB665: -0.157123 | AC665: -0.183838 | AD665: 0.169231 | AE665: -0.038124 | AF665: -0.170467 | AG665: 0.243129 | AH665: -0.09898 | AI665: -0.022273 | AJ665: 0.024324 | AK665: -0.127403 | AL665: 0.093737 | AM665: 0.17575 | AN665: -0.239503 | AO665: -0.178887 | AP665: -0.110274 | AQ665: 0.096735 | AR665: 0.187982 | AS665: -0.098376 | AT665: -0.223881 | AU665: 0.001326 | AV665: -0.155629 | AW665: -0.118431 | AX665: -0.129893 | AY665: -0.035787 | AZ665: -0.239661 | BA665: 0.280335 | BB665: -0.019608 | BC665: 0.331111 | BD665: -0.241235 | BE665: 0.117712 | BF665: -0.059055 | BG665: -0.167364 | BM665: 0.107972 | BN665: -0.045521 | BO665: -0.045743 | BP665: 0.107281 | BQ665: 0.053002 | BR665: -0.009351 | BS665: -0.005854 | BT665: 0.01839 | BU665: 0.059373 | BV665: -0.013515 | BW665: 0.057192 | BX665: 0.032936 | BY665: 0.033156 | BZ665: -0.052802 | CA665: 0.089956 | CB665: 0.012325 | CC665: 0.021218 | CD665: -0.077613 | CE665: -0.033277 | CF665: 0.048718 | CG665: -0.10863 | CH665: -0.030079 | CI665: -0.078069 | CJ665: 0.127169 | CK665: -0.053498 | CL665: -0.100388 | CM665: 0.052883 | CN665: 0.047454 | CO665: -0.082033 | CP665: 0.087217 | CQ665: -0.01317 | CR665: 0.081256 | CS665: 0.01129 | CT665: 0.054991 | CU665: 0.072447 | CV665: 0.023838 | CW665: -0.008326 | CX665: -0.05542 | CY665: -0.009954 | CZ665: 0.098907 | DA665: 0.037524 | DB665: 0.022668 | DC665: 0.060191 | DD665: 0.016533 | DE665: -0.040193 | DF665: 0.059598 | DG665: 0.061092 | DH665: -0.008513 | DI665: 0.021543 | DJ665: 0.024194 | DK665: -0.007924 | DL665: 0.063182 | DM665: 0.003266 | DN665: 0.014885 | DO665: -0.031109 | DP665: -0.076633 | DV665: 0.054124 | DW665: -0.020604 | DX665: -0.021628 | DY665: 0.130555 | DZ665: 0.041795 | EA665: -0.018249 | EB665: 0.019443 | EC665: 0.020896 | ED665: 0.053291 | EE665: -0.004423 | EF665: 0.043268 | EG665: 0.030241 | EH665: 0.029029 | EI665: -0.051931 | EJ665: 0.076494 | EK665: -0.023675 | EL665: 0.027244 | EM665: -0.105932 | EN665: -0.028087 | EO665: 0.024591 | EP665: -0.102794 | EQ665: -0.042047 | ER665: -0.081421 | ES665: 0.115932 | ET665: -0.040409 | EU665: -0.09131 | EV665: 0.077555 | EW665: 0.068696 | EX665: -0.064949 | EY665: 0.083649 | EZ665: -0.013406 | FA665: 0.044705 | FB665: -0.010179 | FC665: 0.017315 | FD665: 0.073915 | FE665: 0.027187 | FF665: -0.023523 | FG665: -0.051409 | FH665: -0.03327 | FI665: 0.105435 | FJ665: 0.064066 | FK665: 0.005583 | FL665: 0.053753 | FM665: 0.021634 | FN665: -0.048148 | FO665: 0.010258 | FP665: 0.019325 | FQ665: 0.000127 | FR665: 0.029717 | FS665: 0.023121 | FT665: -0.009897 | FU665: 0.082276 | FV665: -0.042846 | FW665: 0.045785 | FX665: -0.023907 | FY665: -0.062674
B666: =Deals!B666 -> Revance Therapeutics, Inc. | C666: 1 | D666: 0.244889 | E666: -0.139925 | F666: 0.029435 | G666: -0.067233 | H666: 0.173985 | I666: -0.102329 | J666: 0.032233 | K666: 0.064356 | L666: 0.04186 | M666: 0.016827 | N666: 0.001013 | O666: -0.018893 | P666: -0.079092 | Q666: 0.040329 | R666: -0.506461 | S666: -0.005091 | T666: 0.192982 | U666: -0.183211 | V666: 0.018005 | W666: 0.436993 | X666: -0.16 | Y666: -0.164835 | Z666: 0.010234 | AA666: 0.12301 | AB666: 0.282216 | AC666: 0.356784 | AD666: -0.173704 | AE666: -0.026894 | AF666: -0.149701 | AG666: 0.878657 | AH666: 0.000577 | AI666: -0.071758 | AJ666: -0.011798 | AK666: -0.039899 | AL666: -0.171793 | AM666: -0.066377 | AN666: -0.253915 | AO666: -0.349404 | AP666: -0.312119 | AQ666: -0.141952 | AR666: 0.298375 | AS666: -0.427759 | AT666: 0.419483 | AU666: -0.310924 | AV666: -0.26626 | AW666: -0.213296 | AX666: -0.09507 | AY666: 0.470817 | AZ666: 0.738095 | BA666: -0.210046 | BB666: 0.136802 | BC666: -0.388136 | BD666: -0.157895 | BE666: 0.194079 | BF666: -0.084494 | BG666: -0.082801 | BM666: 0.079862 | BN666: 0.003401 | BO666: -0.019809 | BP666: 0.214791 | BQ666: 0.115065 | BR666: 0.116678 | BS666: 0.040745 | BT666: -0.048473 | BU666: 0.032353 | BV666: -0.025949 | BW666: 0.06983 | BX666: -0.075376 | BY666: 0.020545 | BZ666: -0.052806 | CA666: 0.024457 | CB666: -0.080613 | CC666: -0.005266 | CD666: -0.163775 | CE666: -0.001611 | CF666: 0.012199 | CG666: -0.180685 | CH666: -0.032766 | CI666: -0.019338 | CJ666: 0.128546 | CK666: 0.036743 | CL666: -0.088022 | CM666: 0.076143 | CN666: -0.002315 | CO666: -0.050589 | CP666: 0.141421 | CQ666: -0.040665 | CR666: -0.034632 | CS666: -0.027967 | CT666: 0.012513 | CU666: 0.070349 | CV666: 0.041532 | CW666: -0.071954 | CX666: -0.091371 | CY666: -0.101457 | CZ666: 0.108746 | DA666: 0.122171 | DB666: -0.039346 | DC666: 0.094637 | DD666: 0.003944 | DE666: -0.069152 | DF666: 0.019278 | DG666: -0.016837 | DH666: 0.075097 | DI666: 0.006764 | DJ666: 0.000931 | DK666: -0.008068 | DL666: 0.14058 | DM666: -0.041389 | DN666: 0.005532 | DO666: -0.084494 | DP666: -0.082801 | DV666: 0.087533 | DW666: -0.011573 | DX666: -0.028636 | DY666: 0.206308 | DZ666: 0.094331 | EA666: 0.112618 | EB666: 0.051624 | EC666: -0.046095 | ED666: 0.028573 | EE666: -0.026132 | EF666: 0.06635 | EG666: -0.076813 | EH666: 0.018217 | EI666: -0.053317 | EJ666: 0.021146 | EK666: -0.091985 | EL666: -0.014805 | EM666: -0.173369 | EN666: -0.012789 | EO666: 0.018464 | EP666: -0.198696 | EQ666: -0.057167 | ER666: -0.02625 | ES666: 0.129928 | ET666: 0.030138 | EU666: -0.081445 | EV666: 0.087294 | EW666: -0.006501 | EX666: -0.051629 | EY666: 0.164361 | EZ666: -0.049102 | FA666: -0.042333 | FB666: -0.043651 | FC666: 0.027983 | FD666: 0.075292 | FE666: 0.041174 | FF666: -0.071456 | FG666: -0.098155 | FH666: -0.110132 | FI666: 0.107279 | FJ666: 0.142226 | FK666: -0.046726 | FL666: 0.099012 | FM666: -0.006566 | FN666: -0.088553 | FO666: 0.04379 | FP666: -0.01381 | FQ666: 0.076992 | FR666: -0.007169 | FS666: -0.005011 | FT666: -0.001446 | FU666: 0.13118 | FV666: -0.044324 | FW666: 0.027517 | FX666: -0.087576 | FY666: -0.080425
B667: =Deals!B667 -> Caesars Entertainment, Inc. | C667: 1 | D667: 0.47504 | E667: 0.224017 | F667: -0.200499 | G667: 0.519857 | H667: 0.090282 | I667: -0.052242 | J667: 0.327461 | K667: -0.064105 | L667: 0.118811 | M667: 0.098222 | N667: -0.034435 | O667: -0.157976 | P667: 0.163347 | Q667: 0.104792 | R667: -0.025116 | S667: -0.177142 | T667: 0.038415 | U667: -0.18593 | V667: 0.105726 | W667: -0.081126 | X667: -0.143226 | Y667: -0.24306 | Z667: -0.236596 | AA667: 0.19295 | AB667: -0.056249 | AC667: -0.251855 | AD667: 0.355549 | AE667: 0.161903 | AF667: -0.181264 | AG667: 0.251442 | AH667: -0.024971 | AI667: -0.038416 | AJ667: -0.072116 | AK667: -0.094502 | AL667: 0.242868 | AM667: 0.157936 | AN667: -0.063707 | AO667: -0.161238 | AP667: -0.139374 | AQ667: 0.121083 | AR667: 0.048301 | AS667: -0.064206 | AT667: -0.009118 | AU667: 0.006211 | AV667: -0.18107 | AW667: -0.007259 | AX667: 0.117548 | AY667: 0.005284 | AZ667: -0.057822 | BA667: 0.108927 | BB667: -0.040489 | BC667: -0.038951 | BD667: -0.131723 | BE667: 0.078695 | BF667: -0.078502 | BG667: -0.247441 | BM667: 0.042064 | BN667: 0.00853 | BO667: 0.014059 | BP667: 0.135594 | BQ667: 0.068794 | BR667: -0.002337 | BS667: 0.034689 | BT667: -0.020006 | BU667: 0.043697 | BV667: -0.020314 | BW667: 0.05157 | BX667: -0.008614 | BY667: 0.031631 | BZ667: -0.042971 | CA667: 0.047924 | CB667: -0.063866 | CC667: 0.003966 | CD667: -0.127141 | CE667: 0.001103 | CF667: 0.001259 | CG667: -0.107022 | CH667: -0.028824 | CI667: -0.072625 | CJ667: 0.130842 | CK667: -0.025181 | CL667: -0.091353 | CM667: 0.057844 | CN667: 0.043218 | CO667: -0.053526 | CP667: 0.096917 | CQ667: -0.024248 | CR667: 0.012549 | CS667: -0.018976 | CT667: 0.00158 | CU667: 0.08151 | CV667: 0.012495 | CW667: -0.024647 | CX667: -0.058736 | CY667: -0.06088 | CZ667: 0.098774 | DA667: 0.08847 | DB667: -0.016905 | DC667: 0.070309 | DD667: 0.038473 | DE667: -0.057327 | DF667: 0.025533 | DG667: -0.006069 | DH667: 0.032133 | DI667: 0.017784 | DJ667: 0.034516 | DK667: -0.010065 | DL667: 0.097341 | DM667: -0.082651 | DN667: 0.042638 | DO667: -0.042825 | DP667: -0.066421 | DV667: 0.040966 | DW667: 0.005233 | DX667: 0.019264 | DY667: 0.135549 | DZ667: 0.067697 | EA667: 0.004164 | EB667: 0.031611 | EC667: -0.019813 | ED667: 0.037602 | EE667: -0.018649 | EF667: 0.047074 | EG667: -0.012965 | EH667: 0.026925 | EI667: -0.043898 | EJ667: 0.049157 | EK667: -0.074862 | EL667: 0.009118 | EM667: -0.133336 | EN667: -0.004978 | EO667: 0.001746 | EP667: -0.124799 | EQ667: -0.039308 | ER667: -0.070351 | ES667: 0.130499 | ET667: -0.023216 | EU667: -0.090202 | EV667: 0.053736 | EW667: 0.048669 | EX667: -0.052265 | EY667: 0.117259 | EZ667: -0.019842 | FA667: 0.012199 | FB667: -0.009812 | FC667: 0.008894 | FD667: 0.090874 | FE667: 0.014205 | FF667: -0.019595 | FG667: -0.061965 | FH667: -0.063279 | FI667: 0.099242 | FJ667: 0.096129 | FK667: -0.01973 | FL667: 0.076137 | FM667: 0.039414 | FN667: -0.059407 | FO667: 0.019381 | FP667: -0.010354 | FQ667: 0.033709 | FR667: 0.014427 | FS667: 0.029627 | FT667: -0.006623 | FU667: 0.091114 | FV667: -0.075772 | FW667: 0.036599 | FX667: -0.045902 | FY667: -0.058795
B668: =Deals!B668 -> Enviva Inc. | C668: 1 | D668: 0.100105 | E668: -0.024473 | F668: 0.064332 | G668: 0.05986 | H668: 0.017473 | I668: 0.096874 | J668: 0.080088 | K668: -0.088629 | L668: 0.019036 | M668: 0.008832 | N668: 0.071779 | O668: 0.030338 | P668: 0.015833 | Q668: 0.000925 | R668: 0.237937 | S668: 0.058393 | T668: 0.005569 | U668: -0.006248 | V668: 0.008288 | W668: 0.135581 | X668: 0.065572 | Y668: -0.065746 | Z668: -0.265374 | AA668: 0.216882 | AB668: 0.011417 | AC668: -0.136076 | AD668: -0.003663 | AE668: -0.036514 | AF668: -0.066608 | AG668: -0.141401 | AH668: -0.022318 | AI668: -0.337006 | AJ668: -0.25554 | AK668: -0.591628 | AL668: 0.235763 | AM668: 0.241475 | AN668: -0.317001 | AO668: -0.188043 | AP668: -0.515395 | AQ668: -0.662983 | AR668: -0.18377 | AS668: -0.559952 | AT668: -0.087859 | AU668: 0.101076 | AV668: 0.159509 | AW668: 0.11699 | AX668: -0.245614 | AY668: -0.018372 | AZ668: 0.248519 | BA668: -0.231879 | BB668: -0.00881 | BC668: 0.132864 | BD668: -0.092084 | BE668: 0.027376 | BF668: -0.087184 | BG668: -0.07152 | BM668: 0.069178 | BN668: -0.047385 | BO668: 0.03365 | BP668: 0.188158 | BQ668: 0.101547 | BR668: 0.049816 | BS668: 0.086155 | BT668: -0.008262 | BU668: 0.015677 | BV668: 0.002446 | BW668: 0.035313 | BX668: -0.028278 | BY668: 0.024312 | BZ668: -0.041121 | CA668: 0.023534 | CB668: -0.034555 | CC668: 0.001539 | CD668: -0.116597 | CE668: 0.020508 | CF668: 0.022185 | CG668: -0.119564 | CH668: -0.028738 | CI668: -0.063921 | CJ668: 0.135102 | CK668: -0.007929 | CL668: -0.088004 | CM668: 0.092762 | CN668: -0.018141 | CO668: -0.073757 | CP668: 0.160132 | CQ668: -0.029084 | CR668: -0.030294 | CS668: 0.000974 | CT668: 0.034374 | CU668: 0.071376 | CV668: 0.055658 | CW668: -0.070227 | CX668: -0.055895 | CY668: -0.076043 | CZ668: 0.090818 | DA668: 0.141331 | DB668: -0.03884 | DC668: 0.062772 | DD668: 0.020685 | DE668: -0.08132 | DF668: 0.03247 | DG668: -0.016085 | DH668: 0.096359 | DI668: 0.002008 | DJ668: 0.012156 | DK668: -0.00881 | DL668: 0.132864 | DM668: -0.092084 | DN668: 0.027376 | DO668: -0.087184 | DP668: -0.07152 | DV668: 0.076086 | DW668: -0.053883 | DX668: 0.035066 | DY668: 0.203256 | DZ668: 0.100877 | EA668: 0.053073 | EB668: 0.075831 | EC668: -0.001805 | ED668: 0.008333 | EE668: -0.008533 | EF668: 0.032572 | EG668: -0.030216 | EH668: 0.020798 | EI668: -0.040113 | EJ668: 0.024885 | EK668: -0.052054 | EL668: 0.002106 | EM668: -0.122474 | EN668: 0.004163 | EO668: 0.029007 | EP668: -0.150847 | EQ668: -0.038851 | ER668: -0.043457 | ES668: 0.133239 | ET668: 0.00337 | EU668: -0.088268 | EV668: 0.09263 | EW668: -0.008961 | EX668: -0.073196 | EY668: 0.179925 | EZ668: -0.037455 | FA668: -0.045087 | FB668: -0.007067 | FC668: 0.026671 | FD668: 0.081708 | FE668: 0.048745 | FF668: -0.067184 | FG668: -0.056578 | FH668: -0.086289 | FI668: 0.096397 | FJ668: 0.143956 | FK668: -0.055801 | FL668: 0.059786 | FM668: 0.003677 | FN668: -0.079926 | FO668: 0.024106 | FP668: -0.027662 | FQ668: 0.104449 | FR668: -0.005668 | FS668: 0.005186 | FT668: -0.005121 | FU668: 0.118651 | FV668: -0.083389 | FW668: 0.025358 | FX668: -0.082682 | FY668: -0.0774
B669: =Deals!B669 -> Willscot Mobile Mini Holdings Corp. | C669: 1 | D669: 0.188579 | E669: -0.068156 | F669: 0.113909 | G669: 0.157696 | H669: 0.077173 | I669: 0.023306 | J669: 0.169549 | K669: 0.000721 | L669: 0.054775 | M669: -0.009224 | N669: -0.038966 | O669: 0.03014 | P669: 0.031 | Q669: 0.071622 | R669: 0.095523 | S669: 0.096115 | T669: 0.072197 | U669: -0.093046 | V669: -0.040767 | W669: 0.101323 | X669: -0.10299 | Y669: 0.017949 | Z669: -0.092639 | AA669: 0.190932 | AB669: 0.039627 | AC669: 0.004733 | AD669: 0.05455 | AE669: 0.133553 | AF669: -0.063057 | AG669: 0.072836 | AH669: 0.060669 | AI669: -0.087938 | AJ669: -0.03157 | AK669: -0.051101 | AL669: 0.109331 | AM669: 0.003348 | AN669: -0.144526 | AO669: 0.013896 | AP669: -0.052416 | AQ669: 0.058615 | AR669: 0.066635 | AS669: 0.062921 | AT669: 0.009514 | AU669: -0.026178 | AV669: -0.205161 | AW669: 0.066829 | AX669: -0.045397 | AY669: 0.089267 | AZ669: -0.06 | BA669: -0.02439 | BB669: -0.118617 | BC669: 0.153893 | BD669: -0.125262 | BE669: 0.107922 | BF669: -0.110901 | BG669: -0.154173 | BM669: 0.084196 | BN669: -0.031087 | BO669: 0.030388 | BP669: 0.207556 | BQ669: 0.12645 | BR669: 0.024415 | BS669: -0.000483 | BT669: -0.047837 | BU669: 0.02869 | BV669: -0.033421 | BW669: 0.054695 | BX669: -0.02501 | BY669: 0.019022 | BZ669: -0.038561 | CA669: 0.046626 | CB669: -0.08576 | CC669: 0.000968 | CD669: -0.142109 | CE669: -0.007716 | CF669: 0.017833 | CG669: -0.117955 | CH669: -0.053077 | CI669: -0.044319 | CJ669: 0.116268 | CK669: -0.038541 | CL669: -0.088512 | CM669: 0.034639 | CN669: 0.031372 | CO669: -0.043533 | CP669: 0.106176 | CQ669: -0.003618 | CR669: -0.008652 | CS669: -0.032515 | CT669: 0.010489 | CU669: 0.068229 | CV669: 0.053331 | CW669: -0.053394 | CX669: -0.058727 | CY669: -0.073528 | CZ669: 0.111124 | DA669: 0.103291 | DB669: -0.042161 | DC669: 0.032515 | DD669: 0.006384 | DE669: -0.06286 | DF669: 0.046483 | DG669: 0.028059 | DH669: 0.064974 | DI669: -0.001472 | DJ669: 0.042635 | DK669: -0.016588 | DL669: 0.102793 | DM669: -0.079478 | DN669: 0.053794 | DO669: -0.056928 | DP669: -0.07451 | DV669: 0.084717 | DW669: -0.030373 | DX669: 0.034269 | DY669: 0.21392 | DZ669: 0.129432 | EA669: 0.017059 | EB669: 0.021424 | EC669: -0.036464 | ED669: 0.030769 | EE669: -0.028421 | EF669: 0.061708 | EG669: -0.023545 | EH669: 0.015868 | EI669: -0.039964 | EJ669: 0.047113 | EK669: -0.084736 | EL669: -0.003415 | EM669: -0.141596 | EN669: -0.016339 | EO669: 0.004296 | EP669: -0.138311 | EQ669: -0.045222 | ER669: -0.046504 | ES669: 0.116767 | ET669: -0.030875 | EU669: -0.092886 | EV669: 0.038196 | EW669: 0.031364 | EX669: -0.050589 | EY669: 0.12749 | EZ669: -0.008377 | FA669: -0.018392 | FB669: -0.031244 | FC669: 0.024876 | FD669: 0.074528 | FE669: 0.058153 | FF669: -0.055866 | FG669: -0.061774 | FH669: -0.07758 | FI669: 0.128905 | FJ669: 0.115622 | FK669: -0.04519 | FL669: 0.029184 | FM669: 0.003445 | FN669: -0.066565 | FO669: 0.07274 | FP669: 0.026772 | FQ669: 0.068904 | FR669: -0.001826 | FS669: 0.034451 | FT669: -0.012354 | FU669: 0.129517 | FV669: -0.079792 | FW669: 0.048261 | FX669: -0.057773 | FY669: -0.075988
B670: =Deals!B670 -> Bally’S Corporation | C670: 1 | D670: 0.109926 | E670: 0.097785 | F670: -0.076132 | G670: 0.188158 | H670: 0.130542 | I670: 0.044794 | J670: 0.134146 | K670: 0.091734 | L670: -0.108033 | M670: 0.001208 | N670: -0.067551 | O670: -0.089817 | P670: 0.020102 | Q670: -0.00199 | R670: -0.086358 | S670: -0.163065 | T670: -0.007303 | U670: -0.060956 | V670: 0.007834 | W670: -0.146585 | X670: -0.029278 | Y670: -0.123995 | Z670: -0.243305 | AA670: 0.110718 | AB670: 0.078289 | AC670: -0.165893 | AD670: 0.140688 | AE670: 0.109139 | AF670: -0.2248 | AG670: 0.025284 | AH670: -0.006039 | AI670: -0.011646 | AJ670: -0.118852 | AK670: -0.209884 | AL670: 0.14496 | AM670: 0.046272 | AN670: 0.019656 | AO670: -0.210241 | AP670: -0.304348 | AQ670: 0.263158 | AR670: 0.210069 | AS670: -0.192253 | AT670: -0.001776 | AU670: 0.240214 | AV670: -0.057389 | AW670: -0.075342 | AX670: -0.014815 | AY670: 0.439432 | AZ670: -0.001741 | BA670: 0.002907 | BB670: 0.011594 | BC670: 0.016046 | BD670: 0.009024 | BE670: 0.01621 | BF670: -0.009901 | BG670: -0.316667 | BM670: 0.069178 | BN670: -0.047385 | BO670: 0.03365 | BP670: 0.188158 | BQ670: 0.101547 | BR670: 0.049816 | BS670: 0.086155 | BT670: -0.008262 | BU670: 0.015677 | BV670: 0.002446 | BW670: 0.035313 | BX670: -0.028278 | BY670: 0.024312 | BZ670: -0.041121 | CA670: 0.023534 | CB670: -0.034555 | CC670: 0.001539 | CD670: -0.116597 | CE670: 0.020508 | CF670: 0.022185 | CG670: -0.119564 | CH670: -0.028738 | CI670: -0.063921 | CJ670: 0.135102 | CK670: -0.007929 | CL670: -0.088004 | CM670: 0.092762 | CN670: -0.018141 | CO670: -0.073757 | CP670: 0.160132 | CQ670: -0.029084 | CR670: -0.030294 | CS670: 0.000974 | CT670: 0.034374 | CU670: 0.071376 | CV670: 0.055658 | CW670: -0.070227 | CX670: -0.055895 | CY670: -0.076043 | CZ670: 0.090818 | DA670: 0.141331 | DB670: -0.03884 | DC670: 0.062772 | DD670: 0.020685 | DE670: -0.08132 | DF670: 0.03247 | DG670: -0.016085 | DH670: 0.096359 | DI670: 0.002008 | DJ670: 0.012156 | DK670: -0.00881 | DL670: 0.132864 | DM670: -0.092084 | DN670: 0.027376 | DO670: -0.087184 | DP670: -0.07152 | DV670: 0.076086 | DW670: -0.053883 | DX670: 0.035066 | DY670: 0.203256 | DZ670: 0.100877 | EA670: 0.053073 | EB670: 0.075831 | EC670: -0.001805 | ED670: 0.008333 | EE670: -0.008533 | EF670: 0.032572 | EG670: -0.030216 | EH670: 0.020798 | EI670: -0.040113 | EJ670: 0.024885 | EK670: -0.052054 | EL670: 0.002106 | EM670: -0.122474 | EN670: 0.004163 | EO670: 0.029007 | EP670: -0.150847 | EQ670: -0.038851 | ER670: -0.043457 | ES670: 0.133239 | ET670: 0.00337 | EU670: -0.088268 | EV670: 0.09263 | EW670: -0.008961 | EX670: -0.073196 | EY670: 0.179925 | EZ670: -0.037455 | FA670: -0.045087 | FB670: -0.007067 | FC670: 0.026671 | FD670: 0.081708 | FE670: 0.048745 | FF670: -0.067184 | FG670: -0.056578 | FH670: -0.086289 | FI670: 0.096397 | FJ670: 0.143956 | FK670: -0.055801 | FL670: 0.059786 | FM670: 0.003677 | FN670: -0.079926 | FO670: 0.024106 | FP670: -0.027662 | FQ670: 0.104449 | FR670: -0.005668 | FS670: 0.005186 | FT670: -0.005121 | FU670: 0.118651 | FV670: -0.083389 | FW670: 0.025358 | FX670: -0.082682 | FY670: -0.0774
B671: =Deals!B671 -> Asbury Automotive Group, Inc | C671: 1 | D671: -0.078835 | E671: 0.056747 | F671: 0.095067 | G671: 0.292365 | H671: -0.021477 | I671: 0.188206 | J671: 0.159634 | K671: 0.010738 | L671: -0.001611 | M671: -0.135761 | N671: 0.198926 | O671: -0.093546 | P671: 0.056379 | Q671: -0.005235 | R671: -0.163865 | S671: 0.055549 | T671: -0.068083 | U671: 0.205877 | V671: -0.174695 | W671: 0.146754 | X671: -0.013935 | Y671: -0.065195 | Z671: 0.013582 | AA671: 0.016546 | AB671: -0.133998 | AC671: 0.044011 | AD671: 0.18935 | AE671: -0.044611 | AF671: 0.227336 | AG671: 0.032273 | AH671: -0.075297 | AI671: -0.078762 | AJ671: 0.080895 | AK671: 0.14973 | AL671: -0.061642 | AM671: 0.019504 | AN671: 0.000304 | AO671: -0.16821 | AP671: 0.09641 | AQ671: 0.072205 | AR671: -0.070721 | AS671: -0.0011 | AT671: 0.129052 | AU671: -0.108321 | AV671: 0.118103 | AW671: -0.030629 | AX671: 0.181463 | AY671: -0.087586 | AZ671: -0.028701 | BA671: -0.045056 | BB671: 0.140406 | BC671: -0.064658 | BD671: 0.220755 | BE671: -0.095322 | BF671: -0.177198 | BM671: -0.011854 | BN671: 0.020769 | BO671: 0.176056 | BP671: 0.08836 | BQ671: 0.00942 | BR671: 0.079959 | BS671: 0.025467 | BT671: 0.039993 | BU671: -0.007853 | BV671: 0.001045 | BW671: -0.008307 | BX671: 0.01354 | BY671: -0.039939 | BZ671: 0.038484 | CA671: -0.021291 | CB671: 0.044855 | CC671: -0.101419 | CD671: 0.005679 | CE671: 0.008371 | CF671: -0.076092 | CG671: 0.009316 | CH671: -0.073263 | CI671: 0.117887 | CJ671: -0.03435 | CK671: -0.091984 | CL671: 0.09267 | CM671: 0.054291 | CN671: -0.075471 | CO671: 0.127305 | CP671: -0.012527 | CQ671: -0.00927 | CR671: -0.004757 | CS671: -0.021191 | CT671: 0.089021 | CU671: 0.032669 | CV671: -0.044226 | CW671: -0.046387 | CX671: -0.06206 | CY671: 0.074219 | CZ671: 0.108568 | DA671: -0.030991 | DB671: 0.05521 | DC671: 0.028812 | DD671: -0.062882 | DE671: 0.051154 | DF671: -0.00855 | DG671: 0.060491 | DH671: -0.020629 | DI671: 0.023503 | DJ671: -0.027289 | DK671: 0.111932 | DL671: -0.079098 | DM671: 0.028509 | DN671: -0.049352 | DO671: -0.068196 | DV671: -0.010098 | DW671: 0.031145 | DX671: 0.183067 | DY671: 0.08896 | DZ671: 0.013987 | EA671: 0.089016 | EB671: 0.028616 | EC671: 0.03792 | ED671: -0.009349 | EE671: 0.003632 | EF671: -0.007576 | EG671: 0.0162 | EH671: -0.038653 | EI671: 0.035353 | EJ671: -0.023202 | EK671: 0.045936 | EL671: -0.099006 | EM671: -0.001334 | EN671: 0.010422 | EO671: -0.081153 | EP671: 0.007554 | EQ671: -0.063068 | ER671: 0.12091 | ES671: -0.033799 | ET671: -0.094081 | EU671: 0.091652 | EV671: 0.062795 | EW671: -0.069898 | EX671: 0.136796 | EY671: -0.019023 | EZ671: -0.011326 | FA671: -0.003019 | FB671: -0.022705 | FC671: 0.084591 | FD671: 0.036865 | FE671: -0.046647 | FF671: -0.049839 | FG671: -0.066086 | FH671: 0.082842 | FI671: 0.115153 | FJ671: -0.037422 | FK671: 0.047999 | FL671: 0.024713 | FM671: -0.074428 | FN671: 0.050026 | FO671: -0.009515 | FP671: 0.060442 | FQ671: -0.020796 | FR671: 0.019958 | FS671: -0.025874 | FT671: 0.113772 | FU671: -0.072511 | FV671: 0.021458 | FW671: -0.05812 | FX671: -0.071289
B672: =Deals!B672 -> Elanco Animal Health Inc | C672: 1 | D672: -0.038885 | E672: 0.110276 | F672: -0.013544 | G672: 0.002615 | H672: -0.053472 | I672: 0.131932 | J672: -0.103774 | K672: 0.07674 | L672: 0.134658 | M672: -0.035853 | N672: 0.051312 | O672: -0.084727 | P672: -0.044638 | Q672: 0.031044 | R672: -0.125912 | S672: -0.012526 | T672: -0.082452 | U672: 0.091014 | V672: -0.081661 | W672: -0.029897 | X672: -0.063611 | Y672: -0.17173 | Z672: 0.032094 | AA672: -0.253208 | AB672: -0.179775 | AC672: 0.062853 | AD672: -0.024261 | AE672: -0.050505 | AF672: 0.123568 | AG672: -0.164603 | AH672: -0.180471 | AI672: 0.007447 | AJ672: -0.139388 | AK672: 0.234356 | AL672: 0.199801 | AM672: 0.010771 | AN672: -0.078689 | AO672: -0.216192 | AP672: 0.337117 | AQ672: 0.264856 | AR672: -0.010738 | AS672: 0.078019 | AT672: 0.024544 | AU672: -0.191646 | AV672: 0.343465 | AW672: -0.183824 | AX672: -0.096327 | AY672: 0.18635 | AZ672: -0.05042 | BA672: -0.139551 | BB672: 0.045095 | BC672: -0.08327 | BD672: -0.006606 | BE672: -0.071488 | BF672: -0.059982 | BM672: -0.030538 | BN672: 0.019421 | BO672: 0.161394 | BP672: 0.077555 | BQ672: 0.023801 | BR672: 0.121902 | BS672: 0.052824 | BT672: 0.032792 | BU672: 0.037667 | BV672: -0.038754 | BW672: 0.013609 | BX672: 0.032297 | BY672: -0.045915 | BZ672: 0.045505 | CA672: -0.013633 | CB672: 0.061869 | CC672: -0.027948 | CD672: 0.02007 | CE672: 0.011779 | CF672: -0.057821 | CG672: 0.009084 | CH672: -0.100595 | CI672: 0.096505 | CJ672: -0.025527 | CK672: -0.098613 | CL672: 0.08813 | CM672: 0.068372 | CN672: -0.054141 | CO672: 0.112513 | CP672: -0.032575 | CQ672: -0.040192 | CR672: -0.016039 | CS672: -0.032273 | CT672: 0.099205 | CU672: 0.097039 | CV672: -0.03784 | CW672: -0.048187 | CX672: -0.054759 | CY672: 0.08531 | CZ672: 0.089012 | DA672: -0.032855 | DB672: 0.04613 | DC672: 0.082041 | DD672: -0.068568 | DE672: 0.052938 | DF672: -0.016565 | DG672: 0.067612 | DH672: 0.014801 | DI672: 0.036539 | DJ672: 0.015997 | DK672: 0.104277 | DL672: -0.062309 | DM672: 0.067514 | DN672: -0.02811 | DO672: -0.06433 | DV672: -0.03982 | DW672: 0.028925 | DX672: 0.17725 | DY672: 0.077862 | DZ672: 0.037767 | EA672: 0.124762 | EB672: 0.075836 | EC672: 0.022259 | ED672: 0.024649 | EE672: -0.032897 | EF672: 0.009484 | EG672: 0.032401 | EH672: -0.042227 | EI672: 0.036012 | EJ672: -0.010791 | EK672: 0.059268 | EL672: -0.027601 | EM672: 0.023828 | EN672: -0.00181 | EO672: -0.059716 | EP672: 0.010661 | EQ672: -0.095414 | ER672: 0.094773 | ES672: -0.024873 | ET672: -0.093939 | EU672: 0.085451 | EV672: 0.06848 | EW672: -0.056006 | EX672: 0.113387 | EY672: -0.037696 | EZ672: -0.050124 | FA672: -0.012263 | FB672: -0.039979 | FC672: 0.106961 | FD672: 0.082148 | FE672: -0.026329 | FF672: -0.052519 | FG672: -0.058072 | FH672: 0.087314 | FI672: 0.086254 | FJ672: -0.022001 | FK672: 0.027241 | FL672: 0.064789 | FM672: -0.066625 | FN672: 0.046882 | FO672: -0.015991 | FP672: 0.07244 | FQ672: 0.010649 | FR672: 0.039863 | FS672: 0.009522 | FT672: 0.093858 | FU672: -0.069416 | FV672: 0.055399 | FW672: -0.022104 | FX672: -0.056148
B673: =Deals!B673 -> Gilead Sciences, Inc. | C673: 1 | D673: 0.043336 | E673: -0.028515 | F673: 0.125987 | G673: -0.064024 | H673: 0.064169 | I673: -0.017948 | J673: 0.041594 | K673: 0.052337 | L673: -0.008278 | M673: 0.065749 | N673: -0.030503 | O673: -0.071152 | P673: 0.062423 | Q673: 0.063688 | R673: -0.054125 | S673: -0.120559 | T673: -0.003642 | U673: -0.00185 | V673: 0.092855 | W673: -0.035621 | X673: -0.033328 | Y673: 0.062259 | Z673: -0.016543 | AA673: 0.271843 | AB673: 0.119424 | AC673: -0.014232 | AD673: -0.022248 | AE673: -0.040624 | AF673: 0.039613 | AG673: -0.00916 | AH673: -0.064104 | AI673: 0.011437 | AJ673: -0.012067 | AK673: 0.004465 | AL673: -0.010329 | AM673: 0.048038 | AN673: -0.024701 | AO673: 0.067363 | AP673: -0.033946 | AQ673: -0.078712 | AR673: 0.02663 | AS673: -0.109898 | AT673: -0.014264 | AU673: 0.079508 | AV673: 0.108585 | AW673: 0.038654 | AX673: 0.071013 | AY673: 0.059399 | AZ673: 0.042333 | BA673: 0.006049 | BB673: 0.05229 | BC673: 0.176029 | BD673: -0.01286 | BM673: 0.095437 | BN673: 0.018008 | BO673: -0.004263 | BP673: 0.033434 | BQ673: 0.050128 | BR673: 0.057761 | BS673: 0.008179 | BT673: 0.014271 | BU673: 0.031948 | BV673: 0.041276 | BW673: -0.062381 | BX673: 0.056413 | BY673: -0.030068 | BZ673: 0.052595 | CA673: -0.063404 | CB673: -0.043294 | CC673: 0.035373 | CD673: -0.092215 | CE673: -0.003193 | CF673: -0.055016 | CG673: 0.054082 | CH673: -0.03048 | CI673: -0.053718 | CJ673: 0.074071 | CK673: 0.066348 | CL673: -0.037114 | CM673: 0.019238 | CN673: -0.021663 | CO673: 0.032915 | CP673: 0.01434 | CQ673: -0.011454 | CR673: 0.054518 | CS673: 0.062584 | CT673: -0.00811 | CU673: -0.043722 | CV673: -0.049086 | CW673: 0.069409 | CX673: 0.047821 | CY673: -0.005114 | CZ673: 0.016618 | DA673: 0.064515 | DB673: 0.01242 | DC673: 0.040278 | DD673: 0.01096 | DE673: 0.022329 | DF673: 0.038852 | DG673: 0.039933 | DH673: -0.013064 | DI673: 0.053371 | DJ673: -0.048243 | DK673: 0.078641 | DL673: -0.01884 | DM673: -0.04998 | DV673: 0.107181 | DW673: 0.030363 | DX673: -0.005163 | DY673: 0.036358 | DZ673: 0.054406 | EA673: 0.037926 | EB673: 0.009424 | EC673: 0.005841 | ED673: 0.007504 | EE673: 0.018091 | EF673: -0.045445 | EG673: 0.054598 | EH673: -0.036521 | EI673: 0.062596 | EJ673: -0.052353 | EK673: -0.01718 | EL673: 0.02918 | EM673: -0.064922 | EN673: 0.00681 | EO673: -0.072194 | EP673: 0.087506 | EQ673: -0.022641 | ER673: -0.065037 | ES673: 0.097577 | ET673: 0.065188 | EU673: -0.052193 | EV673: 0.04789 | EW673: -0.022741 | EX673: 0.007548 | EY673: 0.004502 | EZ673: -0.023821 | FA673: 0.074965 | FB673: 0.043995 | FC673: -0.029982 | FD673: -0.049891 | FE673: -0.058507 | FF673: 0.075235 | FG673: 0.064448 | FH673: -0.021101 | FI673: 0.051823 | FJ673: 0.054538 | FK673: -0.026294 | FL673: 0.028052 | FM673: -0.019401 | FN673: 0.049667 | FO673: 0.019289 | FP673: 0.028512 | FQ673: -0.005521 | FR673: 0.068438 | FS673: -0.070851 | FT673: 0.047296 | FU673: -0.021506 | FV673: -0.026357
B674: =Deals!B674 -> Ligand Pharmaceuticals Inc | C674: 1 | D674: 0.023287 | E674: 0.178737 | F674: 0.863751 | G674: -0.200324 | H674: 0.028539 | I674: -0.043031 | J674: -0.193228 | K674: 0.114613 | L674: -0.134766 | M674: 0.165536 | N674: 0.053061 | O674: 0.047517 | P674: 0.109497 | Q674: -0.046072 | R674: -0.193124 | S674: -0.187836 | T674: 0.111342 | U674: -0.174504 | V674: -0.042537 | W674: 0.003487 | X674: 0.031495 | Y674: 0.003912 | Z674: -0.067973 | AA674: 0.017884 | AB674: -0.168283 | AC674: -0.083676 | AD674: 0.043413 | AE674: 0.035007 | AF674: 0.019684 | AG674: 0.037928 | AH674: -0.082122 | AI674: 0.028824 | AJ674: -0.071706 | AK674: -0.017332 | AL674: -0.088946 | AM674: -0.127336 | AN674: 0.115127 | AO674: 0.224833 | AP674: 0.023523 | AQ674: 0.085499 | AR674: -0.078765 | AS674: -0.043912 | AT674: 0.216912 | AU674: -0.009289 | AV674: 0.293496 | AW674: -0.029269 | AX674: -0.05397 | AY674: 0.05605 | AZ674: 0.149196 | BA674: -0.117889 | BB674: 0.087727 | BC674: 0.048734 | BD674: -0.139818 | BM674: 0.183297 | BN674: 0.08958 | BO674: 0.077042 | BP674: 0.09566 | BQ674: 0.02182 | BR674: 0.023396 | BS674: 0.011055 | BT674: 0.012853 | BU674: -0.018155 | BV674: 0.013589 | BW674: -0.034063 | BX674: 0.039859 | BY674: 0.0057 | BZ674: 0.0589 | CA674: -0.095829 | CB674: 0.005483 | CC674: 0.017931 | CD674: -0.080424 | CE674: 0.023442 | CF674: -0.072115 | CG674: 0.115972 | CH674: -0.044554 | CI674: -0.114803 | CJ674: 0.104466 | CK674: 0.004422 | CL674: -0.070133 | CM674: 0.1231 | CN674: -0.00465 | CO674: -0.032965 | CP674: -0.032649 | CQ674: 0.019558 | CR674: 0.091615 | CS674: 0.061544 | CT674: -0.036861 | CU674: -0.046311 | CV674: -0.069716 | CW674: 0.086093 | CX674: 0.108974 | CY674: -0.035745 | CZ674: 0.06812 | DA674: 0.025352 | DB674: -0.065718 | DC674: 0.052673 | DD674: -0.021843 | DE674: 0.098444 | DF674: -0.036221 | DG674: 0.009113 | DH674: -0.032464 | DI674: 0.108871 | DJ674: -0.087427 | DK674: 0.036021 | DL674: -0.082942 | DM674: -0.084026 | DV674: 0.193071 | DW674: 0.097805 | DX674: 0.082572 | DY674: 0.092176 | DZ674: 0.032457 | EA674: 0.023833 | EB674: 0.016413 | EC674: 0.003494 | ED674: -0.023492 | EE674: 0.010659 | EF674: -0.035282 | EG674: 0.041156 | EH674: -0.003587 | EI674: 0.054826 | EJ674: -0.097752 | EK674: 0.003239 | EL674: 0.007621 | EM674: -0.080781 | EN674: 0.012501 | EO674: -0.060414 | EP674: 0.113842 | EQ674: -0.039008 | ER674: -0.119468 | ES674: 0.105606 | ET674: 0.003522 | EU674: -0.065539 | EV674: 0.134282 | EW674: -0.02221 | EX674: -0.049024 | EY674: -0.025935 | EZ674: 0.015862 | FA674: 0.096287 | FB674: 0.061646 | FC674: -0.040878 | FD674: -0.054465 | FE674: -0.078234 | FF674: 0.101981 | FG674: 0.125443 | FH674: -0.045067 | FI674: 0.078133 | FJ674: 0.031478 | FK674: -0.080992 | FL674: 0.054415 | FM674: -0.025984 | FN674: 0.100317 | FO674: -0.040457 | FP674: 0.012299 | FQ674: -0.028165 | FR674: 0.103669 | FS674: -0.083363 | FT674: 0.030766 | FU674: -0.088055 | FV674: -0.091066
B675: =Deals!B675 -> MarineMax, Inc. | C675: 1 | D675: 0.095397 | E675: 0.066687 | F675: 0.194119 | G675: 0.067416 | H675: 0.105487 | I675: 0.150729 | J675: -0.094542 | K675: -0.052304 | L675: 0.103611 | M675: -0.096115 | N675: -0.002057 | O675: 0.067395 | P675: 0.028577 | Q675: 0.108316 | R675: -0.202913 | S675: -0.027624 | T675: -0.120192 | U675: 0.016393 | V675: 0.011975 | W675: -0.127747 | X675: 0.130676 | Y675: -0.110186 | Z675: -0.180242 | AA675: 0.084592 | AB675: 0.022284 | AC675: -0.054799 | AD675: 0.000961 | AE675: 0.07456 | AF675: -0.143836 | AG675: 0.01287 | AH675: -0.025755 | AI675: 0.204089 | AJ675: 0.180621 | AK675: -0.175056 | AL675: -0.013526 | AM675: -0.165753 | AN675: 0.089481 | AO675: 0.304056 | AP675: -0.280206 | AQ675: 0.185714 | AR675: 0.001807 | AS675: -0.258268 | AT675: 0.154439 | AU675: 0.136587 | AV675: 0.077232 | AW675: -0.090336 | AX675: 0.111917 | AY675: -0.174086 | AZ675: 0.178167 | BA675: -0.156469 | BB675: 0.048705 | BC675: -0.16502 | BD675: -0.151874 | BM675: 0.187037 | BN675: 0.088872 | BO675: 0.042029 | BP675: 0.122259 | BQ675: 0.046456 | BR675: 0.006733 | BS675: 0.026615 | BT675: -0.017984 | BU675: -0.022034 | BV675: 0.01685 | BW675: -0.007108 | BX675: 0.049723 | BY675: -0.026919 | BZ675: 0.060643 | CA675: -0.05249 | CB675: 0.031228 | CC675: -0.001624 | CD675: -0.063465 | CE675: 0.040402 | CF675: -0.06493 | CG675: 0.098137 | CH675: -0.038615 | CI675: -0.094177 | CJ675: 0.1276 | CK675: 0.044059 | CL675: -0.052868 | CM675: 0.082098 | CN675: -0.026258 | CO675: -0.052486 | CP675: -0.030739 | CQ675: 0.020507 | CR675: 0.088055 | CS675: 0.084062 | CT675: -0.050354 | CU675: -0.057355 | CV675: -0.039185 | CW675: 0.087086 | CX675: 0.133132 | CY675: -0.049956 | CZ675: 0.045055 | DA675: 0.027131 | DB675: -0.05644 | DC675: 0.047468 | DD675: -0.014183 | DE675: 0.120522 | DF675: -0.02238 | DG675: -0.004959 | DH675: -0.004851 | DI675: 0.126278 | DJ675: -0.088626 | DK675: 0.030713 | DL675: -0.05651 | DM675: -0.060607 | DV675: 0.193279 | DW675: 0.088936 | DX675: 0.053208 | DY675: 0.127437 | DZ675: 0.058206 | EA675: 0.009815 | EB675: 0.02938 | EC675: -0.01931 | ED675: -0.01904 | EE675: 0.014363 | EF675: -0.004066 | EG675: 0.046113 | EH675: -0.025583 | EI675: 0.065363 | EJ675: -0.044123 | EK675: 0.027911 | EL675: 0.000467 | EM675: -0.062672 | EN675: 0.042617 | EO675: -0.071091 | EP675: 0.098027 | EQ675: -0.03928 | ER675: -0.095241 | ES675: 0.125444 | ET675: 0.039659 | EU675: -0.063255 | EV675: 0.100845 | EW675: -0.032236 | EX675: -0.067798 | EY675: -0.045484 | EZ675: -0.011718 | FA675: 0.10126 | FB675: 0.083698 | FC675: -0.052925 | FD675: -0.059869 | FE675: -0.042783 | FF675: 0.082297 | FG675: 0.137984 | FH675: -0.053643 | FI675: 0.044356 | FJ675: 0.031723 | FK675: -0.061814 | FL675: 0.048244 | FM675: -0.021929 | FN675: 0.122527 | FO675: -0.024336 | FP675: -0.003355 | FQ675: -0.00554 | FR675: 0.128018 | FS675: -0.086606 | FT675: 0.026976 | FU675: -0.065102 | FV675: -0.05041
B676: =Deals!B676 -> Cryoport, Inc. | C676: 1 | D676: 0.212008 | E676: -0.098047 | F676: 0.554239 | G676: -0.128446 | H676: -0.125 | I676: 0.087675 | J676: -0.01149 | K676: 0.128398 | L676: -0.02187 | M676: 0.029974 | N676: 0.046248 | O676: 0.225981 | P676: -0.185185 | Q676: -0.109422 | R676: -0.294068 | S676: -0.178118 | T676: 0.016895 | U676: -0.353767 | V676: 0.128103 | W676: 0.217289 | X676: 0.200775 | Y676: -0.122043 | Z676: -0.254133 | AA676: 0.139573 | AB676: -0.288545 | AC676: -0.121519 | AD676: 0.31585 | AE676: -0.051248 | AF676: 0.108033 | AG676: -0.123333 | AH676: -0.125 | AI676: -0.063009 | AJ676: -0.068406 | AK676: -0.122589 | AL676: -0.02766 | AM676: -0.292487 | AN676: 0.445361 | AO676: 0.10485 | AP676: -0.063267 | AQ676: 0.217781 | AR676: 0.001698 | AS676: -0.085311 | AT676: -0.36504 | AU676: -0.327821 | AV676: 0.335745 | AW676: 0.009751 | AX676: -0.129828 | AY676: -0.178792 | AZ676: 0.063063 | BA676: 0.09887 | BB676: -0.030848 | BC676: -0.261273 | BD676: 0.091562 | BM676: 0.207556 | BN676: 0.12645 | BO676: 0.024415 | BP676: -0.000483 | BQ676: -0.047837 | BR676: 0.02869 | BS676: -0.033421 | BT676: 0.054695 | BU676: -0.02501 | BV676: 0.019022 | BW676: -0.038561 | BX676: 0.046626 | BY676: -0.08576 | BZ676: 0.000968 | CA676: -0.142109 | CB676: -0.007716 | CC676: 0.017833 | CD676: -0.117955 | CE676: -0.053077 | CF676: -0.044319 | CG676: 0.116268 | CH676: -0.038541 | CI676: -0.088512 | CJ676: 0.034639 | CK676: 0.031372 | CL676: -0.043533 | CM676: 0.106176 | CN676: -0.003618 | CO676: -0.008652 | CP676: -0.032515 | CQ676: 0.010489 | CR676: 0.068229 | CS676: 0.053331 | CT676: -0.053394 | CU676: -0.058727 | CV676: -0.073528 | CW676: 0.111124 | CX676: 0.103291 | CY676: -0.042161 | CZ676: 0.032515 | DA676: 0.006384 | DB676: -0.06286 | DC676: 0.046483 | DD676: 0.028059 | DE676: 0.064974 | DF676: -0.001472 | DG676: 0.042635 | DH676: -0.016588 | DI676: 0.102793 | DJ676: -0.079478 | DK676: 0.053794 | DL676: -0.056928 | DM676: -0.07451 | DV676: 0.21392 | DW676: 0.129432 | DX676: 0.017059 | DY676: 0.021424 | DZ676: -0.036464 | EA676: 0.030769 | EB676: -0.028421 | EC676: 0.061708 | ED676: -0.023545 | EE676: 0.015868 | EF676: -0.039964 | EG676: 0.047113 | EH676: -0.084736 | EI676: -0.003415 | EJ676: -0.141596 | EK676: -0.016339 | EL676: 0.004296 | EM676: -0.138311 | EN676: -0.045222 | EO676: -0.046504 | EP676: 0.116767 | EQ676: -0.030875 | ER676: -0.092886 | ES676: 0.038196 | ET676: 0.031364 | EU676: -0.050589 | EV676: 0.12749 | EW676: -0.008377 | EX676: -0.018392 | EY676: -0.031244 | EZ676: 0.024876 | FA676: 0.074528 | FB676: 0.058153 | FC676: -0.055866 | FD676: -0.061774 | FE676: -0.07758 | FF676: 0.128905 | FG676: 0.115622 | FH676: -0.04519 | FI676: 0.029184 | FJ676: 0.003445 | FK676: -0.066565 | FL676: 0.07274 | FM676: 0.026772 | FN676: 0.068904 | FO676: -0.001826 | FP676: 0.034451 | FQ676: -0.012354 | FR676: 0.129517 | FS676: -0.079792 | FT676: 0.048261 | FU676: -0.057773 | FV676: -0.075988
B677: =Deals!B677 -> KBR, Inc. | C677: 1 | D677: 0.24585 | E677: 0.117393 | F677: -0.060782 | G677: 0.067126 | H677: 0.238387 | I677: 0.030477 | J677: 0.029828 | K677: -0.060874 | L677: 0.014417 | M677: 0.006202 | N677: 0.014638 | O677: 0.077157 | P677: 0.036758 | Q677: 0.084773 | R677: -0.088618 | S677: 0.143779 | T677: 0.104956 | U677: -0.100493 | V677: 0.010766 | W677: -0.025121 | X677: 0.100021 | Y677: -0.092617 | Z677: -0.102692 | AA677: 0.15155 | AB677: 0.038176 | AC677: 0.024192 | AD677: -0.029735 | AE677: 0.075737 | AF677: 0.001361 | AG677: 0.030518 | AH677: 0.040367 | AI677: 0.104626 | AJ677: -0.054872 | AK677: 0.000488 | AL677: -0.039743 | AM677: -0.013403 | AN677: -0.111436 | AO677: 0.074995 | AP677: -0.059556 | AQ677: 0.151986 | AR677: 0.062969 | AS677: 0.020107 | AT677: 0.011087 | AU677: -0.020865 | AV677: 0.038198 | AW677: 0.041598 | AX677: -0.058824 | AY677: 0.028865 | AZ677: -0.092225 | BA677: -0.045208 | BB677: -0.06059 | BC677: -0.099044 | BD677: 0.019274 | BM677: 0.166688 | BN677: 0.086023 | BO677: 0.018859 | BP677: 0.124743 | BQ677: 0.062936 | BR677: 0.022207 | BS677: 0.019771 | BT677: -0.032132 | BU677: -0.009893 | BV677: 0.018473 | BW677: -0.048492 | BX677: 0.039037 | BY677: -0.024358 | BZ677: 0.052503 | CA677: -0.039308 | CB677: -0.002388 | CC677: 0.003781 | CD677: -0.066351 | CE677: 0.042167 | CF677: -0.106721 | CG677: 0.07714 | CH677: -0.017984 | CI677: -0.102042 | CJ677: 0.144777 | CK677: 0.068711 | CL677: -0.067906 | CM677: 0.076853 | CN677: -0.016453 | CO677: -0.046464 | CP677: -0.012823 | CQ677: -0.036533 | CR677: 0.091363 | CS677: 0.086874 | CT677: -0.065287 | CU677: -0.051739 | CV677: -0.047857 | CW677: 0.112489 | CX677: 0.122413 | CY677: -0.034258 | CZ677: 0.016457 | DA677: 0.046139 | DB677: -0.064626 | DC677: 0.053275 | DD677: -0.027688 | DE677: 0.104114 | DF677: -0.013943 | DG677: 0.000766 | DH677: -0.013824 | DI677: 0.097792 | DJ677: -0.089497 | DK677: 0.027332 | DL677: -0.027759 | DM677: -0.055594 | DV677: 0.168825 | DW677: 0.081255 | DX677: 0.019686 | DY677: 0.117689 | DZ677: 0.06659 | EA677: 0.01446 | EB677: 0.023615 | EC677: -0.030644 | ED677: -0.01229 | EE677: 0.017278 | EF677: -0.052903 | EG677: 0.033634 | EH677: -0.018818 | EI677: 0.04535 | EJ677: -0.035218 | EK677: -0.007035 | EL677: 0.004345 | EM677: -0.071522 | EN677: 0.033714 | EO677: -0.118202 | EP677: 0.082529 | EQ677: -0.019642 | ER677: -0.100677 | ES677: 0.152502 | ET677: 0.068526 | EU677: -0.064298 | EV677: 0.076842 | EW677: -0.009427 | EX677: -0.050456 | EY677: -0.013969 | EZ677: -0.037495 | FA677: 0.092045 | FB677: 0.08631 | FC677: -0.06023 | FD677: -0.056655 | FE677: -0.047128 | FF677: 0.118415 | FG677: 0.124417 | FH677: -0.041467 | FI677: 0.01738 | FJ677: 0.042759 | FK677: -0.063393 | FL677: 0.055185 | FM677: -0.031237 | FN677: 0.107288 | FO677: -0.014896 | FP677: 0.002511 | FQ677: -0.016107 | FR677: 0.097455 | FS677: -0.08821 | FT677: 0.022448 | FU677: -0.029876 | FV677: -0.045354
B678: =Deals!B678 -> Spirit AeroSystems Holdings, Inc. | C678: 1 | D678: 0.869159 | E678: 0.15 | F678: -0.133538 | G678: 0.264541 | H678: 0.13612 | I678: -0.060843 | J678: 0.077041 | K678: -0.040845 | L678: -0.08434 | M678: -0.091877 | N678: 0.126402 | O678: -0.065626 | P678: -0.083071 | Q678: 0.138405 | R678: 0.017173 | S678: 0.140771 | T678: -0.022 | U678: -0.14011 | V678: -0.252617 | W678: -0.067155 | X678: 0.120137 | Y678: -0.082876 | Z678: -0.271429 | AA678: 0.056569 | AB678: 0.131693 | AC678: 0.12934 | AD678: 0.221284 | AE678: -0.054495 | AF678: 0.01024 | AG678: -0.138141 | AH678: -0.106519 | AI678: 0.097781 | AJ678: 0.090099 | AK678: -0.329981 | AL678: -0.242964 | AM678: 0.400248 | AN678: 0.216372 | AO678: 0.156057 | AP678: -0.135935 | AQ678: 0.041515 | AR678: 0.261189 | AS678: -0.112836 | AT678: -0.0525 | AU678: 0.084103 | AV678: 0.102829 | AW678: -0.02869 | AX678: -0.076683 | AY678: -0.004306 | AZ678: -0.000309 | BA678: 0.053152 | BB678: -0.002054 | BC678: 0.026169 | BD678: -0.012607 | BM678: 0.166688 | BN678: 0.086023 | BO678: 0.018859 | BP678: 0.124743 | BQ678: 0.062936 | BR678: 0.022207 | BS678: 0.019771 | BT678: -0.032132 | BU678: -0.009893 | BV678: 0.018473 | BW678: -0.048492 | BX678: 0.039037 | BY678: -0.024358 | BZ678: 0.052503 | CA678: -0.039308 | CB678: -0.002388 | CC678: 0.003781 | CD678: -0.066351 | CE678: 0.042167 | CF678: -0.106721 | CG678: 0.07714 | CH678: -0.017984 | CI678: -0.102042 | CJ678: 0.144777 | CK678: 0.068711 | CL678: -0.067906 | CM678: 0.076853 | CN678: -0.016453 | CO678: -0.046464 | CP678: -0.012823 | CQ678: -0.036533 | CR678: 0.091363 | CS678: 0.086874 | CT678: -0.065287 | CU678: -0.051739 | CV678: -0.047857 | CW678: 0.112489 | CX678: 0.122413 | CY678: -0.034258 | CZ678: 0.016457 | DA678: 0.046139 | DB678: -0.064626 | DC678: 0.053275 | DD678: -0.027688 | DE678: 0.104114 | DF678: -0.013943 | DG678: 0.000766 | DH678: -0.013824 | DI678: 0.097792 | DJ678: -0.089497 | DK678: 0.027332 | DL678: -0.027759 | DM678: -0.055594 | DV678: 0.168825 | DW678: 0.081255 | DX678: 0.019686 | DY678: 0.117689 | DZ678: 0.06659 | EA678: 0.01446 | EB678: 0.023615 | EC678: -0.030644 | ED678: -0.01229 | EE678: 0.017278 | EF678: -0.052903 | EG678: 0.033634 | EH678: -0.018818 | EI678: 0.04535 | EJ678: -0.035218 | EK678: -0.007035 | EL678: 0.004345 | EM678: -0.071522 | EN678: 0.033714 | EO678: -0.118202 | EP678: 0.082529 | EQ678: -0.019642 | ER678: -0.100677 | ES678: 0.152502 | ET678: 0.068526 | EU678: -0.064298 | EV678: 0.076842 | EW678: -0.009427 | EX678: -0.050456 | EY678: -0.013969 | EZ678: -0.037495 | FA678: 0.092045 | FB678: 0.08631 | FC678: -0.06023 | FD678: -0.056655 | FE678: -0.047128 | FF678: 0.118415 | FG678: 0.124417 | FH678: -0.041467 | FI678: 0.01738 | FJ678: 0.042759 | FK678: -0.063393 | FL678: 0.055185 | FM678: -0.031237 | FN678: 0.107288 | FO678: -0.014896 | FP678: 0.002511 | FQ678: -0.016107 | FR678: 0.097455 | FS678: -0.08821 | FT678: 0.022448 | FU678: -0.029876 | FV678: -0.045354
B679: =Deals!B679 -> Sunrun Inc. | C679: 1 | D679: 0.231834 | E679: 0.082709 | F679: -0.001585 | G679: -0.096579 | H679: -0.033557 | I679: -0.189815 | J679: -0.087347 | K679: 0.247317 | L679: -0.050376 | M679: -0.164621 | N679: -0.00565 | O679: 0.310909 | P679: -0.201803 | Q679: -0.254996 | R679: -0.244023 | S679: 0.052063 | T679: 0.11327 | U679: -0.342114 | V679: 0.307307 | W679: -0.105666 | X679: 0.399401 | Y679: 0.010401 | Z679: -0.164699 | AA679: -0.184125 | AB679: 0.447357 | AC679: -0.262738 | AD679: 0.094088 | AE679: -0.085236 | AF679: -0.161814 | AG679: 0.044169 | AH679: -0.161597 | AI679: 0.012472 | AJ679: 0.06271 | AK679: -0.176502 | AL679: -0.196417 | AM679: -0.231688 | AN679: 0.336788 | AO679: 0.521705 | AP679: -0.262354 | AQ679: -0.168508 | AR679: 0.094684 | AS679: -0.219272 | AT679: 0.405248 | AU679: -0.179806 | AV679: 0.478078 | AW679: 0.170565 | AX679: -0.119883 | AY679: -0.199889 | AZ679: -0.202076 | BA679: -0.197745 | BB679: -0.021622 | BC679: -0.198895 | BD679: -0.191724 | BM679: 0.107281 | BN679: 0.053002 | BO679: -0.009351 | BP679: -0.005854 | BQ679: 0.01839 | BR679: 0.059373 | BS679: -0.013515 | BT679: 0.057192 | BU679: 0.032936 | BV679: 0.033156 | BW679: -0.052802 | BX679: 0.089956 | BY679: 0.012325 | BZ679: 0.021218 | CA679: -0.077613 | CB679: -0.033277 | CC679: 0.048718 | CD679: -0.10863 | CE679: -0.030079 | CF679: -0.078069 | CG679: 0.127169 | CH679: -0.053498 | CI679: -0.100388 | CJ679: 0.052883 | CK679: 0.047454 | CL679: -0.082033 | CM679: 0.087217 | CN679: -0.01317 | CO679: 0.081256 | CP679: 0.01129 | CQ679: 0.054991 | CR679: 0.072447 | CS679: 0.023838 | CT679: -0.008326 | CU679: -0.05542 | CV679: -0.009954 | CW679: 0.098907 | CX679: 0.037524 | CY679: 0.022668 | CZ679: 0.060191 | DA679: 0.016533 | DB679: -0.040193 | DC679: 0.059598 | DD679: 0.061092 | DE679: -0.008513 | DF679: 0.021543 | DG679: 0.024194 | DH679: -0.007924 | DI679: 0.063182 | DJ679: 0.003266 | DK679: 0.014885 | DL679: -0.031109 | DM679: -0.076633 | DV679: 0.130555 | DW679: 0.041795 | DX679: -0.018249 | DY679: 0.019443 | DZ679: 0.020896 | EA679: 0.053291 | EB679: -0.004423 | EC679: 0.043268 | ED679: 0.030241 | EE679: 0.029029 | EF679: -0.051931 | EG679: 0.076494 | EH679: -0.023675 | EI679: 0.027244 | EJ679: -0.105932 | EK679: -0.028087 | EL679: 0.024591 | EM679: -0.102794 | EN679: -0.042047 | EO679: -0.081421 | EP679: 0.115932 | EQ679: -0.040409 | ER679: -0.09131 | ES679: 0.077555 | ET679: 0.068696 | EU679: -0.064949 | EV679: 0.083649 | EW679: -0.013406 | EX679: 0.044705 | EY679: -0.010179 | EZ679: 0.017315 | FA679: 0.073915 | FB679: 0.027187 | FC679: -0.023523 | FD679: -0.051409 | FE679: -0.03327 | FF679: 0.105435 | FG679: 0.064066 | FH679: 0.005583 | FI679: 0.053753 | FJ679: 0.021634 | FK679: -0.048148 | FL679: 0.010258 | FM679: 0.019325 | FN679: 0.000127 | FO679: 0.029717 | FP679: 0.023121 | FQ679: -0.009897 | FR679: 0.082276 | FS679: -0.042846 | FT679: 0.045785 | FU679: -0.023907 | FV679: -0.062674
B680: =Deals!B680 -> Southwestern Energy Company | C680: 1 | D680: -0.041801 | E680: 0.265101 | F680: 0.074271 | G680: 0.148148 | H680: -0.08172 | I680: 0.210773 | J680: 0.096712 | K680: -0.169312 | L680: -0.03397 | M680: 0.217582 | N680: -0.119134 | O680: -0.081967 | P680: 0.040179 | Q680: -0.055794 | R680: 0.134091 | S680: 0.436874 | T680: 0.046025 | U680: 0.216 | V680: -0.314693 | W680: 0.1296 | X680: 0.060907 | Y680: -0.182911 | Z680: 0.132353 | AA680: -0.001443 | AB680: -0.154624 | AC680: -0.05641 | AD680: -0.039855 | AE680: -0.056604 | AF680: 0.038 | AG680: -0.080925 | AH680: 0.259958 | AI680: 0.078203 | AJ680: 0.046296 | AK680: -0.048673 | AL680: 0.105426 | AM680: -0.075736 | AN680: -0.00607 | AO680: -0.015267 | AP680: 0.08062 | AQ680: 0.087518 | AR680: -0.011873 | AS680: 0.00534 | AT680: -0.106242 | AU680: -0.041605 | AV680: -0.010853 | AW680: 0.11442 | AX680: -0.009615 | AY680: 0.11257 | AZ680: -0.067704 | BA680: 0.025424 | BB680: -0.042389 | BC680: -0.072074 | BM680: 0.071491 | BN680: 0.089893 | BO680: 0.08839 | BP680: 0.074558 | BQ680: 0.012305 | BR680: 0.071065 | BS680: 0.004465 | BT680: -0.060784 | BU680: 0.024565 | BV680: 0.033738 | BW680: 0.028453 | BX680: -0.040391 | BY680: 0.050249 | BZ680: 0.003868 | CA680: 0.027265 | CB680: -0.000287 | CC680: -0.060679 | CD680: 0.059566 | CE680: -0.128977 | CF680: 0.092258 | CG680: -0.024771 | CH680: -0.101276 | CI680: 0.157299 | CJ680: 0.014679 | CK680: -0.056763 | CL680: 0.066881 | CM680: -0.015086 | CN680: -0.100858 | CO680: -0.029129 | CP680: -0.049448 | CQ680: 0.082103 | CR680: 0.102372 | CS680: -0.042175 | CT680: -0.063858 | CU680: -0.070333 | CV680: 0.106582 | CW680: 0.156883 | CX680: -0.059712 | CY680: 0.008072 | CZ680: 0.043252 | DA680: -0.067276 | DB680: 0.055662 | DC680: -0.02875 | DD680: 0.149324 | DE680: -0.018352 | DF680: -0.009528 | DG680: -0.009615 | DH680: 0.11257 | DI680: -0.067704 | DJ680: 0.025424 | DK680: -0.042389 | DL680: -0.072074 | DV680: 0.066273 | DW680: 0.082058 | DX680: 0.104681 | DY680: 0.087232 | DZ680: 0.018575 | EA680: 0.064895 | EB680: -0.004041 | EC680: -0.062834 | ED680: 0.023676 | EE680: 0.038432 | EF680: 0.027954 | EG680: -0.042826 | EH680: 0.047521 | EI680: 0.005107 | EJ680: 0.031754 | EK680: 0.002859 | EL680: -0.064882 | EM680: 0.048428 | EN680: -0.118309 | EO680: 0.088304 | EP680: -0.01777 | EQ680: -0.107483 | ER680: 0.153918 | ES680: 0.014489 | ET680: -0.056602 | EU680: 0.077091 | EV680: -0.018164 | EW680: -0.10622 | EX680: -0.03736 | EY680: -0.047588 | EZ680: 0.085889 | FA680: 0.103458 | FB680: -0.027839 | FC680: -0.069414 | FD680: -0.078196 | FE680: 0.117579 | FF680: 0.155973 | FG680: -0.059929 | FH680: 0.0096 | FI680: 0.049697 | FJ680: -0.073271 | FK680: 0.057942 | FL680: -0.038418 | FM680: 0.151899 | FN680: -0.021682 | FO680: -0.00605 | FP680: -0.013066 | FQ680: 0.118278 | FR680: -0.07173 | FS680: 0.015888 | FT680: -0.041501 | FU680: -0.079441
B681: =Deals!B681 -> Helios Technologies, Inc. | C681: 1 | D681: 0.08247 | E681: 0.025333 | F681: 0.1989 | G681: 0.11422 | H681: -0.008097 | I681: -0.017017 | J681: 0.098522 | K681: 0.035874 | L681: 0.009524 | M681: 0.006003 | N681: 0.109974 | O681: 0.101922 | P681: 0.048241 | Q681: -0.270514 | R681: 0.023229 | S681: 0.023466 | T681: -0.161745 | U681: 0.018458 | V681: -0.031716 | W681: 0.038792 | X681: -0.206335 | Y681: -0.073599 | Z681: 0.122134 | AA681: -0.069677 | AB681: 0.032234 | AC681: 0.213997 | AD681: 0.026364 | AE681: -0.034544 | AF681: -0.079052 | AG681: -0.177752 | AH681: 0.336502 | AI681: -0.042366 | AJ681: -0.084177 | AK681: -0.041465 | AL681: -0.06615 | AM681: -0.257927 | AN681: 0.181605 | AO681: -0.088203 | AP681: 0.070044 | AQ681: 0.012231 | AR681: 0.011188 | AS681: 0.110421 | AT681: -0.046526 | AU681: -0.037696 | AV681: -0.038303 | AW681: 0.07943 | AX681: -0.031027 | AY681: 0.134186 | AZ681: -0.146789 | BA681: 0.001344 | BB681: -0.115669 | BC681: -0.186565 | BM681: 0.08958 | BN681: 0.077042 | BO681: 0.09566 | BP681: 0.02182 | BQ681: 0.023396 | BR681: 0.011055 | BS681: 0.012853 | BT681: -0.018155 | BU681: 0.013589 | BV681: -0.034063 | BW681: 0.039859 | BX681: 0.0057 | BY681: 0.0589 | BZ681: -0.095829 | CA681: 0.005483 | CB681: 0.017931 | CC681: -0.080424 | CD681: 0.023442 | CE681: -0.072115 | CF681: 0.115972 | CG681: -0.044554 | CH681: -0.114803 | CI681: 0.104466 | CJ681: 0.004422 | CK681: -0.070133 | CL681: 0.1231 | CM681: -0.00465 | CN681: -0.032965 | CO681: -0.032649 | CP681: 0.019558 | CQ681: 0.091615 | CR681: 0.061544 | CS681: -0.036861 | CT681: -0.046311 | CU681: -0.069716 | CV681: 0.086093 | CW681: 0.108974 | CX681: -0.035745 | CY681: 0.06812 | CZ681: 0.025352 | DA681: -0.065718 | DB681: 0.052673 | DC681: -0.021843 | DD681: 0.098444 | DE681: -0.036221 | DF681: 0.009113 | DG681: -0.032464 | DH681: 0.108871 | DI681: -0.087427 | DJ681: 0.036021 | DK681: -0.082942 | DL681: -0.084026 | DV681: 0.097805 | DW681: 0.082572 | DX681: 0.092176 | DY681: 0.032457 | DZ681: 0.023833 | EA681: 0.016413 | EB681: 0.003494 | EC681: -0.023492 | ED681: 0.010659 | EE681: -0.035282 | EF681: 0.041156 | EG681: -0.003587 | EH681: 0.054826 | EI681: -0.097752 | EJ681: 0.003239 | EK681: 0.007621 | EL681: -0.080781 | EM681: 0.012501 | EN681: -0.060414 | EO681: 0.113842 | EP681: -0.039008 | EQ681: -0.119468 | ER681: 0.105606 | ES681: 0.003522 | ET681: -0.065539 | EU681: 0.134282 | EV681: -0.02221 | EW681: -0.049024 | EX681: -0.025935 | EY681: 0.015862 | EZ681: 0.096287 | FA681: 0.061646 | FB681: -0.040878 | FC681: -0.054465 | FD681: -0.078234 | FE681: 0.101981 | FF681: 0.125443 | FG681: -0.045067 | FH681: 0.078133 | FI681: 0.031478 | FJ681: -0.080992 | FK681: 0.054415 | FL681: -0.025984 | FM681: 0.100317 | FN681: -0.040457 | FO681: 0.012299 | FP681: -0.028165 | FQ681: 0.103669 | FR681: -0.083363 | FS681: 0.030766 | FT681: -0.088055 | FU681: -0.091066
B682: =Deals!B682 -> KAR Auction Services, Inc. | C682: 1 | D682: 0.031025 | E682: -0.00806 | F682: -0.246479 | G682: 0.078361 | H682: -0.000667 | I682: 0.196798 | J682: -0.021739 | K682: -0.060969 | L682: 0.026092 | M682: -0.030751 | N682: -0.104942 | O682: 0.021813 | P682: 0.042028 | Q682: -0.089629 | R682: 0.298172 | S682: -0.02221 | T682: -0.187812 | U682: 0.089359 | V682: -0.075141 | W682: 0.157752 | X682: -0.146199 | Y682: -0.234932 | Z682: 0.300806 | AA682: -0.05437 | AB682: -0.050218 | AC682: 0.115709 | AD682: -0.018544 | AE682: -0.042687 | AF682: -0.010234 | AG682: 0.109306 | AH682: 0.013316 | AI682: 0.031537 | AJ682: -0.005732 | AK682: -0.044202 | AL682: -0.099866 | AM682: 0.088608 | AN682: 0.012996 | AO682: -0.049291 | AP682: 0.084517 | AQ682: 0.13294 | AR682: -0.006936 | AS682: 0.004075 | AT682: -0.038261 | AU682: 0.077758 | AV682: -0.030761 | AW682: -0.025967 | AX682: -0.063981 | AY682: 0.278481 | AZ682: -0.017822 | BA682: 0.02369 | BB682: 0.097981 | BC682: -0.135426 | BM682: 0.086023 | BN682: 0.018859 | BO682: 0.124743 | BP682: 0.062936 | BQ682: 0.022207 | BR682: 0.019771 | BS682: -0.032132 | BT682: -0.009893 | BU682: 0.018473 | BV682: -0.048492 | BW682: 0.039037 | BX682: -0.024358 | BY682: 0.052503 | BZ682: -0.039308 | CA682: -0.002388 | CB682: 0.003781 | CC682: -0.066351 | CD682: 0.042167 | CE682: -0.106721 | CF682: 0.07714 | CG682: -0.017984 | CH682: -0.102042 | CI682: 0.144777 | CJ682: 0.068711 | CK682: -0.067906 | CL682: 0.076853 | CM682: -0.016453 | CN682: -0.046464 | CO682: -0.012823 | CP682: -0.036533 | CQ682: 0.091363 | CR682: 0.086874 | CS682: -0.065287 | CT682: -0.051739 | CU682: -0.047857 | CV682: 0.112489 | CW682: 0.122413 | CX682: -0.034258 | CY682: 0.016457 | CZ682: 0.046139 | DA682: -0.064626 | DB682: 0.053275 | DC682: -0.027688 | DD682: 0.104114 | DE682: -0.013943 | DF682: 0.000766 | DG682: -0.013824 | DH682: 0.097792 | DI682: -0.089497 | DJ682: 0.027332 | DK682: -0.027759 | DL682: -0.055594 | DV682: 0.081255 | DW682: 0.019686 | DX682: 0.117689 | DY682: 0.06659 | DZ682: 0.01446 | EA682: 0.023615 | EB682: -0.030644 | EC682: -0.01229 | ED682: 0.017278 | EE682: -0.052903 | EF682: 0.033634 | EG682: -0.018818 | EH682: 0.04535 | EI682: -0.035218 | EJ682: -0.007035 | EK682: 0.004345 | EL682: -0.071522 | EM682: 0.033714 | EN682: -0.118202 | EO682: 0.082529 | EP682: -0.019642 | EQ682: -0.100677 | ER682: 0.152502 | ES682: 0.068526 | ET682: -0.064298 | EU682: 0.076842 | EV682: -0.009427 | EW682: -0.050456 | EX682: -0.013969 | EY682: -0.037495 | EZ682: 0.092045 | FA682: 0.08631 | FB682: -0.06023 | FC682: -0.056655 | FD682: -0.047128 | FE682: 0.118415 | FF682: 0.124417 | FG682: -0.041467 | FH682: 0.01738 | FI682: 0.042759 | FJ682: -0.063393 | FK682: 0.055185 | FL682: -0.031237 | FM682: 0.107288 | FN682: -0.014896 | FO682: 0.002511 | FP682: -0.016107 | FQ682: 0.097455 | FR682: -0.08821 | FS682: 0.022448 | FT682: -0.029876 | FU682: -0.045354
B683: =Deals!B683 -> Tenet Healthcare Corp | C683: 1 | D683: 0.183822 | E683: 0.079331 | F683: 0.019208 | G683: 0.139615 | H683: 0.129092 | I683: 0.001196 | J683: 0.072399 | K683: 0.048859 | L683: -0.118248 | M683: 0.078567 | N683: 0.016885 | O683: 0.121037 | P683: -0.092667 | Q683: 0.160146 | R683: -0.000349 | S683: -0.156468 | T683: -0.107571 | U683: -0.187761 | V683: 0.257991 | W683: -0.145493 | X683: -0.08708 | Y683: -0.139977 | Z683: 0.041028 | AA683: 0.056518 | AB683: 0.124206 | AC683: 0.067092 | AD683: 0.015206 | AE683: 0.233928 | AF683: -0.028914 | AG683: 0.142978 | AH683: -0.081715 | AI683: 0.03787 | AJ683: -0.150464 | AK683: -0.185005 | AL683: 0.285102 | AM683: 0.095059 | AN683: 0.094879 | AO683: 0.124003 | AP683: 0.130215 | AQ683: 0.068309 | AR683: 0.204203 | AS683: -0.016196 | AT683: 0.12531 | AU683: 0.107816 | AV683: 0.002171 | AW683: -0.067268 | AX683: -0.079603 | AY683: -0.115293 | AZ683: 0.116137 | BA683: -0.101498 | BB683: 0.062485 | BM683: 0.024415 | BN683: -0.000483 | BO683: -0.047837 | BP683: 0.02869 | BQ683: -0.033421 | BR683: 0.054695 | BS683: -0.02501 | BT683: 0.019022 | BU683: -0.038561 | BV683: 0.046626 | BW683: -0.08576 | BX683: 0.000968 | BY683: -0.142109 | BZ683: -0.007716 | CA683: 0.017833 | CB683: -0.117955 | CC683: -0.053077 | CD683: -0.044319 | CE683: 0.116268 | CF683: -0.038541 | CG683: -0.088512 | CH683: 0.034639 | CI683: 0.031372 | CJ683: -0.043533 | CK683: 0.106176 | CL683: -0.003618 | CM683: -0.008652 | CN683: -0.032515 | CO683: 0.010489 | CP683: 0.068229 | CQ683: 0.053331 | CR683: -0.053394 | CS683: -0.058727 | CT683: -0.073528 | CU683: 0.111124 | CV683: 0.103291 | CW683: -0.042161 | CX683: 0.032515 | CY683: 0.006384 | CZ683: -0.06286 | DA683: 0.046483 | DB683: 0.028059 | DC683: 0.064974 | DD683: -0.001472 | DE683: 0.042635 | DF683: -0.016588 | DG683: 0.102793 | DH683: -0.079478 | DI683: 0.053794 | DJ683: -0.056928 | DK683: -0.07451 | DV683: 0.017059 | DW683: 0.021424 | DX683: -0.036464 | DY683: 0.030769 | DZ683: -0.028421 | EA683: 0.061708 | EB683: -0.023545 | EC683: 0.015868 | ED683: -0.039964 | EE683: 0.047113 | EF683: -0.084736 | EG683: -0.003415 | EH683: -0.141596 | EI683: -0.016339 | EJ683: 0.004296 | EK683: -0.138311 | EL683: -0.045222 | EM683: -0.046504 | EN683: 0.116767 | EO683: -0.030875 | EP683: -0.092886 | EQ683: 0.038196 | ER683: 0.031364 | ES683: -0.050589 | ET683: 0.12749 | EU683: -0.008377 | EV683: -0.018392 | EW683: -0.031244 | EX683: 0.024876 | EY683: 0.074528 | EZ683: 0.058153 | FA683: -0.055866 | FB683: -0.061774 | FC683: -0.07758 | FD683: 0.128905 | FE683: 0.115622 | FF683: -0.04519 | FG683: 0.029184 | FH683: 0.003445 | FI683: -0.066565 | FJ683: 0.07274 | FK683: 0.026772 | FL683: 0.068904 | FM683: -0.001826 | FN683: 0.034451 | FO683: -0.012354 | FP683: 0.129517 | FQ683: -0.079792 | FR683: 0.048261 | FS683: -0.057773 | FT683: -0.075988
B684: =Deals!B684 -> ACCO Brands Corporation | C684: 1 | D684: -0.042604 | E684: 0.001236 | F684: 0.05 | G684: 0.016588 | H684: 0.069347 | I684: -0.052689 | J684: 0.035921 | K684: 0.055369 | L684: -0.083244 | M684: -0.037253 | N684: 0.00786 | O684: 0 | P684: -0.014528 | Q684: 0.056511 | R684: -0.061047 | S684: -0.08375 | T684: 0.038881 | U684: -0.133952 | V684: 0.098009 | W684: -0.162483 | X684: -0.173693 | Y684: -0.061224 | Z684: 0.227174 | AA684: 0.003591 | AB684: 0.135957 | AC684: -0.107087 | AD684: -0.048501 | AE684: -0.139098 | AF684: 0.073144 | AG684: 0.076446 | AH684: 0.168906 | AI684: -0.112479 | AJ684: 0.076923 | AK684: -0.118467 | AL684: 0.078063 | AM684: 0.130112 | AN684: 0 | AO684: -0.082237 | AP684: 0.018817 | AQ684: -0.14082 | AR684: 0.071577 | AS684: -0.076621 | AT684: 0.087234 | AU684: 0.087084 | AV684: -0.001825 | AW684: -0.104205 | AX684: 0.203061 | AY684: -0.097938 | AZ684: 0.001905 | BA684: -0.112167 | BB684: -0.086724 | BM684: 0.089893 | BN684: 0.08839 | BO684: 0.074558 | BP684: 0.012305 | BQ684: 0.071065 | BR684: 0.004465 | BS684: -0.060784 | BT684: 0.024565 | BU684: 0.033738 | BV684: 0.028453 | BW684: -0.040391 | BX684: 0.050249 | BY684: 0.003868 | BZ684: 0.027265 | CA684: -0.000287 | CB684: -0.060679 | CC684: 0.059566 | CD684: -0.128977 | CE684: 0.092258 | CF684: -0.024771 | CG684: -0.101276 | CH684: 0.157299 | CI684: 0.014679 | CJ684: -0.056763 | CK684: 0.066881 | CL684: -0.015086 | CM684: -0.100858 | CN684: -0.029129 | CO684: -0.049448 | CP684: 0.082103 | CQ684: 0.102372 | CR684: -0.042175 | CS684: -0.063858 | CT684: -0.070333 | CU684: 0.106582 | CV684: 0.156883 | CW684: -0.059712 | CX684: 0.008072 | CY684: 0.043252 | CZ684: -0.067276 | DA684: 0.055662 | DB684: -0.02875 | DC684: 0.149324 | DD684: -0.018352 | DE684: -0.009528 | DF684: -0.009615 | DG684: 0.11257 | DH684: -0.067704 | DI684: 0.025424 | DJ684: -0.042389 | DK684: -0.072074 | DV684: 0.082058 | DW684: 0.104681 | DX684: 0.087232 | DY684: 0.018575 | DZ684: 0.064895 | EA684: -0.004041 | EB684: -0.062834 | EC684: 0.023676 | ED684: 0.038432 | EE684: 0.027954 | EF684: -0.042826 | EG684: 0.047521 | EH684: 0.005107 | EI684: 0.031754 | EJ684: 0.002859 | EK684: -0.064882 | EL684: 0.048428 | EM684: -0.118309 | EN684: 0.088304 | EO684: -0.01777 | EP684: -0.107483 | EQ684: 0.153918 | ER684: 0.014489 | ES684: -0.056602 | ET684: 0.077091 | EU684: -0.018164 | EV684: -0.10622 | EW684: -0.03736 | EX684: -0.047588 | EY684: 0.085889 | EZ684: 0.103458 | FA684: -0.027839 | FB684: -0.069414 | FC684: -0.078196 | FD684: 0.117579 | FE684: 0.155973 | FF684: -0.059929 | FG684: 0.0096 | FH684: 0.049697 | FI684: -0.073271 | FJ684: 0.057942 | FK684: -0.038418 | FL684: 0.151899 | FM684: -0.021682 | FN684: -0.00605 | FO684: -0.013066 | FP684: 0.118278 | FQ684: -0.07173 | FR684: 0.015888 | FS684: -0.041501 | FT684: -0.079441
B685: =Deals!B685 -> Td Synnex Corporation | C685: 1 | D685: 0.004666 | E685: 0.092379 | F685: 0.288022 | G685: 0.057123 | H685: 0.044554 | I685: -0.038231 | J685: -0.01659 | K685: 0.062991 | L685: -0.180767 | M685: 0.010567 | N685: -0.014667 | O685: 0.105355 | P685: -0.082984 | Q685: -0.026203 | R685: 0.013552 | S685: -0.027323 | T685: 0.037566 | U685: -0.122773 | V685: 0.105598 | W685: -0.041227 | X685: -0.15673 | Y685: 0.130804 | Z685: 0.117911 | AA685: -0.074194 | AB685: 0.082251 | AC685: -0.055115 | AD685: 0.002797 | AE685: -0.076454 | AF685: 0.003819 | AG685: 0.051689 | AH685: 0.05383 | AI685: 0.030797 | AJ685: -0.018575 | AK685: -0.07841 | AL685: 0.075916 | AM685: 0.090937 | AN685: -0.067187 | AO685: 0.039208 | AP685: 0.088547 | AQ685: 0.045447 | AR685: 0.110319 | AS685: -0.118007 | AT685: 0.036135 | AU685: 0.018881 | AV685: -0.011036 | AW685: -0.036059 | AX685: 0.031556 | AY685: -0.014371 | AZ685: 0.218878 | BA685: -0.035226 | BB685: -0.243872 | BM685: -0.002059 | BN685: 0.092254 | BO685: 0.040771 | BP685: 0.058012 | BQ685: 0.022358 | BR685: -0.012513 | BS685: -0.012862 | BT685: 0.016428 | BU685: -0.021588 | BV685: 0.053756 | BW685: -0.030463 | BX685: 0.054007 | BY685: -0.041405 | BZ685: 0.006859 | CA685: 0.035932 | CB685: -0.048852 | CC685: 0.044371 | CD685: -0.113068 | CE685: 0.068956 | CF685: -0.039545 | CG685: -0.111256 | CH685: 0.1186 | CI685: 0.053685 | CJ685: -0.047152 | CK685: 0.08114 | CL685: -0.029058 | CM685: -0.025019 | CN685: -0.00394 | CO685: -0.040008 | CP685: 0.091469 | CQ685: 0.049151 | CR685: -0.027942 | CS685: -0.067057 | CT685: -0.071421 | CU685: 0.090999 | CV685: 0.090679 | CW685: -0.014938 | CX685: 0.036154 | CY685: 0.050535 | CZ685: -0.060649 | DA685: 0.025392 | DB685: -0.023903 | DC685: 0.066677 | DD685: 0.015802 | DE685: 0.012306 | DF685: -0.014521 | DG685: 0.056845 | DH685: -0.065352 | DI685: 0.050171 | DJ685: -0.022094 | DK685: -0.035011 | DV685: 0.00476 | DW685: 0.081124 | DX685: 0.054214 | DY685: 0.05332 | DZ685: 0.016144 | EA685: -0.008976 | EB685: -0.011142 | EC685: 0.012908 | ED685: -0.016159 | EE685: 0.052565 | EF685: -0.036406 | EG685: 0.050779 | EH685: -0.041859 | EI685: 0.00545 | EJ685: 0.028508 | EK685: -0.054502 | EL685: 0.038173 | EM685: -0.110414 | EN685: 0.073636 | EO685: -0.035969 | EP685: -0.110605 | EQ685: 0.118592 | ER685: 0.057764 | ES685: -0.048956 | ET685: 0.092385 | EU685: -0.027413 | EV685: -0.02707 | EW685: -0.006752 | EX685: -0.040006 | EY685: 0.08934 | EZ685: 0.052942 | FA685: -0.029106 | FB685: -0.068619 | FC685: -0.076182 | FD685: 0.092525 | FE685: 0.095987 | FF685: -0.019535 | FG685: 0.030822 | FH685: 0.047036 | FI685: -0.066117 | FJ685: 0.037484 | FK685: -0.029571 | FL685: 0.068915 | FM685: 0.015475 | FN685: 0.013876 | FO685: -0.011102 | FP685: 0.061639 | FQ685: -0.064144 | FR685: 0.049973 | FS685: -0.030876 | FT685: -0.033423
B686: =Deals!B686 -> B&G Foods, Inc. | C686: 1 | D686: 0.373242 | E686: -0.203519 | F686: 0.03973 | G686: -0.060528 | H686: 0.048663 | I686: 0.087418 | J686: -0.12439 | K686: 0.057103 | L686: 0.000165 | M686: -0.015055 | N686: 0.023438 | O686: 0.035679 | P686: 0.01204 | Q686: -0.048232 | R686: -0.072466 | S686: -0.001853 | T686: -0.160416 | U686: 0.072755 | V686: 0.039108 | W686: -0.123432 | X686: -0.216759 | Y686: -0.006671 | Z686: -0.189255 | AA686: -0.146084 | AB686: 0.257399 | AC686: -0.096291 | AD686: 0.240726 | AE686: 0.03284 | AF686: -0.201372 | AG686: 0.101483 | AH686: -0.047414 | AI686: -0.035445 | AJ686: -0.211884 | AK686: -0.184024 | AL686: 0.144981 | AM686: 0.156926 | AN686: -0.041905 | AO686: 0.148111 | AP686: 0.006926 | AQ686: -0.02972 | AR686: -0.140541 | AS686: -0.133124 | AT686: 0.066832 | AU686: -0.017401 | AV686: 0.070838 | AW686: -0.040541 | AX686: -0.215962 | AY686: 0.05988 | AZ686: -0.059507 | BA686: 0.030864 | BB686: 0.056886 | BM686: 0.077042 | BN686: 0.09566 | BO686: 0.02182 | BP686: 0.023396 | BQ686: 0.011055 | BR686: 0.012853 | BS686: -0.018155 | BT686: 0.013589 | BU686: -0.034063 | BV686: 0.039859 | BW686: 0.0057 | BX686: 0.0589 | BY686: -0.095829 | BZ686: 0.005483 | CA686: 0.017931 | CB686: -0.080424 | CC686: 0.023442 | CD686: -0.072115 | CE686: 0.115972 | CF686: -0.044554 | CG686: -0.114803 | CH686: 0.104466 | CI686: 0.004422 | CJ686: -0.070133 | CK686: 0.1231 | CL686: -0.00465 | CM686: -0.032965 | CN686: -0.032649 | CO686: 0.019558 | CP686: 0.091615 | CQ686: 0.061544 | CR686: -0.036861 | CS686: -0.046311 | CT686: -0.069716 | CU686: 0.086093 | CV686: 0.108974 | CW686: -0.035745 | CX686: 0.06812 | CY686: 0.025352 | CZ686: -0.065718 | DA686: 0.052673 | DB686: -0.021843 | DC686: 0.098444 | DD686: -0.036221 | DE686: 0.009113 | DF686: -0.032464 | DG686: 0.108871 | DH686: -0.087427 | DI686: 0.036021 | DJ686: -0.082942 | DK686: -0.084026 | DV686: 0.082572 | DW686: 0.092176 | DX686: 0.032457 | DY686: 0.023833 | DZ686: 0.016413 | EA686: 0.003494 | EB686: -0.023492 | EC686: 0.010659 | ED686: -0.035282 | EE686: 0.041156 | EF686: -0.003587 | EG686: 0.054826 | EH686: -0.097752 | EI686: 0.003239 | EJ686: 0.007621 | EK686: -0.080781 | EL686: 0.012501 | EM686: -0.060414 | EN686: 0.113842 | EO686: -0.039008 | EP686: -0.119468 | EQ686: 0.105606 | ER686: 0.003522 | ES686: -0.065539 | ET686: 0.134282 | EU686: -0.02221 | EV686: -0.049024 | EW686: -0.025935 | EX686: 0.015862 | EY686: 0.096287 | EZ686: 0.061646 | FA686: -0.040878 | FB686: -0.054465 | FC686: -0.078234 | FD686: 0.101981 | FE686: 0.125443 | FF686: -0.045067 | FG686: 0.078133 | FH686: 0.031478 | FI686: -0.080992 | FJ686: 0.054415 | FK686: -0.025984 | FL686: 0.100317 | FM686: -0.040457 | FN686: 0.012299 | FO686: -0.028165 | FP686: 0.103669 | FQ686: -0.083363 | FR686: 0.030766 | FS686: -0.088055 | FT686: -0.091066
B687: =Deals!B687 -> Techtarget, Inc. | C687: 1 | D687: 0.263746 | E687: 0.119545 | F687: -0.169556 | G687: 0.104392 | H687: -0.083312 | I687: 0.102119 | J687: -0.056911 | K687: 0.157362 | L687: -0.025538 | M687: 0.144261 | N687: 0.0246 | O687: -0.010038 | P687: -0.132971 | Q687: -0.05498 | R687: 0.036999 | S687: -0.171875 | T687: 0.056158 | U687: -0.075538 | V687: -0.008065 | W687: -0.004449 | X687: -0.087827 | Y687: 0.090372 | Z687: -0.292641 | AA687: -0.035042 | AB687: 0.124149 | AC687: -0.238239 | AD687: -0.042672 | AE687: -0.056202 | AF687: 0.019067 | AG687: -0.103915 | AH687: 0.043367 | AI687: -0.11484 | AJ687: 0.056 | AK687: -0.170619 | AL687: 0.175536 | AM687: 0.177703 | AN687: -0.019793 | AO687: -0.071993 | AP687: 0.043204 | AQ687: -0.168682 | AR687: 0.098909 | AS687: 0.031436 | AT687: 0.026628 | AU687: -0.167188 | AV687: -0.082552 | AW687: 0.183845 | AX687: 0.109345 | AY687: -0.382747 | AZ687: -0.140767 | BA687: -0.138579 | BB687: 0.009543 | BM687: 0.116678 | BN687: 0.040745 | BO687: -0.048473 | BP687: 0.032353 | BQ687: -0.025949 | BR687: 0.06983 | BS687: -0.075376 | BT687: 0.020545 | BU687: -0.052806 | BV687: 0.024457 | BW687: -0.080613 | BX687: -0.005266 | BY687: -0.163775 | BZ687: -0.001611 | CA687: 0.012199 | CB687: -0.180685 | CC687: -0.032766 | CD687: -0.019338 | CE687: 0.128546 | CF687: 0.036743 | CG687: -0.088022 | CH687: 0.076143 | CI687: -0.002315 | CJ687: -0.050589 | CK687: 0.141421 | CL687: -0.040665 | CM687: -0.034632 | CN687: -0.027967 | CO687: 0.012513 | CP687: 0.070349 | CQ687: 0.041532 | CR687: -0.071954 | CS687: -0.091371 | CT687: -0.101457 | CU687: 0.108746 | CV687: 0.122171 | CW687: -0.039346 | CX687: 0.094637 | CY687: 0.003944 | CZ687: -0.069152 | DA687: 0.019278 | DB687: -0.016837 | DC687: 0.075097 | DD687: 0.006764 | DE687: 0.000931 | DF687: -0.008068 | DG687: 0.14058 | DH687: -0.041389 | DI687: 0.005532 | DJ687: -0.084494 | DK687: -0.082801 | DV687: 0.112618 | DW687: 0.051624 | DX687: -0.046095 | DY687: 0.028573 | DZ687: -0.026132 | EA687: 0.06635 | EB687: -0.076813 | EC687: 0.018217 | ED687: -0.053317 | EE687: 0.021146 | EF687: -0.091985 | EG687: -0.014805 | EH687: -0.173369 | EI687: -0.012789 | EJ687: 0.018464 | EK687: -0.198696 | EL687: -0.057167 | EM687: -0.02625 | EN687: 0.129928 | EO687: 0.030138 | EP687: -0.081445 | EQ687: 0.087294 | ER687: -0.006501 | ES687: -0.051629 | ET687: 0.164361 | EU687: -0.049102 | EV687: -0.042333 | EW687: -0.043651 | EX687: 0.027983 | EY687: 0.075292 | EZ687: 0.041174 | FA687: -0.071456 | FB687: -0.098155 | FC687: -0.110132 | FD687: 0.107279 | FE687: 0.142226 | FF687: -0.046726 | FG687: 0.099012 | FH687: -0.006566 | FI687: -0.088553 | FJ687: 0.04379 | FK687: -0.01381 | FL687: 0.076992 | FM687: -0.007169 | FN687: -0.005011 | FO687: -0.001446 | FP687: 0.13118 | FQ687: -0.044324 | FR687: 0.027517 | FS687: -0.087576 | FT687: -0.080425
B688: =Deals!B688 -> Csw Industrials, Inc. | C688: 1 | D688: 0.041194 | E688: 0.077669 | F688: 0.075098 | G688: 0.003037 | H688: -0.100362 | I688: -0.027582 | J688: -0.001435 | K688: 0.12258 | L688: -0.038331 | M688: 0.085513 | N688: -0.132881 | O688: 0.005491 | P688: -0.081582 | Q688: 0.084054 | R688: -0.022771 | S688: -0.10273 | T688: 0.005781 | U688: -0.029118 | V688: 0.159565 | W688: 0.05968 | X688: -0.053712 | Y688: 0.076127 | Z688: -0.061821 | AA688: -0.041505 | AB688: 0.166307 | AC688: 0.046964 | AD688: -0.018579 | AE688: -0.030663 | AF688: 0.05235 | AG688: 0.172664 | AH688: 0.086407 | AI688: -0.005096 | AJ688: -0.024439 | AK688: 0.011527 | AL688: 0.000395 | AM688: 0.169627 | AN688: 0.020057 | AO688: 0.088954 | AP688: 0.018273 | AQ688: 0.012873 | AR688: 0.070028 | AS688: 0.043459 | AT688: 0.222796 | AU688: 0.040719 | AV688: 0.085182 | AW688: -0.036273 | AX688: 0.196233 | AY688: -0.164753 | AZ688: -0.065164 | BA688: -0.07192 | BB688: -0.0476 | BM688: 0.116678 | BN688: 0.040745 | BO688: -0.048473 | BP688: 0.032353 | BQ688: -0.025949 | BR688: 0.06983 | BS688: -0.075376 | BT688: 0.020545 | BU688: -0.052806 | BV688: 0.024457 | BW688: -0.080613 | BX688: -0.005266 | BY688: -0.163775 | BZ688: -0.001611 | CA688: 0.012199 | CB688: -0.180685 | CC688: -0.032766 | CD688: -0.019338 | CE688: 0.128546 | CF688: 0.036743 | CG688: -0.088022 | CH688: 0.076143 | CI688: -0.002315 | CJ688: -0.050589 | CK688: 0.141421 | CL688: -0.040665 | CM688: -0.034632 | CN688: -0.027967 | CO688: 0.012513 | CP688: 0.070349 | CQ688: 0.041532 | CR688: -0.071954 | CS688: -0.091371 | CT688: -0.101457 | CU688: 0.108746 | CV688: 0.122171 | CW688: -0.039346 | CX688: 0.094637 | CY688: 0.003944 | CZ688: -0.069152 | DA688: 0.019278 | DB688: -0.016837 | DC688: 0.075097 | DD688: 0.006764 | DE688: 0.000931 | DF688: -0.008068 | DG688: 0.14058 | DH688: -0.041389 | DI688: 0.005532 | DJ688: -0.084494 | DK688: -0.082801 | DV688: 0.112618 | DW688: 0.051624 | DX688: -0.046095 | DY688: 0.028573 | DZ688: -0.026132 | EA688: 0.06635 | EB688: -0.076813 | EC688: 0.018217 | ED688: -0.053317 | EE688: 0.021146 | EF688: -0.091985 | EG688: -0.014805 | EH688: -0.173369 | EI688: -0.012789 | EJ688: 0.018464 | EK688: -0.198696 | EL688: -0.057167 | EM688: -0.02625 | EN688: 0.129928 | EO688: 0.030138 | EP688: -0.081445 | EQ688: 0.087294 | ER688: -0.006501 | ES688: -0.051629 | ET688: 0.164361 | EU688: -0.049102 | EV688: -0.042333 | EW688: -0.043651 | EX688: 0.027983 | EY688: 0.075292 | EZ688: 0.041174 | FA688: -0.071456 | FB688: -0.098155 | FC688: -0.110132 | FD688: 0.107279 | FE688: 0.142226 | FF688: -0.046726 | FG688: 0.099012 | FH688: -0.006566 | FI688: -0.088553 | FJ688: 0.04379 | FK688: -0.01381 | FL688: 0.076992 | FM688: -0.007169 | FN688: -0.005011 | FO688: -0.001446 | FP688: 0.13118 | FQ688: -0.044324 | FR688: 0.027517 | FS688: -0.087576 | FT688: -0.080425
B689: =Deals!B689 -> FAT Brands Inc. | C689: 1 | D689: 0.137815 | E689: 0.261448 | F689: -0.114754 | G689: 0.281746 | H689: 0.061715 | I689: 0.450246 | J689: -0.207676 | K689: 0.044983 | L689: -0.216887 | M689: 0.07074 | N689: 0.012012 | O689: 0.061122 | P689: -0.002833 | Q689: -0.289773 | R689: 0.014925 | S689: -0.204545 | T689: 0.188235 | U689: 0.073487 | V689: 0.181221 | W689: -0.021602 | X689: -0.125148 | Y689: 0.121457 | Z689: -0.158845 | AA689: -0.27781 | AB689: 0.353325 | AC689: 0.110547 | AD689: -0.033585 | AE689: -0.219858 | AF689: 0.106364 | AG689: 0.157275 | AH689: 0.0625 | AI689: -0.002736 | AJ689: -0.082308 | AK689: -0.058142 | AL689: -0.038835 | AM689: 0.044828 | AN689: 0.006965 | AO689: 0.099101 | AP689: -0.030177 | AQ689: -0.124977 | AR689: 0.073358 | AS689: -0.041906 | AT689: 0.114197 | AU689: -0.021811 | AV689: 0.030587 | AW689: 0.047145 | AX689: 0.115239 | AY689: -0.061979 | AZ689: 0.016076 | BA689: -0.066187 | BB689: -0.139327 | BM689: 0.165083 | BN689: 0.083909 | BO689: -0.055244 | BP689: -0.027003 | BQ689: 0.018956 | BR689: 0.083779 | BS689: -0.103342 | BT689: 0.025586 | BU689: -0.056338 | BV689: 0.018208 | BW689: -0.08429 | BX689: -0.067665 | BY689: -0.158681 | BZ689: -0.015223 | CA689: 0.008697 | CB689: -0.161376 | CC689: -0.055295 | CD689: -0.065598 | CE689: 0.149652 | CF689: 0.036347 | CG689: -0.129015 | CH689: 0.033099 | CI689: -0.060405 | CJ689: -0.065045 | CK689: 0.154106 | CL689: -0.040771 | CM689: -0.103145 | CN689: 0.01904 | CO689: 0.045464 | CP689: 0.07288 | CQ689: 0.023517 | CR689: -0.116052 | CS689: -0.083019 | CT689: -0.097033 | CU689: 0.049912 | CV689: 0.150898 | CW689: 0.006965 | CX689: 0.099101 | CY689: -0.030177 | CZ689: -0.124977 | DA689: 0.073358 | DB689: -0.041906 | DC689: 0.114197 | DD689: -0.021811 | DE689: 0.030587 | DF689: 0.047145 | DG689: 0.115239 | DH689: -0.061979 | DI689: 0.016076 | DJ689: -0.066187 | DK689: -0.139327 | DV689: 0.22543 | DW689: 0.091176 | DX689: -0.028298 | DY689: -0.037297 | DZ689: 0.011387 | EA689: 0.070936 | EB689: -0.104703 | EC689: 0.017921 | ED689: -0.072222 | EE689: -0.016606 | EF689: -0.11212 | EG689: -0.094973 | EH689: -0.138658 | EI689: -0.029596 | EJ689: 0.039724 | EK689: -0.185483 | EL689: -0.085558 | EM689: -0.034031 | EN689: 0.106342 | EO689: 0.064099 | EP689: -0.127659 | EQ689: 0.015749 | ER689: -0.055527 | ES689: -0.057586 | ET689: 0.164074 | EU689: -0.054561 | EV689: -0.11631 | EW689: -0.010131 | EX689: 0.044679 | EY689: 0.013592 | EZ689: -0.009781 | FA689: -0.080373 | FB689: -0.096684 | FC689: -0.081711 | FD689: 0.057956 | FE689: 0.096736 | FF689: -0.043898 | FG689: 0.07111 | FH689: -0.016705 | FI689: -0.069768 | FJ689: 0.008716 | FK689: -0.066445 | FL689: 0.056494 | FM689: -0.061303 | FN689: 0.005118 | FO689: 0.023625 | FP689: 0.042316 | FQ689: 0.04149 | FR689: 0.032226 | FS689: -0.102208 | FT689: -0.125848
B690: =Deals!B690 -> Innovate Corp. | C690: 1 | D690: 0.002865 | E690: 0.125714 | F690: 0.06599 | G690: -0.047619 | H690: -0.005 | I690: -0.075377 | J690: 0.027174 | K690: 0.084656 | L690: -0.036585 | M690: -0.035443 | N690: -0.028871 | O690: 0.062162 | P690: -0.152672 | Q690: 0.108108 | R690: -0.178862 | S690: -0.19802 | T690: -0.288066 | U690: 0.040462 | V690: -0.15 | W690: -0.542353 | X690: 0.053699 | Y690: 0.626457 | Z690: 0.558333 | AA690: 0.684492 | AB690: -0.060317 | AC690: 0.003378 | AD690: -0.037037 | AE690: -0.545455 | AF690: 0.346154 | AG690: -0.057143 | AH690: -0.030303 | AI690: 0.0125 | AJ690: -0.246914 | AK690: -0.131148 | AL690: 0.160377 | AM690: -0.265041 | AN690: -0.132412 | AO690: -0.106592 | AP690: 0.001427 | AQ690: -0.130113 | AR690: -0.009502 | AS690: -0.117764 | AT690: -0.223847 | AU690: -0.10628 | AV690: 0.586486 | AW690: 0.032368 | AX690: -0.184818 | AY690: 1.352227 | AZ690: -0.215146 | BA690: -0.141447 | BM690: -0.035384 | BN690: 0.117823 | BO690: -0.010157 | BP690: 0.107327 | BQ690: 0.037629 | BR690: -0.015695 | BS690: 0.03808 | BT690: 0.000428 | BU690: 0.041354 | BV690: -0.033466 | BW690: 0.034385 | BX690: -0.019091 | BY690: 0.029208 | BZ690: 0.024942 | CA690: -0.040798 | CB690: 0.029279 | CC690: -0.099199 | CD690: 0.058975 | CE690: -0.003345 | CF690: -0.092831 | CG690: 0.099183 | CH690: 0.015688 | CI690: -0.034399 | CJ690: 0.071003 | CK690: -0.010212 | CL690: -0.096968 | CM690: -0.041692 | CN690: -0.018759 | CO690: 0.071504 | CP690: 0.104731 | CQ690: -0.076887 | CR690: -0.059078 | CS690: -0.078456 | CT690: 0.07131 | CU690: 0.15025 | CV690: -0.035734 | CW690: 0.043465 | CX690: 0.047526 | CY690: -0.075752 | CZ690: 0.043204 | DA690: -0.025702 | DB690: 0.145137 | DC690: -0.021203 | DD690: -0.002295 | DE690: 0.006632 | DF690: 0.107518 | DG690: -0.045938 | DH690: -0.000909 | DI690: -0.023508 | DJ690: -0.066419 | DV690: 0.128665 | DW690: 0.046507 | DX690: -0.004233 | DY690: 0.062602 | DZ690: 0.061298 | EA690: -0.016461 | EB690: 0.0263 | EC690: 0.001292 | ED690: 0.028219 | EE690: -0.035104 | EF690: 0.015844 | EG690: -0.018371 | EH690: 0.016085 | EI690: 0.017487 | EJ690: -0.049066 | EK690: -0.002746 | EL690: -0.076071 | EM690: 0.038029 | EN690: 0.00642 | EO690: -0.118368 | EP690: 0.060375 | EQ690: -0.007672 | ER690: -0.046204 | ES690: 0.168055 | ET690: -0.035842 | EU690: -0.088333 | EV690: -0.028705 | EW690: -0.004111 | EX690: 0.057559 | EY690: 0.065658 | EZ690: -0.078492 | FA690: -0.071479 | FB690: -0.083379 | FC690: 0.049842 | FD690: 0.129295 | FE690: -0.007747 | FF690: 0.050661 | FG690: 0.031632 | FH690: -0.072511 | FI690: 0.083515 | FJ690: -0.04613 | FK690: 0.074418 | FL690: -0.03696 | FM690: 0.005838 | FN690: -0.006542 | FO690: 0.088662 | FP690: 0.016914 | FQ690: -0.000135 | FR690: -0.044578 | FS690: -0.097047
B691: =Deals!B691 -> Pioneer Natural Resources Co | C691: 1 | D691: 0.228867 | E691: 0.07276 | F691: -0.031419 | G691: -0.010661 | H691: 0.071555 | I691: -0.105525 | J691: 0.02958 | K691: 0.126345 | L691: 0.122936 | M691: -0.030164 | N691: 0.023441 | O691: 0.203486 | P691: 0.111883 | Q691: 0.043531 | R691: -0.070232 | S691: 0.227341 | T691: -0.197381 | U691: 0.062175 | V691: 0.068664 | W691: -0.11105 | X691: 0.184178 | Y691: -0.057369 | Z691: -0.032205 | AA691: 0.008582 | AB691: -0.129976 | AC691: 0.046954 | AD691: 0.065168 | AE691: -0.067892 | AF691: 0.038809 | AG691: 0.089246 | AH691: 0.054327 | AI691: -0.027487 | AJ691: 0.041168 | AK691: -0.017406 | AL691: -0.029183 | AM691: 0.022012 | AN691: 0.023322 | AO691: 0.127004 | AP691: 0.025981 | AQ691: 0.040482 | AR691: -0.016716 | AS691: 0.065989 | AT691: 0.0415 | AU691: -0.011409 | AV691: 0.003624 | AW691: 0.08907 | AX691: -0.067957 | AY691: 0.059145 | AZ691: 0.028663 | BA691: -0.021792 | BM691: 0.084093 | BN691: 0.07392 | BO691: 0.047877 | BP691: 0.036587 | BQ691: -0.023503 | BR691: -0.015461 | BS691: 0.012886 | BT691: -0.007545 | BU691: 0.055337 | BV691: -0.045384 | BW691: 0.058993 | BX691: 0.03027 | BY691: 0.000341 | BZ691: 0.039921 | CA691: -0.05704 | CB691: 0.06335 | CC691: -0.121937 | CD691: 0.073352 | CE691: 0.000433 | CF691: -0.087957 | CG691: 0.158705 | CH691: 0.04735 | CI691: -0.041334 | CJ691: 0.035402 | CK691: -0.041951 | CL691: -0.037313 | CM691: 0.024192 | CN691: -0.072248 | CO691: 0.056433 | CP691: 0.052207 | CQ691: -0.02907 | CR691: -0.021396 | CS691: -0.026849 | CT691: 0.086643 | CU691: 0.046596 | CV691: 0.02666 | CW691: 0.049929 | CX691: 0.061457 | CY691: -0.049964 | CZ691: 0.040482 | DA691: -0.016716 | DB691: 0.065989 | DC691: 0.0415 | DD691: -0.011409 | DE691: 0.003624 | DF691: 0.08907 | DG691: -0.067957 | DH691: 0.059145 | DI691: 0.028663 | DJ691: -0.021792 | DV691: 0.0714 | DW691: 0.086885 | DX691: 0.043662 | DY691: 0.039444 | DZ691: -0.026355 | EA691: -0.027717 | EB691: 0.015767 | EC691: -0.011866 | ED691: 0.058004 | EE691: -0.04395 | EF691: 0.063957 | EG691: 0.023504 | EH691: 0.002904 | EI691: 0.038624 | EJ691: -0.058055 | EK691: 0.06776 | EL691: -0.125042 | EM691: 0.065659 | EN691: -0.002083 | EO691: -0.093846 | EP691: 0.114182 | EQ691: 0.060974 | ER691: -0.036693 | ES691: 0.04132 | ET691: -0.044028 | EU691: -0.015674 | EV691: 0.01281 | EW691: -0.072714 | EX691: 0.061257 | EY691: 0.062813 | EZ691: -0.040058 | FA691: -0.023958 | FB691: -0.022377 | FC691: 0.082148 | FD691: 0.068922 | FE691: -0.008177 | FF691: 0.03118 | FG691: 0.070265 | FH691: -0.045928 | FI691: 0.039659 | FJ691: -0.031396 | FK691: 0.074023 | FL691: 0.024512 | FM691: 0.007537 | FN691: -0.010398 | FO691: 0.064241 | FP691: -0.08545 | FQ691: 0.04612 | FR691: 0.010657 | FS691: -0.011338
B692: =Deals!B692 -> ConocoPhillips | C692: 1 | D692: 0.310017 | E692: 0.018458 | F692: -0.034548 | G692: 0.098357 | H692: 0.092573 | I692: -0.072414 | J692: -0.009454 | K692: 0.220421 | L692: 0.105947 | M692: -0.058531 | N692: 0.032083 | O692: 0.227764 | P692: 0.075604 | Q692: 0.057348 | R692: -0.0448 | S692: 0.181114 | T692: -0.194464 | U692: 0.084846 | V692: 0.128092 | W692: -0.05217 | X692: 0.23207 | Y692: -0.016417 | Z692: -0.038944 | AA692: 0.032797 | AB692: -0.14778 | AC692: -0.034253 | AD692: 0.037093 | AE692: -0.029935 | AF692: 0.049446 | AG692: 0.136184 | AH692: 0.01546 | AI692: 0.01151 | AJ692: -0.008347 | AK692: -0.022306 | AL692: 0.004326 | AM692: -0.036185 | AN692: 0.012961 | AO692: 0.130976 | AP692: -0.013042 | AQ692: -0.06655 | AR692: -0.018029 | AS692: -0.027802 | AT692: 0.030306 | AU692: -0.074787 | AV692: 0.040464 | AW692: -0.003834 | AX692: -0.084641 | AY692: -0.003428 | AZ692: 0.01113 | BA692: 0.059203 | BM692: 0.084093 | BN692: 0.07392 | BO692: 0.047877 | BP692: 0.036587 | BQ692: -0.023503 | BR692: -0.015461 | BS692: 0.012886 | BT692: -0.007545 | BU692: 0.055337 | BV692: -0.045384 | BW692: 0.058993 | BX692: 0.03027 | BY692: 0.000341 | BZ692: 0.039921 | CA692: -0.05704 | CB692: 0.06335 | CC692: -0.121937 | CD692: 0.073352 | CE692: 0.000433 | CF692: -0.087957 | CG692: 0.158705 | CH692: 0.04735 | CI692: -0.041334 | CJ692: 0.035402 | CK692: -0.041951 | CL692: -0.037313 | CM692: 0.024192 | CN692: -0.072248 | CO692: 0.056433 | CP692: 0.052207 | CQ692: -0.02907 | CR692: -0.021396 | CS692: -0.026849 | CT692: 0.086643 | CU692: 0.046596 | CV692: 0.02666 | CW692: 0.049929 | CX692: 0.061457 | CY692: -0.049964 | CZ692: 0.040482 | DA692: -0.016716 | DB692: 0.065989 | DC692: 0.0415 | DD692: -0.011409 | DE692: 0.003624 | DF692: 0.08907 | DG692: -0.067957 | DH692: 0.059145 | DI692: 0.028663 | DJ692: -0.021792 | DV692: 0.0714 | DW692: 0.086885 | DX692: 0.043662 | DY692: 0.039444 | DZ692: -0.026355 | EA692: -0.027717 | EB692: 0.015767 | EC692: -0.011866 | ED692: 0.058004 | EE692: -0.04395 | EF692: 0.063957 | EG692: 0.023504 | EH692: 0.002904 | EI692: 0.038624 | EJ692: -0.058055 | EK692: 0.06776 | EL692: -0.125042 | EM692: 0.065659 | EN692: -0.002083 | EO692: -0.093846 | EP692: 0.114182 | EQ692: 0.060974 | ER692: -0.036693 | ES692: 0.04132 | ET692: -0.044028 | EU692: -0.015674 | EV692: 0.01281 | EW692: -0.072714 | EX692: 0.061257 | EY692: 0.062813 | EZ692: -0.040058 | FA692: -0.023958 | FB692: -0.022377 | FC692: 0.082148 | FD692: 0.068922 | FE692: -0.008177 | FF692: 0.03118 | FG692: 0.070265 | FH692: -0.045928 | FI692: 0.039659 | FJ692: -0.031396 | FK692: 0.074023 | FL692: 0.024512 | FM692: 0.007537 | FN692: -0.010398 | FO692: 0.064241 | FP692: -0.08545 | FQ692: 0.04612 | FR692: 0.010657 | FS692: -0.011338
B693: =Deals!B693 -> United States Steel Corp | C693: 1 | D693: -0.064189 | E693: 0.575557 | F693: -0.120749 | G693: 0.127336 | H693: -0.074431 | I693: 0.103333 | J693: 0.010574 | K693: -0.178692 | L693: 0.201183 | M693: -0.141341 | N693: 0.053074 | O693: -0.129777 | P693: 0.315637 | Q693: 0.38699 | R693: -0.192104 | S693: -0.176123 | T693: -0.2856 | U693: 0.320491 | V693: -0.030867 | W693: -0.207696 | X693: 0.12362 | Y693: 0.293713 | Z693: -0.047166 | AA693: 0.137325 | AB693: 0.076869 | AC693: -0.147894 | AD693: -0.123372 | AE693: -0.083479 | AF693: 0.195507 | AG693: 0.019592 | AH693: 0.221176 | AI693: 0.044709 | AJ693: 0.043411 | AK693: 0.060785 | AL693: 0.355153 | AM693: -0.033505 | AN693: 0.007869 | AO693: -0.138572 | AP693: -0.104953 | AQ693: 0.050685 | AR693: -0.014342 | AS693: 0.087037 | AT693: -0.076174 | AU693: -0.068056 | AV693: 0.099632 | AW693: 0.050708 | AX693: -0.166299 | AY693: 0.084142 | AZ693: 0.092809 | BA693: 0.050721 | BM693: 0.138744 | BN693: 0.064522 | BO693: 0.029652 | BP693: 0.065904 | BQ693: -0.058275 | BR693: -0.044843 | BS693: 0.035352 | BT693: 0.020392 | BU693: 0.041177 | BV693: -0.039369 | BW693: 0.044554 | BX693: 0.017767 | BY693: 0.030461 | BZ693: 0.031499 | CA693: -0.053818 | CB693: 0.061138 | CC693: -0.154247 | CD693: 0.094429 | CE693: -0.01378 | CF693: -0.083181 | CG693: 0.148928 | CH693: 0.028522 | CI693: -0.070242 | CJ693: 0.069175 | CK693: -0.013406 | CL693: -0.111544 | CM693: -0.013578 | CN693: -0.046105 | CO693: 0.095738 | CP693: 0.080733 | CQ693: -0.051777 | CR693: -0.071566 | CS693: -0.066334 | CT693: 0.153369 | CU693: 0.170162 | CV693: -0.053363 | CW693: 0.012683 | CX693: 0.066566 | CY693: -0.076944 | CZ693: 0.040525 | DA693: -0.023404 | DB693: 0.115109 | DC693: -0.010361 | DD693: 0.001618 | DE693: 0.001278 | DF693: 0.119435 | DG693: -0.090364 | DH693: 0.039426 | DI693: -0.027996 | DJ693: -0.044976 | DV693: 0.139543 | DW693: 0.06859 | DX693: 0.024907 | DY693: 0.07229 | DZ693: -0.05665 | EA693: -0.043153 | EB693: 0.032365 | EC693: 0.02642 | ED693: 0.039946 | EE693: -0.0394 | EF693: 0.050695 | EG693: 0.019659 | EH693: 0.029888 | EI693: 0.022157 | EJ693: -0.060112 | EK693: 0.047198 | EL693: -0.139103 | EM693: 0.09284 | EN693: -0.015161 | EO693: -0.0827 | EP693: 0.146638 | EQ693: 0.029851 | ER693: -0.071437 | ES693: 0.072824 | ET693: -0.016783 | EU693: -0.11066 | EV693: -0.016908 | EW693: -0.046289 | EX693: 0.101201 | EY693: 0.084514 | EZ693: -0.04928 | FA693: -0.076272 | FB693: -0.069073 | FC693: 0.1522 | FD693: 0.16965 | FE693: -0.047894 | FF693: 0.018751 | FG693: 0.067522 | FH693: -0.07264 | FI693: 0.041068 | FJ693: -0.018427 | FK693: 0.105315 | FL693: -0.015238 | FM693: 0.004384 | FN693: -0.003092 | FO693: 0.123618 | FP693: -0.085159 | FQ693: 0.031429 | FR693: -0.030507 | FS693: -0.043821
B694: =Deals!B694 -> Builders Firstsource, Inc. | C694: 1 | D694: 0.131111 | E694: 0.071767 | F694: 0.049601 | G694: -0.084857 | H694: -0.042209 | I694: 0.043132 | J694: 0.197528 | K694: -0.029086 | L694: 0.126208 | M694: 0.191694 | N694: 0.234303 | O694: -0.206744 | P694: 0.094573 | Q694: -0.13276 | R694: -0.046018 | S694: 0.057171 | T694: -0.174988 | U694: 0.266294 | V694: -0.138088 | W694: 0.005289 | X694: 0.046504 | Y694: 0.036815 | Z694: 0.01486 | AA694: 0.228422 | AB694: 0.063739 | AC694: 0.047181 | AD694: 0.06747 | AE694: 0.223488 | AF694: 0.172919 | AG694: 0.061985 | AH694: 0.004223 | AI694: -0.141685 | AJ694: -0.128283 | AK694: 0.235809 | AL694: 0.244799 | AM694: 0.040673 | AN694: 0.123467 | AO694: 0.068501 | AP694: -0.123376 | AQ694: -0.120501 | AR694: -0.139188 | AS694: 0.209233 | AT694: 0.039613 | AU694: 0.114138 | AV694: -0.115857 | AW694: 0.087923 | AX694: -0.233496 | AY694: 0.170363 | AZ694: -0.169118 | BA694: -0.101086 | BM694: -0.000483 | BN694: -0.047837 | BO694: 0.02869 | BP694: -0.033421 | BQ694: 0.054695 | BR694: -0.02501 | BS694: 0.019022 | BT694: -0.038561 | BU694: 0.046626 | BV694: -0.08576 | BW694: 0.000968 | BX694: -0.142109 | BY694: -0.007716 | BZ694: 0.017833 | CA694: -0.117955 | CB694: -0.053077 | CC694: -0.044319 | CD694: 0.116268 | CE694: -0.038541 | CF694: -0.088512 | CG694: 0.034639 | CH694: 0.031372 | CI694: -0.043533 | CJ694: 0.106176 | CK694: -0.003618 | CL694: -0.008652 | CM694: -0.032515 | CN694: 0.010489 | CO694: 0.068229 | CP694: 0.053331 | CQ694: -0.053394 | CR694: -0.058727 | CS694: -0.073528 | CT694: 0.111124 | CU694: 0.103291 | CV694: -0.042161 | CW694: 0.032515 | CX694: 0.006384 | CY694: -0.06286 | CZ694: 0.046483 | DA694: 0.028059 | DB694: 0.064974 | DC694: -0.001472 | DD694: 0.042635 | DE694: -0.016588 | DF694: 0.102793 | DG694: -0.079478 | DH694: 0.053794 | DI694: -0.056928 | DJ694: -0.07451 | DV694: 0.021424 | DW694: -0.036464 | DX694: 0.030769 | DY694: -0.028421 | DZ694: 0.061708 | EA694: -0.023545 | EB694: 0.015868 | EC694: -0.039964 | ED694: 0.047113 | EE694: -0.084736 | EF694: -0.003415 | EG694: -0.141596 | EH694: -0.016339 | EI694: 0.004296 | EJ694: -0.138311 | EK694: -0.045222 | EL694: -0.046504 | EM694: 0.116767 | EN694: -0.030875 | EO694: -0.092886 | EP694: 0.038196 | EQ694: 0.031364 | ER694: -0.050589 | ES694: 0.12749 | ET694: -0.008377 | EU694: -0.018392 | EV694: -0.031244 | EW694: 0.024876 | EX694: 0.074528 | EY694: 0.058153 | EZ694: -0.055866 | FA694: -0.061774 | FB694: -0.07758 | FC694: 0.128905 | FD694: 0.115622 | FE694: -0.04519 | FF694: 0.029184 | FG694: 0.003445 | FH694: -0.066565 | FI694: 0.07274 | FJ694: 0.026772 | FK694: 0.068904 | FL694: -0.001826 | FM694: 0.034451 | FN694: -0.012354 | FO694: 0.129517 | FP694: -0.079792 | FQ694: 0.048261 | FR694: -0.057773 | FS694: -0.075988
B695: =Deals!B695 -> Primoris Services Corporation | C695: 1 | D695: 0.149974 | E695: -0.008366 | F695: -0.014187 | G695: -0.026638 | H695: -0.07235 | I695: 0.01597 | J695: -0.140468 | K695: -0.044747 | L695: 0.100449 | M695: -0.168089 | N695: 0.072257 | O695: 0.07256 | P695: 0.025272 | Q695: -0.094425 | R695: -0.026868 | S695: 0.047455 | T695: -0.101318 | U695: 0.073529 | V695: -0.132277 | W695: -0.195363 | X695: 0.242462 | Y695: 0.057454 | Z695: 0.030445 | AA695: 0.212397 | AB695: 0.033835 | AC695: -0.101091 | AD695: 0.025953 | AE695: 0.059289 | AF695: 0.139179 | AG695: 0.042337 | AH695: 0.113665 | AI695: -0.072943 | AJ695: -0.081577 | AK695: 0.00998 | AL695: 0.09585 | AM695: -0.012346 | AN695: 0.204573 | AO695: 0.078967 | AP695: 0.094668 | AQ695: 0.175107 | AR695: -0.087838 | AS695: 0.13189 | AT695: -0.000531 | AU695: 0.03012 | AV695: 0.078168 | AW695: 0.336793 | AX695: -0.08637 | AY695: 0.004843 | AZ695: -0.06552 | BA695: -0.198634 | BM695: 0.09566 | BN695: 0.02182 | BO695: 0.023396 | BP695: 0.011055 | BQ695: 0.012853 | BR695: -0.018155 | BS695: 0.013589 | BT695: -0.034063 | BU695: 0.039859 | BV695: 0.0057 | BW695: 0.0589 | BX695: -0.095829 | BY695: 0.005483 | BZ695: 0.017931 | CA695: -0.080424 | CB695: 0.023442 | CC695: -0.072115 | CD695: 0.115972 | CE695: -0.044554 | CF695: -0.114803 | CG695: 0.104466 | CH695: 0.004422 | CI695: -0.070133 | CJ695: 0.1231 | CK695: -0.00465 | CL695: -0.032965 | CM695: -0.032649 | CN695: 0.019558 | CO695: 0.091615 | CP695: 0.061544 | CQ695: -0.036861 | CR695: -0.046311 | CS695: -0.069716 | CT695: 0.086093 | CU695: 0.108974 | CV695: -0.035745 | CW695: 0.06812 | CX695: 0.025352 | CY695: -0.065718 | CZ695: 0.052673 | DA695: -0.021843 | DB695: 0.098444 | DC695: -0.036221 | DD695: 0.009113 | DE695: -0.032464 | DF695: 0.108871 | DG695: -0.087427 | DH695: 0.036021 | DI695: -0.082942 | DJ695: -0.084026 | DV695: 0.092176 | DW695: 0.032457 | DX695: 0.023833 | DY695: 0.016413 | DZ695: 0.003494 | EA695: -0.023492 | EB695: 0.010659 | EC695: -0.035282 | ED695: 0.041156 | EE695: -0.003587 | EF695: 0.054826 | EG695: -0.097752 | EH695: 0.003239 | EI695: 0.007621 | EJ695: -0.080781 | EK695: 0.012501 | EL695: -0.060414 | EM695: 0.113842 | EN695: -0.039008 | EO695: -0.119468 | EP695: 0.105606 | EQ695: 0.003522 | ER695: -0.065539 | ES695: 0.134282 | ET695: -0.02221 | EU695: -0.049024 | EV695: -0.025935 | EW695: 0.015862 | EX695: 0.096287 | EY695: 0.061646 | EZ695: -0.040878 | FA695: -0.054465 | FB695: -0.078234 | FC695: 0.101981 | FD695: 0.125443 | FE695: -0.045067 | FF695: 0.078133 | FG695: 0.031478 | FH695: -0.080992 | FI695: 0.054415 | FJ695: -0.025984 | FK695: 0.100317 | FL695: -0.040457 | FM695: 0.012299 | FN695: -0.028165 | FO695: 0.103669 | FP695: -0.083363 | FQ695: 0.030766 | FR695: -0.088055 | FS695: -0.091066
B696: =Deals!B696 -> V2X, Inc. | C696: 1 | D696: 0.062257 | E696: -0.021245 | F696: -0.020397 | G696: -0.025406 | H696: -0.067229 | I696: -0.048329 | J696: 0.110841 | K696: -0.000596 | L696: -0.036794 | M696: -0.136073 | N696: 0.093929 | O696: 0.005244 | P696: -0.003695 | Q696: -0.217714 | R696: 0.006693 | S696: -0.007756 | T696: -0.065885 | U696: -0.006575 | V696: 0.04272 | W696: 0.02135 | X696: 0.15791 | Y696: -0.01415 | Z696: 0.021777 | AA696: 0.069508 | AB696: 0.050045 | AC696: -0.143412 | AD696: 0.087613 | AE696: -0.045139 | AF696: 0.201455 | AG696: 0.038337 | AH696: -0.022347 | AI696: 0.026834 | AJ696: -0.011421 | AK696: -0.169767 | AL696: 0.095283 | AM696: -0.162575 | AN696: -0.010028 | AO696: 0.213247 | AP696: 0.040034 | AQ696: -0.009675 | AR696: -0.003118 | AS696: 0.086947 | AT696: 0.086706 | AU696: -0.013945 | AV696: 0.102757 | AW696: -0.021916 | AX696: -0.206141 | AY696: 0.089902 | AZ696: -0.099942 | BA696: 0.045396 | BM696: 0.106119 | BN696: 0.018588 | BO696: 0.017138 | BP696: 0.008568 | BQ696: 0.015969 | BR696: -0.039027 | BS696: 0.042598 | BT696: -0.036639 | BU696: 0.012365 | BV696: -0.039551 | BW696: 0.022606 | BX696: -0.101461 | BY696: 0.008251 | BZ696: 0.005535 | CA696: -0.100427 | CB696: -0.009566 | CC696: -0.039563 | CD696: 0.078731 | CE696: 0.007907 | CF696: -0.073666 | CG696: 0.089828 | CH696: 0.005661 | CI696: -0.051979 | CJ696: 0.137687 | CK696: -0.037377 | CL696: -0.070433 | CM696: -0.013914 | CN696: 0.032692 | CO696: 0.055486 | CP696: 0.039656 | CQ696: -0.104754 | CR696: -0.065225 | CS696: -0.07957 | CT696: 0.107235 | CU696: 0.146642 | CV696: -0.03506 | CW696: 0.117399 | CX696: 0.008684 | CY696: -0.07102 | CZ696: 0.045414 | DA696: -0.055948 | DB696: 0.143277 | DC696: -0.025141 | DD696: -0.014124 | DE696: -0.006188 | DF696: 0.094269 | DG696: -0.072125 | DH696: 0.009544 | DI696: -0.068984 | DJ696: -0.089412 | DV696: 0.125412 | DW696: 0.0025 | DX696: -0.001835 | DY696: 0.008948 | DZ696: 0.037328 | EA696: -0.047931 | EB696: 0.038013 | EC696: -0.047 | ED696: -0.012191 | EE696: -0.05156 | EF696: -0.025657 | EG696: -0.103698 | EH696: -0.011993 | EI696: 0.028031 | EJ696: -0.14847 | EK696: -0.024898 | EL696: -0.045521 | EM696: 0.07809 | EN696: 0.017632 | EO696: -0.123383 | EP696: 0.057189 | EQ696: -0.032158 | ER696: -0.087071 | ES696: 0.220874 | ET696: -0.049709 | EU696: -0.092185 | EV696: -0.017177 | EW696: 0.009133 | EX696: 0.037347 | EY696: 0.020107 | EZ696: -0.117804 | FA696: -0.082947 | FB696: -0.087058 | FC696: 0.169079 | FD696: 0.109784 | FE696: -0.050656 | FF696: 0.102283 | FG696: 0.008975 | FH696: -0.109011 | FI696: 0.046828 | FJ696: -0.062047 | FK696: 0.107094 | FL696: -0.023277 | FM696: 0.010234 | FN696: 0.017124 | FO696: 0.050459 | FP696: -0.052297 | FQ696: 0.020697 | FR696: -0.060564 | FS696: -0.111692
B697: =Deals!B697 -> Gan Limited | C697: 1 | D697: 0.081745 | E697: -0.287392 | F697: 0.013187 | G697: -0.061822 | H697: -0.049711 | I697: -0.069343 | J697: 0.117647 | K697: -0.130409 | L697: -0.039677 | M697: -0.322829 | N697: -0.049638 | O697: -0.250272 | P697: -0.03193 | Q697: -0.277361 | R697: -0.226141 | S697: -0.096515 | T697: -0.121662 | U697: 0.22973 | V697: -0.291209 | W697: -0.139535 | X697: -0.094595 | Y697: -0.333333 | Z697: 0.119403 | AA697: 0.52 | AB697: -0.175439 | AC697: -0.31383 | AD697: 0.286822 | AE697: -0.246988 | AF697: 0.312 | AG697: 0.140244 | AH697: -0.245989 | AI697: -0.177305 | AJ697: -0.244397 | AK697: 0.677125 | AL697: 0.07483 | AM697: -0.037975 | AN697: 0 | AO697: -0.164474 | AP697: -0.070866 | AQ697: 0.144068 | AR697: 0.092593 | AS697: 0.074576 | AT697: 0.091483 | AU697: 0.023121 | AV697: 0.011299 | AW697: 0.022346 | AX697: -0.005464 | AY697: 0.038462 | AZ697: -0.063492 | BA697: 0 | BM697: 0.040745 | BN697: -0.048473 | BO697: 0.032353 | BP697: -0.025949 | BQ697: 0.06983 | BR697: -0.075376 | BS697: 0.020545 | BT697: -0.052806 | BU697: 0.024457 | BV697: -0.080613 | BW697: -0.005266 | BX697: -0.163775 | BY697: -0.001611 | BZ697: 0.012199 | CA697: -0.180685 | CB697: -0.032766 | CC697: -0.019338 | CD697: 0.128546 | CE697: 0.036743 | CF697: -0.088022 | CG697: 0.076143 | CH697: -0.002315 | CI697: -0.050589 | CJ697: 0.141421 | CK697: -0.040665 | CL697: -0.034632 | CM697: -0.027967 | CN697: 0.012513 | CO697: 0.070349 | CP697: 0.041532 | CQ697: -0.071954 | CR697: -0.091371 | CS697: -0.101457 | CT697: 0.108746 | CU697: 0.122171 | CV697: -0.039346 | CW697: 0.094637 | CX697: 0.003944 | CY697: -0.069152 | CZ697: 0.019278 | DA697: -0.016837 | DB697: 0.075097 | DC697: 0.006764 | DD697: 0.000931 | DE697: -0.008068 | DF697: 0.14058 | DG697: -0.041389 | DH697: 0.005532 | DI697: -0.084494 | DJ697: -0.082801 | DV697: 0.051624 | DW697: -0.046095 | DX697: 0.028573 | DY697: -0.026132 | DZ697: 0.06635 | EA697: -0.076813 | EB697: 0.018217 | EC697: -0.053317 | ED697: 0.021146 | EE697: -0.091985 | EF697: -0.014805 | EG697: -0.173369 | EH697: -0.012789 | EI697: 0.018464 | EJ697: -0.198696 | EK697: -0.057167 | EL697: -0.02625 | EM697: 0.129928 | EN697: 0.030138 | EO697: -0.081445 | EP697: 0.087294 | EQ697: -0.006501 | ER697: -0.051629 | ES697: 0.164361 | ET697: -0.049102 | EU697: -0.042333 | EV697: -0.043651 | EW697: 0.027983 | EX697: 0.075292 | EY697: 0.041174 | EZ697: -0.071456 | FA697: -0.098155 | FB697: -0.110132 | FC697: 0.107279 | FD697: 0.142226 | FE697: -0.046726 | FF697: 0.099012 | FG697: -0.006566 | FH697: -0.088553 | FI697: 0.04379 | FJ697: -0.01381 | FK697: 0.076992 | FL697: -0.007169 | FM697: -0.005011 | FN697: -0.001446 | FO697: 0.13118 | FP697: -0.044324 | FQ697: 0.027517 | FR697: -0.087576 | FS697: -0.080425
B698: =Deals!B698 -> Upbound Group, Inc. | C698: 1 | D698: -0.001731 | E698: 0.003469 | F698: 0.074023 | G698: -0.136386 | H698: 0.078199 | I698: 0.102412 | J698: -0.103995 | K698: -0.052482 | L698: -0.170672 | M698: 0.095314 | N698: -0.122606 | O698: -0.325979 | P698: -0.11334 | Q698: -0.02898 | R698: 0.141791 | S698: -0.281409 | T698: 0.209769 | U698: 0.098173 | V698: -0.322368 | W698: 0.210166 | X698: 0.155396 | Y698: -0.049813 | Z698: 0.192461 | AA698: -0.001488 | AB698: -0.087151 | AC698: 0.101591 | AD698: 0.121905 | AE698: 0.052156 | AF698: 0.112432 | AG698: -0.115796 | AH698: -0.03821 | AI698: -0.11511 | AJ698: 0.116654 | AK698: 0.180069 | AL698: -0.022667 | AM698: 0.016867 | AN698: 0.04295 | AO698: -0.119284 | AP698: 0.058368 | AQ698: -0.053321 | AR698: 0.22899 | AS698: -0.117413 | AT698: -0.039339 | AU698: -0.074398 | AV698: 0.176129 | AW698: -0.140448 | AX698: 0.005828 | AY698: -0.119973 | AZ698: -0.072037 | BM698: -0.047837 | BN698: 0.02869 | BO698: -0.033421 | BP698: 0.054695 | BQ698: -0.02501 | BR698: 0.019022 | BS698: -0.038561 | BT698: 0.046626 | BU698: -0.08576 | BV698: 0.000968 | BW698: -0.142109 | BX698: -0.007716 | BY698: 0.017833 | BZ698: -0.117955 | CA698: -0.053077 | CB698: -0.044319 | CC698: 0.116268 | CD698: -0.038541 | CE698: -0.088512 | CF698: 0.034639 | CG698: 0.031372 | CH698: -0.043533 | CI698: 0.106176 | CJ698: -0.003618 | CK698: -0.008652 | CL698: -0.032515 | CM698: 0.010489 | CN698: 0.068229 | CO698: 0.053331 | CP698: -0.053394 | CQ698: -0.058727 | CR698: -0.073528 | CS698: 0.111124 | CT698: 0.103291 | CU698: -0.042161 | CV698: 0.032515 | CW698: 0.006384 | CX698: -0.06286 | CY698: 0.046483 | CZ698: 0.028059 | DA698: 0.064974 | DB698: -0.001472 | DC698: 0.042635 | DD698: -0.016588 | DE698: 0.102793 | DF698: -0.079478 | DG698: 0.053794 | DH698: -0.056928 | DI698: -0.07451 | DV698: -0.036464 | DW698: 0.030769 | DX698: -0.028421 | DY698: 0.061708 | DZ698: -0.023545 | EA698: 0.015868 | EB698: -0.039964 | EC698: 0.047113 | ED698: -0.084736 | EE698: -0.003415 | EF698: -0.141596 | EG698: -0.016339 | EH698: 0.004296 | EI698: -0.138311 | EJ698: -0.045222 | EK698: -0.046504 | EL698: 0.116767 | EM698: -0.030875 | EN698: -0.092886 | EO698: 0.038196 | EP698: 0.031364 | EQ698: -0.050589 | ER698: 0.12749 | ES698: -0.008377 | ET698: -0.018392 | EU698: -0.031244 | EV698: 0.024876 | EW698: 0.074528 | EX698: 0.058153 | EY698: -0.055866 | EZ698: -0.061774 | FA698: -0.07758 | FB698: 0.128905 | FC698: 0.115622 | FD698: -0.04519 | FE698: 0.029184 | FF698: 0.003445 | FG698: -0.066565 | FH698: 0.07274 | FI698: 0.026772 | FJ698: 0.068904 | FK698: -0.001826 | FL698: 0.034451 | FM698: -0.012354 | FN698: 0.129517 | FO698: -0.079792 | FP698: 0.048261 | FQ698: -0.057773 | FR698: -0.075988
B699: =Deals!B699 -> Whole Earth Brands, Inc. | C699: 1 | D699: 0.016368 | E699: 0.035276 | F699: -0.021481 | G699: 0.097653 | H699: -0.113103 | I699: -0.024883 | J699: -0.078947 | K699: 0.050216 | L699: -0.129431 | M699: 0.017045 | N699: -0.117318 | O699: 0.001055 | P699: -0.245522 | Q699: -0.034916 | R699: -0.01013 | S699: -0.093567 | T699: -0.132258 | U699: -0.050186 | V699: -0.248532 | W699: -0.101562 | X699: 0.255072 | Y699: -0.060046 | Z699: -0.068796 | AA699: -0.092348 | AB699: -0.255814 | AC699: -0.0625 | AD699: 0.204167 | AE699: 0.391003 | AF699: 0.007463 | AG699: -0.059259 | AH699: -0.055118 | AI699: -0.016667 | AJ699: -0.081921 | AK699: 0.049231 | AL699: 0.167155 | AM699: 0.201005 | AN699: 0.01046 | AO699: -0.00207 | AP699: -0.002075 | AQ699: 0.010395 | AR699: 0.145137 | AS699: -0.021203 | AT699: -0.002295 | AU699: 0.006632 | AV699: 0.107518 | AW699: -0.045938 | AX699: -0.000909 | AY699: -0.023508 | AZ699: -0.066419 | BM699: 0.117823 | BN699: -0.010157 | BO699: 0.107327 | BP699: 0.037629 | BQ699: -0.015695 | BR699: 0.03808 | BS699: 0.000428 | BT699: 0.041354 | BU699: -0.033466 | BV699: 0.034385 | BW699: -0.019091 | BX699: 0.029208 | BY699: 0.024942 | BZ699: -0.040798 | CA699: 0.029279 | CB699: -0.099199 | CC699: 0.058975 | CD699: -0.003345 | CE699: -0.092831 | CF699: 0.099183 | CG699: 0.015688 | CH699: -0.034399 | CI699: 0.071003 | CJ699: -0.010212 | CK699: -0.096968 | CL699: -0.041692 | CM699: -0.018759 | CN699: 0.071504 | CO699: 0.104731 | CP699: -0.076887 | CQ699: -0.059078 | CR699: -0.078456 | CS699: 0.07131 | CT699: 0.15025 | CU699: -0.035734 | CV699: 0.043465 | CW699: 0.047526 | CX699: -0.075752 | CY699: 0.043204 | CZ699: -0.025702 | DA699: 0.145137 | DB699: -0.021203 | DC699: -0.002295 | DD699: 0.006632 | DE699: 0.107518 | DF699: -0.045938 | DG699: -0.000909 | DH699: -0.023508 | DI699: -0.066419 | DV699: 0.046507 | DW699: -0.004233 | DX699: 0.062602 | DY699: 0.061298 | DZ699: -0.016461 | EA699: 0.0263 | EB699: 0.001292 | EC699: 0.028219 | ED699: -0.035104 | EE699: 0.015844 | EF699: -0.018371 | EG699: 0.016085 | EH699: 0.017487 | EI699: -0.049066 | EJ699: -0.002746 | EK699: -0.076071 | EL699: 0.038029 | EM699: 0.00642 | EN699: -0.118368 | EO699: 0.060375 | EP699: -0.007672 | EQ699: -0.046204 | ER699: 0.168055 | ES699: -0.035842 | ET699: -0.088333 | EU699: -0.028705 | EV699: -0.004111 | EW699: 0.057559 | EX699: 0.065658 | EY699: -0.078492 | EZ699: -0.071479 | FA699: -0.083379 | FB699: 0.049842 | FC699: 0.129295 | FD699: -0.007747 | FE699: 0.050661 | FF699: 0.031632 | FG699: -0.072511 | FH699: 0.083515 | FI699: -0.04613 | FJ699: 0.074418 | FK699: -0.03696 | FL699: 0.005838 | FM699: -0.006542 | FN699: 0.088662 | FO699: 0.016914 | FP699: -0.000135 | FQ699: -0.044578 | FR699: -0.097047
B700: =Deals!B700 -> Desktop Metal, Inc. | C700: 1 | D700: -0.257228 | E700: -0.081879 | F700: -0.034357 | G700: -0.129447 | H700: -0.217391 | I700: -0.077778 | J700: -0.136145 | K700: -0.025105 | L700: -0.067239 | M700: -0.240798 | N700: -0.173737 | O700: 0.017115 | P700: 0.139423 | Q700: -0.259494 | R700: -0.415954 | S700: 0.073171 | T700: -0.031818 | U700: 0.492958 | V700: -0.185535 | W700: -0.023166 | X700: -0.189723 | Y700: -0.336585 | Z700: 0.235294 | AA700: -0.095238 | AB700: 0.513158 | AC700: -0.043478 | AD700: -0.154545 | AE700: -0.048387 | AF700: 0.028249 | AG700: -0.010989 | AH700: -0.188889 | AI700: -0.406575 | AJ700: -0.192405 | AK700: 0.073317 | AL700: -0.136218 | AM700: -0.057037 | AN700: 0.438614 | AO700: -0.110909 | AP700: -0.279525 | AQ700: -0.267341 | AR700: 0.140436 | AS700: -0.067941 | AT700: 0.063781 | AU700: 0.051392 | AV700: -0.152749 | AW700: -0.4375 | AX700: -0.029915 | AY700: 0.004405 | AZ700: 1.153509 | BM700: -0.047837 | BN700: 0.02869 | BO700: -0.033421 | BP700: 0.054695 | BQ700: -0.02501 | BR700: 0.019022 | BS700: -0.038561 | BT700: 0.046626 | BU700: -0.08576 | BV700: 0.000968 | BW700: -0.142109 | BX700: -0.007716 | BY700: 0.017833 | BZ700: -0.117955 | CA700: -0.053077 | CB700: -0.044319 | CC700: 0.116268 | CD700: -0.038541 | CE700: -0.088512 | CF700: 0.034639 | CG700: 0.031372 | CH700: -0.043533 | CI700: 0.106176 | CJ700: -0.003618 | CK700: -0.008652 | CL700: -0.032515 | CM700: 0.010489 | CN700: 0.068229 | CO700: 0.053331 | CP700: -0.053394 | CQ700: -0.058727 | CR700: -0.073528 | CS700: 0.111124 | CT700: 0.103291 | CU700: -0.042161 | CV700: 0.032515 | CW700: 0.006384 | CX700: -0.06286 | CY700: 0.046483 | CZ700: 0.028059 | DA700: 0.064974 | DB700: -0.001472 | DC700: 0.042635 | DD700: -0.016588 | DE700: 0.102793 | DF700: -0.079478 | DG700: 0.053794 | DH700: -0.056928 | DI700: -0.07451 | DV700: -0.036464 | DW700: 0.030769 | DX700: -0.028421 | DY700: 0.061708 | DZ700: -0.023545 | EA700: 0.015868 | EB700: -0.039964 | EC700: 0.047113 | ED700: -0.084736 | EE700: -0.003415 | EF700: -0.141596 | EG700: -0.016339 | EH700: 0.004296 | EI700: -0.138311 | EJ700: -0.045222 | EK700: -0.046504 | EL700: 0.116767 | EM700: -0.030875 | EN700: -0.092886 | EO700: 0.038196 | EP700: 0.031364 | EQ700: -0.050589 | ER700: 0.12749 | ES700: -0.008377 | ET700: -0.018392 | EU700: -0.031244 | EV700: 0.024876 | EW700: 0.074528 | EX700: 0.058153 | EY700: -0.055866 | EZ700: -0.061774 | FA700: -0.07758 | FB700: 0.128905 | FC700: 0.115622 | FD700: -0.04519 | FE700: 0.029184 | FF700: 0.003445 | FG700: -0.066565 | FH700: 0.07274 | FI700: 0.026772 | FJ700: 0.068904 | FK700: -0.001826 | FL700: 0.034451 | FM700: -0.012354 | FN700: 0.129517 | FO700: -0.079792 | FP700: 0.048261 | FQ700: -0.057773 | FR700: -0.075988
B701: =Deals!B701 -> Jacobs Engineering Group Inc. | C701: 1 | D701: 0.033573 | E701: 0.063393 | F701: -0.060952 | G701: 0.013716 | H701: -0.002144 | I701: -0.018005 | J701: 0.059534 | K701: 0.01524 | L701: -0.023359 | M701: -0.065 | N701: -0.055154 | O701: 0.120407 | P701: 0.00537 | Q701: 0.011115 | R701: -0.092512 | S701: 0.079997 | T701: -0.092644 | U701: -0.129154 | V701: 0.062033 | W701: 0.098247 | X701: -0.05113 | Y701: 0.028983 | Z701: -0.03278 | AA701: -0.016653 | AB701: -0.017445 | AC701: -0.050754 | AD701: 0.084763 | AE701: 0.054841 | AF701: 0.075034 | AG701: 0.012461 | AH701: -0.023443 | AI701: -0.045911 | AJ701: 0.020601 | AK701: 0.03829 | AL701: 0.08815 | AM701: 0.048278 | AN701: -0.06635 | AO701: -0.029193 | AP701: 0.002655 | AQ701: 0.047527 | AR701: 0.030953 | AS701: -0.132423 | AT701: 0.07395 | AU701: 0.004624 | AV701: -0.053884 | AW701: 0.04872 | AX701: -0.085777 | AY701: -0.056358 | BM701: 0.058012 | BN701: 0.022358 | BO701: -0.012513 | BP701: -0.012862 | BQ701: 0.016428 | BR701: -0.021588 | BS701: 0.053756 | BT701: -0.030463 | BU701: 0.054007 | BV701: -0.041405 | BW701: 0.006859 | BX701: 0.035932 | BY701: -0.048852 | BZ701: 0.044371 | CA701: -0.113068 | CB701: 0.068956 | CC701: -0.039545 | CD701: -0.111256 | CE701: 0.1186 | CF701: 0.053685 | CG701: -0.047152 | CH701: 0.08114 | CI701: -0.029058 | CJ701: -0.025019 | CK701: -0.00394 | CL701: -0.040008 | CM701: 0.091469 | CN701: 0.049151 | CO701: -0.027942 | CP701: -0.067057 | CQ701: -0.071421 | CR701: 0.090999 | CS701: 0.090679 | CT701: -0.014938 | CU701: 0.036154 | CV701: 0.050535 | CW701: -0.060649 | CX701: 0.025392 | CY701: -0.023903 | CZ701: 0.066677 | DA701: 0.015802 | DB701: 0.012306 | DC701: -0.014521 | DD701: 0.056845 | DE701: -0.065352 | DF701: 0.050171 | DG701: -0.022094 | DH701: -0.035011 | DV701: 0.05332 | DW701: 0.016144 | DX701: -0.008976 | DY701: -0.011142 | DZ701: 0.012908 | EA701: -0.016159 | EB701: 0.052565 | EC701: -0.036406 | ED701: 0.050779 | EE701: -0.041859 | EF701: 0.00545 | EG701: 0.028508 | EH701: -0.054502 | EI701: 0.038173 | EJ701: -0.110414 | EK701: 0.073636 | EL701: -0.035969 | EM701: -0.110605 | EN701: 0.118592 | EO701: 0.057764 | EP701: -0.048956 | EQ701: 0.092385 | ER701: -0.027413 | ES701: -0.02707 | ET701: -0.006752 | EU701: -0.040006 | EV701: 0.08934 | EW701: 0.052942 | EX701: -0.029106 | EY701: -0.068619 | EZ701: -0.076182 | FA701: 0.092525 | FB701: 0.095987 | FC701: -0.019535 | FD701: 0.030822 | FE701: 0.047036 | FF701: -0.066117 | FG701: 0.037484 | FH701: -0.029571 | FI701: 0.068915 | FJ701: 0.015475 | FK701: 0.013876 | FL701: -0.011102 | FM701: 0.061639 | FN701: -0.064144 | FO701: 0.049973 | FP701: -0.030876 | FQ701: -0.033423
B702: =Deals!B702 -> Callaway Golf Co | C702: 1 | D702: 0.082243 | E702: 0.275302 | F702: -0.086403 | G702: -0.060777 | H702: -0.114268 | I702: -0.015324 | J702: -0.020992 | K702: -0.003327 | L702: 0.017804 | M702: -0.130466 | N702: 0.036882 | O702: -0.053355 | P702: -0.063194 | Q702: -0.010483 | R702: -0.060341 | S702: 0.125 | T702: -0.03573 | U702: -0.129688 | V702: -0.028037 | W702: 0.119124 | X702: -0.057279 | Y702: 0.24 | Z702: -0.053491 | AA702: -0.067299 | AB702: 0.025439 | AC702: -0.230041 | AD702: 0.162859 | AE702: 0.006045 | AF702: -0.12669 | AG702: -0.206422 | AH702: -0.117052 | AI702: 0.003273 | AJ702: 0.169657 | AK702: -0.08159 | AL702: 0.081245 | AM702: 0.135534 | AN702: -0.009276 | AO702: -0.023096 | AP702: -0.022364 | AQ702: 0.078431 | AR702: -0.390303 | AS702: 0.091451 | AT702: -0.115665 | AU702: -0.132853 | AV702: -0.066508 | AW702: 0 | AX702: -0.169211 | AY702: 0.009188 | BM702: 0.015677 | BN702: 0.002446 | BO702: 0.035313 | BP702: -0.028278 | BQ702: 0.024312 | BR702: -0.041121 | BS702: 0.023534 | BT702: -0.034555 | BU702: 0.001539 | BV702: -0.116597 | BW702: 0.020508 | BX702: 0.022185 | BY702: -0.119564 | BZ702: -0.028738 | CA702: -0.063921 | CB702: 0.135102 | CC702: -0.007929 | CD702: -0.088004 | CE702: 0.092762 | CF702: -0.018141 | CG702: -0.073757 | CH702: 0.160132 | CI702: -0.029084 | CJ702: -0.030294 | CK702: 0.000974 | CL702: 0.034374 | CM702: 0.071376 | CN702: 0.055658 | CO702: -0.070227 | CP702: -0.055895 | CQ702: -0.076043 | CR702: 0.090818 | CS702: 0.141331 | CT702: -0.03884 | CU702: 0.062772 | CV702: 0.020685 | CW702: -0.08132 | CX702: 0.03247 | CY702: -0.016085 | CZ702: 0.096359 | DA702: 0.002008 | DB702: 0.012156 | DC702: -0.00881 | DD702: 0.132864 | DE702: -0.092084 | DF702: 0.027376 | DG702: -0.087184 | DH702: -0.07152 | DV702: 0.008333 | DW702: -0.008533 | DX702: 0.032572 | DY702: -0.030216 | DZ702: 0.020798 | EA702: -0.040113 | EB702: 0.024885 | EC702: -0.052054 | ED702: 0.002106 | EE702: -0.122474 | EF702: 0.004163 | EG702: 0.029007 | EH702: -0.150847 | EI702: -0.038851 | EJ702: -0.043457 | EK702: 0.133239 | EL702: 0.00337 | EM702: -0.088268 | EN702: 0.09263 | EO702: -0.008961 | EP702: -0.073196 | EQ702: 0.179925 | ER702: -0.037455 | ES702: -0.045087 | ET702: -0.007067 | EU702: 0.026671 | EV702: 0.081708 | EW702: 0.048745 | EX702: -0.067184 | EY702: -0.056578 | EZ702: -0.086289 | FA702: 0.096397 | FB702: 0.143956 | FC702: -0.055801 | FD702: 0.059786 | FE702: 0.003677 | FF702: -0.079926 | FG702: 0.024106 | FH702: -0.027662 | FI702: 0.104449 | FJ702: -0.005668 | FK702: 0.005186 | FL702: -0.005121 | FM702: 0.118651 | FN702: -0.083389 | FO702: 0.025358 | FP702: -0.082682 | FQ702: -0.0774
